Workbook

Sheet Picks for Review (Sep 26)
A1: Series Name | B1: Author | C1: Sub-Genre | D1: Book Series (GoodReads URL) | E1: GoodReads No. of Ratings | F1: Goodreads Book 1 Ratings | G1: Total Primary Books | H1: Total primary Books Page Count | I1: Imprint / Publisher - Book | J1: Agencies | K1: Imprint / Publisher - Audiobook | L1: Crawling POC | M1: Crawling Date | N1: Links addition POC | O1: Links Date | P1: Book 1 Link | Q1: Books (1 - 5) Links | R1: Antigravity QC | S1: Batch Number
A2: The Twilight Saga | B2: Stephenie Meyer | C2: Gothic Dark Romantasy | D2: https://www.goodreads.com/series/45363-the-twilight-saga | E2: 7485263 | F2: 3.68 | G2: 9 | H2: 4817 | I2: ) Format: Audible Audiobook | J2: New Keywords - Amazon | L2: Sakshi Saxena | P2: 1_Twilight_-_Stephenie_Meyer.docx | Q2: The Twilight Saga | S2: Batch 2 Review
A3: Green Creek | B3: Kelly Bennett | C3: Paranormal Romance | D3: https://www.goodreads.com/series/206510-green-creek | E3: 118376 | F3: 4.18 | G3: 4 | H3: 118376 | I3: Indie / Self-Published | J3: Metamorphosis Literary Agency | L3: Vanshika V | M3: 46283 | N3: Vanshika V | P3: https://docs.google.com/document/d/102Co9URvI7NHwz65ofheImstJmx3_C2w/edit?usp=drive_link&ouid=101023058405307348147&rtpof=true&sd=true | Q3: https://drive.google.com/drive/folders/15WyC66FwRnei2POYs01P4BHDFr_5dLPr?usp=drive_link | S3: Batch 1 Review
A4: Air Awakens | B4: Elise Fender Burns | C4: High Fantasy Court Adventure | D4: https://www.goodreads.com/series/155275-air-awakens | E4: 63472 | F4: 3.97 | G4: 5 | H4: 63472 | I4: Indie / Self-Published | J4: Metamorphosis Literary Agency | L4: Vanshika V | M4: 46283 | N4: Vanshika V | P4: https://docs.google.com/document/d/1a42Nqridsbx5sLJgnfsjtz_tM0HKN4Lm/edit?usp=drive_link&ouid=101023058405307348147&rtpof=true&sd=true | Q4: https://drive.google.com/drive/folders/1Z8o5jSlW3Bq8CpAyuYG0Opo3jnRKwAqb?usp=drive_link | S4: Batch 1 Review
A5: Warrior Security | B5: Brittany Cooper | C5: High-Stakes Games & Deadly Trials | D5: https://www.goodreads.com/series/426999-warrior-security | E5: 2310 | F5: 4.47 | G5: 5 | H5: 2310 | I5: Indie / Self-Published | J5: Metamorphosis Literary Agency | L5: Vanshika V | M5: 46283 | N5: Vanshika V | P5: https://docs.google.com/document/d/1uGe-oUialP2el1Y3fhEazOkMe1ixL1Sf/edit?usp=drive_link&ouid=101023058405307348147&rtpof=true&sd=true | Q5: https://drive.google.com/drive/folders/1GRRhk2RsoERxTDphHtU0G_6kKP5UTafA?usp=drive_link | S5: Batch 1 Review
A6: The Shadowhunter Chronicles | B6: Claire Karwowski | C6: Urban / Contemporary Fantasy Romance | D6: https://www.goodreads.com/series/242806-the-shadowhunter-chronicles | E6: 2207639 | F6: 4.06 | G6: 26 | H6: 12245 | I6: Indie / Self-Published | J6: Jane Rotrosen Agency | L6: Sakshi Saxena | P6: 1_City_of_Bones_-_Cassandra_Clare.docx | Q6: The Shadowhunter Chronicles | S6: Batch 2 Review
A7: The Queen's Alpha Series | B7: Teresa Gabelman | C7: High Fantasy Court Adventure | D7: https://www.goodreads.com/series/264896-the-queen-s-alpha | E7: 1808109 | F7: 3.9 | G7: 12 | H7: 2518 | I7: Indie / Self-Published | J7: New Keywords - Amazon | L7: Sakshi Saxena | P7: 1_Eternal_-_W_J_May.docx | Q7: The Queen S Alpha | S7: Batch 2 Review
A8: Summer Court | B8: Gena Showalter | C8: High Fantasy Court Adventure | D8: https://www.goodreads.com/series/348188-summer-court | E8: 1807664 | F8: 3.31 | G8: 8 | H8: 2039 | I8: Indie / Self-Published | J8: New Keywords - Amazon | L8: Sakshi Saxena | P8: 1_Faes_Song_-_Helen_Walton.docx | Q8: Summer Court | S8: Batch 2 Review
A9: Fire And Fang | B9: Lindsay Flanagan | C9: High Fantasy Court Adventure | D9: https://www.goodreads.com/series/428113-fire-and-fang | E9: 3087 | F9: 4.07 | G9: 5 | H9: 3087 | I9: Indie / Self-Published | J9: Metamorphosis Literary Agency | L9: Vanshika V | M9: 46283 | N9: Vanshika V | P9: https://docs.google.com/document/d/1pDpQYoA6iNGrpTRf35YkQ72AulEuFaRE/edit?usp=drive_link&ouid=101023058405307348147&rtpof=true&sd=true | Q9: https://drive.google.com/drive/folders/11Ac4Iz28Vn5AQpHld3YGDFg2606IfaR6?usp=drive_link | S9: Batch 1 Review
A10: The Coven: Elemental Magic | B10: Chandelle LaVaun | C10: Paranormal Romance ( Done ) | D10: https://www.goodreads.com/series/234103-the-coven-elemental-magic | E10: 1276274 | F10: 4.18 | G10: 7 | H10: 2948 | I10: Wanderlost Publishing | J10: New Keywords - Amazon | L10: Sakshi Saxena | P10: 1_The_Lost_Witch_-_Chandelle_LaVaun.docx | Q10: The Coven Elemental Magic | S10: Batch 2 Review
A11: Shatter Me | B11: Tahereh Mafi | C11: Paranormal Romance | D11: https://www.goodreads.com/series/65730-shatter-me | E11: 1260128 | F11: 3.84 | G11: 12 | H11: 2481 | I11: Storytide | K11: Storytide | L11: Noel Regis | M11: 46282 | P11: 1_Shatter Me.docx | Q11: 11_Shatter Me | S11: Batch 1 Review
A12: This Woven Kingdom | B12: Tiffany W. Killoren | C12: Mythology, Legend & Fairy Tale Retelling | D12: https://www.goodreads.com/series/319224-this-woven-kingdom | E12: 119741 | F12: 4.28 | G12: 5 | H12: 119741 | I12: Indie / Self-Published | J12: Metamorphosis Literary Agency | L12: Vanshika V | M12: 46283 | N12: Vanshika V | P12: https://docs.google.com/document/d/1wxQ6oyhK93uhZ1Vu_KLr2C3GVXtcOz_k/edit?usp=drive_link&ouid=101023058405307348147&rtpof=true&sd=true | Q12: https://drive.google.com/drive/folders/11ZUWyaB1f9-L9YCg_WmD7oXTFWU3wwEU?usp=drive_link | S12: Batch 1 Review
A13: The Inheritance Games | B13: Angela Crocker | C13: High-Stakes Games & Deadly Trials | D13: https://www.goodreads.com/series/53144-angel | E13: 1142005 | F13: 3.85 | G13: 3 | H13: 1723 | I13: Indie / Self-Published | J13: Metamorphosis Literary Agency | L13: Sakshi Saxena | P13: 1_Angel_Burn_-_L_A_Weatherly.docx | Q13: Angel Series | S13: Batch 2 Review
A14: Tiffany Black Mysteries | B14: Tiffany W. Killoren | C14: Cozy / Cottagecore Romantasy | D14: https://www.goodreads.com/series/124119-tiffany-black-mysteries | E14: 10545 | F14: 3.71 | G14: 37 | H14: 10545 | I14: Indie / Self-Published | J14: Metamorphosis Literary Agency | L14: Vanshika V | M14: 46283 | N14: Vanshika V | P14: https://docs.google.com/document/d/1ALVv-mpE7V69_4xV4EZZQBBOL08me4xH/edit?usp=drive_link&ouid=101023058405307348147&rtpof=true&sd=true | Q14: https://drive.google.com/drive/folders/1mH43uDPXFbMxk1g9WCgnxqnt-IJgjqmS?usp=drive_link | S14: Batch 1 Review
A15: Arcane Society | B15: Mike Krentz | C15: Paranormal Romance | D15: https://www.goodreads.com/series/57569-arcane-society | E15: 16119 | F15: 3.91 | G15: 12 | H15: 16119 | I15: Indie / Self-Published | J15: Metamorphosis Literary Agency | L15: Vanshika V | M15: 46283 | N15: Vanshika V | P15: https://docs.google.com/document/d/1WKhrsKagyScv3YdVnxwWaAPu3H37_vc6/edit?usp=drive_link&ouid=101023058405307348147&rtpof=true&sd=true | Q15: https://drive.google.com/drive/folders/1BCNS4Cq-JEWdGzXyBnoiW81CzBAbnWoS?usp=drive_link | S15: Batch 1 Review
A16: Fae & Alchemy | B16: Callie Hart | C16: High Fantasy Court Adventure | D16: https://www.goodreads.com/series/392242-fae-alchemy | E16: 987885 | F16: 4.3 | G16: 4 | H16: 3216 | I16: Podium Audio | J16: New Keywords - Amazon | L16: Noel Regis | M16: 46282 | P16: 1_Quicksilver_-_Callie_Hart.docx | Q16: Fae & Alchemy Series | S16: Batch 1 Review
A17: Red Rising | B17: Pierce Brown | C17: Paranormal Romance | D17: https://www.goodreads.com/series/117100-red-rising-saga | E17: 853673 | F17: 4.27 | G17: 18 | H17: 8359 | I17: Recorded Books | K17: Recorded Books | L17: Noel Regis | M17: 46282 | N17: Sakshi Saxena | O17: 46286 | P17: 1_Red Rising.docx | Q17: 17_Red Rising Saga by Pierce Brown | S17: Batch 1 Review
A18: The Witchlands | B18: Kathy MacMillan | C18: High Fantasy Court Adventure | D18: https://www.goodreads.com/series/124183-the-witchlands | E18: 53820 | F18: 3.84 | G18: 5 | H18: 53820 | I18: Indie / Self-Published | J18: Metamorphosis Literary Agency | L18: Vanshika V | M18: 46283 | N18: Vanshika V | P18: https://docs.google.com/document/d/1adWWq7op5vLWMCttQ1VPvc5T4dOFtTJJ/edit?usp=drive_link&ouid=101023058405307348147&rtpof=true&sd=true | Q18: https://drive.google.com/drive/folders/18PRRzh_bCalyoHm28jlcBL3s1HXZsokb?usp=drive_link | S18: Batch 1 Review
A19: Dragon Centurion | B19: Sarah Hawke | C19: High-Stakes Games & Deadly Trials (Done) | D19: https://www.goodreads.com/series/422708-dragon-centurion | E19: 687612 | F19: 4.46 | G19: 5 | H19: 1671 | I19: Indie / Self-Published | J19: New Keywords - Amazon | L19: Sakshi Saxena | P19: 1_Dragon_Centurion_Resurgence_-_Sarah_Hawke.docx | Q19: Dragon Centurion | S19: Batch 2 Review
A20: Sookie Stackhouse | B20: Charlaine Harris | C20: High Fantasy Court Adventure | D20: https://www.goodreads.com/series/42636-sookie-stackhouse | E20: 565155 | F20: 3.97 | G20: 13 | H20: 4112 | I20: ) Format: Audible Audiobook | J20: New Keywords - Amazon | L20: Sakshi Saxena | P20: 1_Dead_Until_Dark_-_Charlaine_Harris.docx | Q20: Sookie Stackhouse | S20: Batch 2 Review
A21: Chaos | B21: Fae Quin | C21: High Fantasy Court Adventure | D21: https://www.goodreads.com/series/127680-chaos | E21: 534728 | F21: 4.11 | G21: 7 | H21: 1938 | I21: Indie / Self-Published | J21: New Keywords - Amazon | L21: Sakshi Saxena | P21: 1_Soul (Farrell Claire).docx | Q21: Chaos | S21: Batch 2 Review
A22: Assistant and the Villain | B22: Hannah Nicole Maehrer | C22: Gothic Dark Romantasy | D22: https://www.goodreads.com/series/377072-assistant-to-the-villain | E22: 392049 | F22: 3.93 | G22: 4 | H22: 1446 | I22: Entangled: Red Tower Books | J22: Self-Represented / N/A | K22: Indie / Self-Published | L22: Sakshi Saxena | P22: 1_Assistant_to_the_villain_-_Hannah_Nicole_Maehrer.docx | Q22: Assistant To The Villain | S22: Batch 2 Review
A23: The Captive | B23: Erica Spiller | C23: Paranormal Romance | D23: https://www.goodreads.com/series/86676-the-captive | E23: 21690 | F23: 4.02 | G23: 8 | H23: 21690 | I23: Indie / Self-Published | J23: Metamorphosis Literary Agency | L23: Vanshika V | M23: 46283 | N23: Vanshika V | P23: https://docs.google.com/document/d/1AZ72q7C8i_7omvj052THx2y2GU2asMRf/edit?usp=drive_link&ouid=101023058405307348147&rtpof=true&sd=true | Q23: https://drive.google.com/drive/folders/1N4b9VEqoo2FBz5hKijQbMEwgVsajsyoz?usp=drive_link | S23: Batch 1 Review
A24: Kingdom of the Wicked Paperback Boxed Set | B24: Kerri Maniscalco | C24: Gothic Dark Romantasy | D24: https://www.goodreads.com/series/270202-kingdom-of-the-wicked | E24: 371413 | F24: 3.86 | G24: 3 | H24: 1226 | I24: Little, Brown Books for Young Readers | J24: Self-Represented / N/A | K24: Indie / Self-Published | L24: Sakshi Saxena | P24: 1_Kingdom_of_the_Wicked_Complete_Trilogy_-_Kerri_Maniscalco.docx | Q24: Kingdom Of The Wicked | S24: Batch 2 Review
A25: Wicked Games | B25: Kaylie Smith | C25: Gothic Dark Romantasy | D25: https://www.goodreads.com/series/400760-wicked-games | E25: 363340 | F25: 4.04 | G25: 3 | H25: 1393 | I25: Hachette UK - Second Sky | J25: Self-Represented / N/A | K25: Indie / Self-Published | L25: Sakshi Saxena | P25: 1_Phantasma_-_Kaylie_Smith.docx | Q25: Wicked Games | S25: Batch 2 Review
A26: Backstreet Evolutionist | B26: Anton Panarin | C26: High-Stakes Games & Deadly Trials (Done) | D26: https://www.goodreads.com/series/420245-backstreet-evolutionist | E26: 358860 | F26: 4.26 | G26: 7 | H26: 2455 | I26: Indie / Self-Published | J26: New Keywords - Amazon | L26: Sakshi Saxena | P26: 1_Backstreet_Evolutionist_Book_1_-_Anton_Panarin.docx | Q26: Backstreet Evolutionist | S26: Batch 2 Review
A27: Kingdom Of The White Sea | B27: Sarah M. Cradit | C27: High Fantasy Court Adventure | D27: https://www.goodreads.com/series/292339-kingdom-of-the-white-sea | E27: 803 | F27: 3.74 | G27: 3 | H27: 2083 | I27: Indie / Self-Published | J27: Metamorphosis Literary Agency | L27: Noel Regis | M27: 46282 | N27: Sakshi Saxena | O27: 46286 | P27: 1_The Kingless Crown.docx | Q27: 27_Kingdom of the White Sea | R27: Vanshika V | S27: Batch 1 Review
A28: The Black Dagger Brotherhood | B28: J. R. Ward | C28: High Fantasy Court Adventure | D28: https://www.goodreads.com/series/41963-black-dagger-brotherhood | E28: 358722 | F28: 4.15 | G28: 25 | H28: 10909 | I28: Indie / Self-Published | J28: New Keywords - Amazon | L28: Sakshi Saxena | P28: 1_Dark_Lover_Black_Dagger_Brotherhood_1_-_JR_Ward.docx | Q28: Black Dagger Brotherhood | S28: Batch 2 Review
A29: The Others | B29: Annie Smith | C29: Werewolf / Shifter Romance | D29: https://www.goodreads.com/series/99557-the-others | E29: 65629 | F29: 4.25 | G29: 10 | H29: 65629 | I29: Indie / Self-Published | J29: Jane Rotrosen Agency | L29: Vanshika V | M29: 46283 | N29: Vanshika V | P29: https://docs.google.com/document/d/12wZLqtIre7YvQctzS7xuAqT-CWOjX2GN/edit?usp=drive_link&ouid=101023058405307348147&rtpof=true&sd=true | Q29: https://drive.google.com/drive/folders/1_up8L0uC7UerTxoII-taECBEt7OvsSrC?usp=drive_link | S29: Batch 1 Review
A30: Blood And Ash World Reading Order | B30: Asha Lemmie | C30: High Fantasy Court Adventure | D30: https://www.goodreads.com/series/426746-blood-and-ash-world-reading-order | E30: 897900 | F30: 4.21 | G30: 11 | H30: 897900 | I30: Indie / Self-Published | J30: Jane Rotrosen Agency | L30: Vanshika V | M30: 46283 | N30: Vanshika V | P30: https://docs.google.com/document/d/135ekbg0UiYUSyVy8jO6tQ5AlJfQuRkV8/edit?usp=drive_link&ouid=101023058405307348147&rtpof=true&sd=true | Q30: https://drive.google.com/drive/folders/15Lw_RHugBnrWsrOGJ7oRPjcoMipkUPbM?usp=drive_link | S30: Batch 1 Review
A31: Serpent & Dove | B31: Shelby Mahurin | C31: Urban Coven Romance | D31: https://www.goodreads.com/series/253800-serpent-dove | E31: 353073 | F31: 3.96 | G31: 3 | H31: 1673 | I31: HarperCollins | J31: New Keywords - Amazon | L31: Sakshi Saxena | P31: 1_Serpent_n_Dove_-_Shelby_Mahurin.docx | Q31: Serpent Dove | S31: Batch 2 Review
A32: Rogues of the Crosslands Book 1 of 2: Rogues of the Crosslands | B32: by Brenda Trim | C32: Paranormal Romance ( Done ) | D32: https://www.goodreads.com/series/343601-twisted-sisters-midlife-maelstrom | E32: 316792 | F32: 4.42 | G32: 15 | H32: 3519 | I32: Amazon.com Services LLC Additional items, like pre-orders, may be ordered individually Items included | J32: New Keywords - Amazon | L32: Sakshi Saxena | P32: 1_Packing_Serious_Magical_Mojo_-_Brenda_Trim.docx | Q32: Twisted Sisters Midlife Maelstrom | S32: Batch 2 Review
A33: The Roots Of Chaos | B33: Shannon Iwanski | C33: High Fantasy Court Adventure | D33: https://www.goodreads.com/series/341670-the-roots-of-chaos | E33: 296756 | F33: 4.16 | G33: 3 | H33: 1992 | I33: Indie / Self-Published | J33: Metamorphosis Literary Agency | L33: Sakshi Saxena | P33: 1_The_Priory_of_the_Orange_Tree_-_Samantha_Shannon.docx | Q33: The Roots of Chaos | S33: Batch 2 Review
A34: Ravenhood Legacy Trilogy | B34: Curtiss Ann Matlock | C34: High Fantasy Court Adventure | D34: https://www.goodreads.com/series/372640-ravenhood-legacy-trilogy | E34: 60193 | F34: 4.52 | G34: 3 | H34: 60193 | I34: Indie / Self-Published | J34: Jane Rotrosen Agency | L34: Vanshika V | M34: 46283 | N34: Vanshika V | P34: https://docs.google.com/document/d/1YkcNeT5boR5hp_Lr3OKZQHp-7p4a93vS/edit?usp=drive_link&ouid=101023058405307348147&rtpof=true&sd=true | Q34: https://drive.google.com/drive/folders/1WZJ1zyPhIBhPxS9GBC-1smJcFWeK30hX?usp=drive_link | S34: Batch 1 Review
A35: The selection | B35: Kiera Cass | C35: High Fantasy Court Adventure | D35: https://www.goodreads.com/series/57517-the-selection | E35: 264382 | F35: 4.07 | G35: 5 | H35: 1615 | I35: Indie / Self-Published | J35: New Keywords - Amazon | L35: Sakshi Saxena | P35: 1_The_Selection_1_-_Kiera_Cass.docx | Q35: The Selection | S35: Batch 2 Review
A36: The Iron Fey | B36: Julie Garwood | C36: High Fantasy Court Adventure | D36: https://www.goodreads.com/series/47329-the-iron-fey | E36: 219403 | F36: 3.87 | G36: 10 | H36: 219403 | I36: Indie / Self-Published | J36: Jane Rotrosen Agency | L36: Vanshika V | M36: 46283 | N36: Vanshika V | P36: https://docs.google.com/document/d/1YafY33HU-RojH2WvpBBn-RiwK9oDIvKe/edit?usp=drive_link&ouid=101023058405307348147&rtpof=true&sd=true | Q36: https://drive.google.com/drive/folders/1YjJfGoDVMlRhji1WdLfrqE4lTkwqkVw0?usp=drive_link | S36: Batch 1 Review
A37: Emily Wilde's History of Dark Faerie: A Novel | B37: Heather Fawcett | C37: High Fantasy Court Adventure | D37: https://www.goodreads.com/series/353912-emily-wilde | E37: 235404 | F37: 3.95 | G37: 4 | H37: 1458 | I37: Del Rey | J37: Self-Represented / N/A | K37: Indie / Self-Published | L37: Sakshi Saxena | P37: 1_Emily_Wildes_Encyclopaedia_of_Faeries_-_Heather_Fawcett.docx | Q37: Emily Wilde | S37: Batch 2 Review
A38: Reign Of Remnants | B38: Julie Johnson | C38: High-Stakes Games & Deadly Trials | D38: https://www.goodreads.com/series/397346-reign-of-remnants | E38: 13147 | F38: 3.93 | G38: 3 | H38: 1088 | I38: Indie / Self-Published | J38: Jane Rotrosen Agency | L38: Noel Regis | M38: 46282 | N38: Sakshi Saxena | O38: 46286 | P38: 1_The Wind Weaver.docx | Q38: 38_Reign of Remnants | R38: Vanshika V | S38: Batch 1 Review
A39: The Marionettes | B39: Katie Lynch | C39: Paranormal Romance | D39: https://www.goodreads.com/series/320243-the-marionettes | E39: 9696 | F39: 3.88 | G39: 4 | H39: 9696 | I39: Indie / Self-Published | J39: Jane Rotrosen Agency | L39: Vanshika V | M39: 46283 | N39: Vanshika V | P39: https://docs.google.com/document/d/1prG7-cor9WE9I-H8dKnBTomzoCU8YK-t/edit?usp=drive_link&ouid=101023058405307348147&rtpof=true&sd=true | Q39: https://drive.google.com/drive/folders/1jFopVdx_P4ISQ_xIB2AUTJI0l0vNy03X?usp=drive_link | S39: Batch 1 Review
A40: Blood of the Ancients | B40: Dan Michaelson | C40: High-Stakes Games & Deadly Trials (Done) | D40: https://www.goodreads.com/series/345894-blood-of-the-ancients | E40: 230469 | F40: 4.06 | G40: 13 | H40: 3553 | I40: Indie / Self-Published | J40: New Keywords - Amazon | L40: Sakshi Saxena | P40: 1_Dragon_Forged_-_Dan_Michaelson.docx | Q40: Blood of the Ancients | S40: Batch 2 Review
A41: Old Kingdom | B41: Chuck Black | C41: High Fantasy Court Adventure | D41: https://www.goodreads.com/series/44888-abhorsen | E41: 221148 | F41: 4.16 | G41: 6 | H41: 2406 | I41: Indie / Self-Published | J41: New Keywords - Amazon | L41: Sakshi Saxena | P41: 1_Old_Kingdom_01__Sabriel_-_Garth_Nix.docx | Q41: Abhorsen | S41: Batch 2 Review
A42: Courts of Blood & Night | B42: Alisson Bento | C42: Paranormal Romance ( Done ) | D42: https://www.goodreads.com/series/442513-shadowed-realms | E42: 219395 | F42: 3.98 | G42: 13 | H42: 6690 | I42: Amazon.com Services LLC Deals on related products Sponsored Come Back for Me | J42: New Keywords - Amazon | L42: Anvita Belawal | M42: 46288 | N42: Vanshika V | S42: Noel Check
A43: Avalon | B43: Diana L. Paxson | C43: War College / Military Academy | D43: https://www.goodreads.com/series/51187-avalon-publication-order | E43: 214844 | F43: 4.13 | G43: 7 | H43: 3549 | I43: ) Format: Audible Audiobook | J43: New Keywords - Amazon | L43: Sakshi Saxena | P43: 1-The-Mists-of-Avalon-Marion-Zim.docx | Q43: Avalon | S43: Batch 2 Review
A44: Cassandra Palmer | B44: Matthew Palmer | C44: Urban / Contemporary Fantasy Romance | D44: https://www.goodreads.com/series/49237-cassandra-palmer | E44: 37083 | F44: 3.72 | G44: 14 | H44: 37083 | I44: Indie / Self-Published | J44: Jane Rotrosen Agency | L44: Vanshika V | M44: 46283 | N44: Vanshika V | P44: https://docs.google.com/document/d/1E8h2XWibVtYByhgI5qhzIFNRJMz2p55X/edit?usp=drive_link&ouid=101023058405307348147&rtpof=true&sd=true | Q44: https://drive.google.com/drive/folders/1WZ1OLSkrK9l-rWgXg6Hx7YzLEyKMLhSz?usp=drive_link | S44: Batch 1 Review
A45: Meg Langslow | B45: Meg Shaffer | C45: Cozy / Cottagecore Romantasy | D45: https://www.goodreads.com/series/41805-meg-langslow | E45: 14392 | F45: 3.89 | G45: 41 | H45: 14392 | I45: Indie / Self-Published | J45: Jane Rotrosen Agency | L45: Vanshika V | M45: 46283 | N45: Vanshika V | P45: https://docs.google.com/document/d/1KyUk6Z2rCFSa20m2bM2ayySgkswWdYw0/edit?usp=drive_link&ouid=101023058405307348147&rtpof=true&sd=true | Q45: https://drive.google.com/drive/folders/1jAYGNYCy4bjjfdMkmc6J--mysTfXq5GF?usp=drive_link | S45: Batch 1 Review
A46: 1 800 Where R You | B46: Meg Shaffer | C46: Paranormal Romance | D46: https://www.goodreads.com/series/40569-1-800-where-r-you | E46: 17799 | F46: 4.05 | G46: 7 | H46: 17799 | I46: Indie / Self-Published | J46: Jane Rotrosen Agency | L46: Vanshika V | M46: 46283 | N46: Vanshika V | P46: https://docs.google.com/document/d/1a_DBroEYhDYUZZ_9pA2J-tEKP-7lpp7b/edit?usp=drive_link&ouid=101023058405307348147&rtpof=true&sd=true | Q46: https://drive.google.com/drive/folders/1ORWEGkxAzBEPEiIJ5U7D_jACG9kTicZD?usp=drive_link | S46: Batch 1 Review
A47: Aunt Dimity Mystery | B47: Nancy Atherton | C47: Cozy / Cottagecore Romantasy | D47: https://www.goodreads.com/series/42315-aunt-dimity-mystery | E47: 15716 | F47: 3.95 | G47: 25 | H47: 15716 | I47: Indie / Self-Published | J47: Jane Rotrosen Agency | L47: Vanshika V | M47: 46283 | N47: Vanshika V | P47: https://docs.google.com/document/d/1k537Q7hk_uLa8koJCiopQKCD7n0VZVvU/edit?usp=drive_link&ouid=101023058405307348147&rtpof=true&sd=true | Q47: https://drive.google.com/drive/folders/1t2XtLfUaXUijVJvATgs_M6fbj1ClrCxB?usp=drive_link | S47: Batch 1 Review
A48: Goddess Summoning | B48: PC Cast | C48: Mythology, Legend & Fairy Tale Retelling | D48: https://www.goodreads.com/series/40627-goddess-summoning | E48: 12053 | F48: 3.84 | G48: 7 | H48: 12053 | I48: Indie / Self-Published | J48: Jane Rotrosen Agency | L48: Vanshika V | M48: 46283 | N48: Vanshika V | P48: https://docs.google.com/document/d/1m5ddGHE0oC5Yhr-UlhC-AyhhskRA7LT0/edit?usp=drive_link&ouid=101023058405307348147&rtpof=true&sd=true | Q48: https://drive.google.com/drive/folders/1egk-g5YU6w5PXma37P3eAij3X2xp5NLa?usp=drive_link | S48: Batch 1 Review
A49: Gone | B49: Libbie Grant | C49: Paranormal Romance | D49: https://www.goodreads.com/series/45284-gone | E49: 213082 | F49: 3.87 | G49: 9 | H49: 8405 | I49: Indie / Self-Published | J49: Jane Rotrosen Agency | L49: Sakshi Saxena | P49: 1_Gone_-_Michael_Grants.docx | Q49: Gone | S49: Batch 2 Review
A50: House Of Night | B50: PC Cast | C50: Paranormal Romance | D50: https://www.goodreads.com/series/40626-house-of-night | E50: 528222 | F50: 3.82 | G50: 18 | H50: 528222 | I50: Indie / Self-Published | J50: Jane Rotrosen Agency | L50: Vanshika V | M50: 46283 | N50: Vanshika V | P50: https://docs.google.com/document/d/13uuR-OEHEJhmnqdQR7l6Pc-V8u-u6h35/edit?usp=drive_link&ouid=101023058405307348147&rtpof=true&sd=true | Q50: https://drive.google.com/drive/folders/1cj1p_aOzARca8F126yrpj_OtN5cTPOcJ?usp=drive_link | S50: Batch 1 Review
A51: The Hunger Games | B51: Susan Andersen | C51: High Fantasy Court Adventure | D51: https://www.goodreads.com/series/73758-the-hunger-games | E51: 10212505 | F51: 4.35 | G51: 4 | H51: 10212505 | I51: Indie / Self-Published | J51: Jane Rotrosen Agency | L51: Vanshika V | M51: 46283 | N51: Vanshika V | P51: https://docs.google.com/document/d/1S34tcHPBrVU9IxnjFfAOy96gQIltQTu7/edit?usp=drive_link&ouid=101023058405307348147&rtpof=true&sd=true | Q51: https://drive.google.com/drive/folders/1Xl527na8Xv1Y9fnkp7XSxLvrJ7iSBhON?usp=drive_link | S51: Batch 1 Review
A52: Elder Races | B52: Thea Weiss | C52: Werewolf / Shifter Romance | D52: https://www.goodreads.com/series/55645-elder-races | E52: 53612 | F52: 4.06 | G52: 10 | H52: 53612 | I52: Indie / Self-Published | J52: Jane Rotrosen Agency | L52: Vanshika V | M52: 46283 | N52: Vanshika V | P52: https://docs.google.com/document/d/1OKtNftMTuy4MrR2QZPPdJUVBS7m02TFq/edit?usp=drive_link&ouid=101023058405307348147&rtpof=true&sd=true | Q52: https://drive.google.com/drive/folders/1xnScBL7f3OMq9yotwc_hn2-0wnoWk1_A?usp=drive_link | S52: Batch 1 Review
A53: A Loon Lake Mystery | B53: Victoria Wlosok | C53: Cozy / Cottagecore Romantasy | D53: https://www.goodreads.com/series/41952-a-loon-lake-mystery | E53: 1939 | F53: 3.84 | G53: 19 | H53: 1939 | I53: Indie / Self-Published | J53: Jane Rotrosen Agency | L53: Vanshika V | M53: 46283 | N53: Vanshika V | P53: https://docs.google.com/document/d/1aVX2sKF7en6zK6u4uOKQwpXd6_NXIN3i/edit?usp=drive_link&ouid=101023058405307348147&rtpof=true&sd=true | Q53: https://drive.google.com/drive/folders/1E9M6ZG6eKPE3JOcqWttamq8-jBRaPgcb?usp=drive_link | S53: Batch 1 Review
A54: Clecanian | B54: Victoria Wlosok | C54: Paranormal Romance | D54: https://www.goodreads.com/series/283794-clecanian | E54: 57309 | F54: 4.08 | G54: 8 | H54: 57309 | I54: Indie / Self-Published | J54: Jane Rotrosen Agency | L54: Vanshika V | M54: 46283 | N54: Vanshika V | P54: https://docs.google.com/document/d/1ifRVlx7vvnVxZqW7huGkHGazBOl1Uk5U/edit?usp=drive_link&ouid=101023058405307348147&rtpof=true&sd=true | Q54: https://drive.google.com/drive/folders/1T6Ekp7dRTIcZ52S_o-Rf6qrfxawtAIhD?usp=drive_link | S54: Batch 1 Review
A55: Sweet | B55: Wendy Francis | C55: Paranormal Romance | D55: https://www.goodreads.com/series/83847-sweet | E55: 78102 | F55: 4.07 | G55: 4 | H55: 78102 | I55: Indie / Self-Published | J55: Jane Rotrosen Agency | L55: Vanshika V | M55: 46283 | N55: Vanshika V | P55: https://docs.google.com/document/d/1cLsmb1DanTTriXKLm_yIc0RdsGv0hukn/edit?usp=drive_link&ouid=101023058405307348147&rtpof=true&sd=true | Q55: https://drive.google.com/drive/folders/1A9PP1ZXzw2XKdTQG6BJbBKozIKwMrqdv?usp=drive_link | S55: Batch 1 Review
A56: The Bargainer | B56: Laura Thalassa | C56: Gothic Dark Romantasy | D56: https://www.goodreads.com/series/182626-the-bargainer | E56: 203832 | F56: 3.89 | G56: 4 | H56: 1555 | I56: Blackstone Publishing | J56: Self-Represented / N/A | K56: Blackstone Publishing | L56: Sakshi Saxena | P56: 1_Rhapsodic_-_Laura_Thalassa.docx | Q56: The Bargainer | S56: Batch 2 Review
A57: Fever | B57: Joyce Bean | C57: Gothic Romance | D57: https://www.goodreads.com/series/41192-fever | E57: 192228 | F57: 4.05 | G57: 11 | H57: 4885 | I57: ) Format: Audible Audiobook | J57: New Keywords - Amazon | L57: Sakshi Saxena | P57: 1_Darkfever_-_Karen_Marie_Moning.docx | Q57: Fever Series | S57: Batch 2 Review
A58: Villains of Lore | B58: Jasmine Mas | C58: Mythology, Legend & Fairy Tale Retelling | D58: https://www.goodreads.com/series/398629-villains-of-lore | E58: 188890 | F58: 3.91 | G58: 3 | H58: 1584 | I58: MIRA | J58: Self-Represented / N/A | K58: Indie / Self-Published | L58: Sakshi Saxena | P58: 1_Blood_of_Hercules_-_Jasmine_Mas.docx | Q58: Villains Of Lore | S58: Batch 2 Review
A59: The Chronicles Of Ixia | B59: Calia Read | C59: High Fantasy Court Adventure | D59: https://www.goodreads.com/series/111197-the-chronicles-of-ixia | E59: 178520 | F59: 4.08 | G59: 9 | H59: 5676 | I59: Indie / Self-Published | J59: Jane Rotrosen Agency | L59: Sakshi Saxena | P59: 1_Poison_Study_-_Maria_V_Snyder.docx | Q59: The Chronicles Of Ixia | S59: Batch 2 Review
A60: The Shadow Walkers Saga by Sloane Murphy | B60: Sloane Murphy | C60: Paranormal Romance ( Done ) | D60: https://www.goodreads.com/series/320304-the-shadow-walkers-saga | E60: 166211 | F60: 4.12 | G60: 6 | H60: 2455 | I60: ) Format: Audible Audiobook | J60: New Keywords - Amazon | L60: Sakshi Saxena | P60: 1_A_Crown_of_Blood_and_Bone_-_Sloane_Murphy.docx | Q60: The Shadow Walkers Saga | S60: Batch 2 Review
A61: The Daevabad Trilogy | B61: S. A. Chakraborty | C61: High Fantasy Court Adventure | D61: https://www.goodreads.com/series/211584-the-daevabad-trilogy | E61: 164266 | F61: 4.14 | G61: 3 | H61: 1923 | I61: ) Format: Audible Audiobook | J61: New Keywords - Amazon | L61: Sakshi Saxena | P61: 1_The_City_of_Brass_-_S_A_Chakraborty.docx | Q61: The Daevabad Trilogy | S61: Batch 2 Review
A62: Dark Verse | B62: RuNyx | C62: Gothic Dark Romantasy | D62: https://www.goodreads.com/series/287221-dark-verse | E62: 146216 | F62: 3.97 | G62: 7 | H62: 4312 | I62: P1: Amazon Digital Services | P2: Smashwords | K62: Podium Audio | L62: Noel Regis | M62: 46282 | N62: Sakshi Saxena | O62: 46286 | P62: 1_The Predator.docx | Q62: 62_Dark Verse | S62: Batch 1 Review
A63: The School For Good And Evil | B63: Jacob Eckeberger | C63: Mythology, Legend & Fairy Tale Retelling | D63: https://www.goodreads.com/series/100839-the-school-for-good-and-evil | E63: 139684 | F63: 3.99 | G63: 8 | H63: 5383 | I63: Indie / Self-Published | J63: Metamorphosis Literary Agency | L63: Sakshi Saxena | P63: 1_The_School_for_Good_and_Evil__The_Ever_Nev_-_Soman_Chainanii.docx | Q63: The School For Good And Evil | S63: Batch 2 Review
A64: The Eating Woods | B64: by Keri Lake | C64: Gothic Romance | D64: https://www.goodreads.com/series/389166-the-eating-woods | E64: 137053 | F64: 4.17 | G64: 3 | H64: 1856 | I64: Amazon.com Services LLC Items included | J64: New Keywords - Amazon | L64: Sakshi Saxena | P64: 1_Anathema_italian_Edition_-_Keri_Lake.docx | Q64: The Eating Woods | S64: Batch 2 Review
A65: The Hollows | B65: Kim Harrison | C65: Gothic Dark Romantasy | D65: https://www.goodreads.com/series/40628-the-hollows | E65: 130318 | F65: 3.99 | G65: 19 | H65: 8728 | I65: ) Format: Audible Audiobook | J65: New Keywords - Amazon | L65: Sakshi Saxena | P65: 1_Dead_Witch_Walking_-_Kim_Harrison.docx | Q65: The Hollows | S65: Batch 2 Review
A66: The Anna Albertini Files Book 1 of 7: The Anna Albertini Files | B66: Parker S. Huntington | C66: High Fantasy Court Adventure | D66: https://www.goodreads.com/series/378153-dark-prince-road | E66: 128858 | F66: 3.71 | G66: 3 | H66: 1230 | I66: PSH Publishing | J66: Self-Represented / N/A | K66: Indie / Self-Published | L66: Sakshi Saxena | P66: 1_My_Dark_Romeo_-_LJ_Shen.docx | Q66: Dark Prince Road | S66: Batch 2 Review
A67: Bloodwing Academy | B67: Briar Boleyn | C67: Gothic Dark Romantasy | D67: https://www.goodreads.com/series/390267-bloodwing-academy | E67: 127131 | F67: 3.91 | G67: 3 | H67: 1418 | I67: Podium Audio | J67: Self-Represented / N/A | K67: Podium Audio | L67: Noel Regis | M67: 46282 | N67: Sakshi Saxena | O67: 46286 | P67: 1_On Wings of Blood.docx | Q67: 67_Bloodwing Academy | S67: Batch 1 Review
A68: Cursed Stars | B68: Lexi Ryan | C68: Gothic Dark Romantasy | D68: https://www.goodreads.com/series/318420-these-hollow-vows | E68: 127092 | F68: 3.93 | G68: 5 | H68: 2775 | I68: Storytide | J68: New Keywords - Amazon | L68: Sakshi Saxena | P68: 1_These_hollow_vows_-_Lexi_Ryan.docx | Q68: These Hollow Vows | S68: Batch 2 Review
A69: Married to Magic | B69: Elise Kova | C69: Romance | D69: https://www.goodreads.com/series/303472-married-to-magic | E69: 122056 | F69: 3.69 | G69: 5 | H69: 2242 | I69: Indie / Self-Published | J69: The Bent Agency (Direct) | L69: Sakshi Saxena | P69: 1_A_Deal_with_the_Elf_King_-_Elise_Kova.docx | Q69: Married to Magic | S69: Batch 2 Review
A70: Prince of Sin | B70: Kerri Maniscalco | C70: High Fantasy Court Adventure | D70: https://www.goodreads.com/series/386472-prince-of-sin | E70: 120580 | F70: 3.96 | G70: 3 | H70: 1564 | I70: Little, Brown and Company | J70: Self-Represented / N/A | K70: Indie / Self-Published | L70: Sakshi Saxena | P70: 1_Throne_of_the_Fallen_-_Kerri_Maniscalco.docx | Q70: Prince of Sin | S70: Batch 2 Review
A71: Crave | B71: Tracy Wolff | C71: Mythology, Legend & Fairy Tale Retelling | D71: https://www.goodreads.com/series/286781-crave | E71: 119076 | F71: 3.76 | G71: 21 | H71: 11803 | I71: Entangled Publishing | K71: Tantor Media | L71: Noel Regis | M71: 46282 | N71: Sakshi Saxena | O71: 46286 | P71: 1_Crave.docx | Q71: 71_Crave | S71: Batch 1 Review
A72: Perfectly Imperfect | B72: Neva Altaj | C72: Urban / Contemporary Fantasy Romance | D72: https://www.goodreads.com/series/343844-perfectly-imperfect | E72: 118006 | F72: 3.73 | G72: 13 | H72: 4497 | I72: Neva Altaj | K72: Podium Audio | L72: Noel Regis | M72: 46282 | N72: Sakshi Saxena | O72: 46286 | P72: 1_Painted Scars.docx | Q72: 72_Perfectly Imperfect | S72: Batch 1 Review
A73: Covenant Series | B73: Jennifer L. Armentrout | C73: Mythology, Legend & Fairy Tale Retelling | D73: https://www.goodreads.com/series/53954-covenant | E73: 116532 | F73: 4.06 | G73: 5 | H73: 1580 | I73: Self Published | K73: Tantor Media | L73: Noel Regis | M73: 46282 | N73: Sakshi Saxena | O73: 46286 | P73: 1_Half-Blood.docx | Q73: 73_Covenant | S73: Batch 1 Review
A74: Lords of the Underworld | B74: Gena Showalter | C74: Mythology, Legend & Fairy Tale Retelling | D74: https://www.goodreads.com/series/46385-lords-of-the-underworld | E74: 110776 | F74: 4.27 | G74: 15 | H74: 7331 | I74: HQN Books | J74: New Keywords - Amazon | L74: Sakshi Saxena | P74: 1_The_Darkest_Night_-_Showalter_Gena.docx | Q74: Lords of the Underworld | S74: Batch 2 Review
A75: The Morganville Vampires | B75: Rachel Caine | C75: Gothic Dark Romantasy | D75: https://www.goodreads.com/series/40593-the-morganville-vampires | E75: 104086 | F75: 4.8 | G75: 20 | H75: 6452 | I75: ) Format: Audible Audiobook | J75: New Keywords - Amazon | L75: Sakshi Saxena | P75: 1_The_Morganville_Vampires_-_Rachel_Cainee.docx | Q75: The Morganville Vampires | S75: Batch 2 Review
A76: Guild Hunter | B76: Nalini Singh | C76: Gothic Dark Romantasy | D76: https://www.goodreads.com/series/47942-guild-hunter | E76: 99349 | F76: 4.06 | G76: 18 | H76: 6700 | I76: ) Format: Audible Audiobook | J76: New Keywords - Amazon | L76: Sakshi Saxena | P76: 1_Angels_Blood_-_Nalini_Singh.docx | Q76: Guild Hunter | S76: Batch 2 Review
A77: The Queen's Thief | B77: Megan Whalen Turner | C77: High Fantasy Court Adventure | D77: https://www.goodreads.com/series/43514-the-queen-s-thief | E77: 95397 | F77: 3.85 | G77: 6 | H77: 2146 | I77: Indie / Self-Published | J77: New Keywords - Amazon | L77: Sakshi Saxena | P77: 1_The_Thief_-_Megan_Whalen_Turner.docx | Q77: The Queen S Thief | S77: Batch 2 Review
A78: Alliance | B78: S.J. Tilly | C78: Urban / Contemporary Fantasy Romance | D78: https://www.goodreads.com/series/362029-alliance | E78: 95274 | F78: 3.81 | G78: 4 | H78: 1668 | I78: Amazon Digital Services | K78: Podium Audio | L78: Noel Regis | M78: 46282 | N78: Sakshi Saxena | O78: 46286 | P78: 1_Nero.docx | Q78: 78_Alliance | S78: Batch 1 Review
A79: The Dark Elements | B79: Jennifer L. Armentrout | C79: Gothic Dark Romantasy | D79: https://www.goodreads.com/series/98903-the-dark-elements | E79: 91654 | F79: 4.16 | G79: 3 | H79: 1219 | I79: Tantor Audio | J79: Self-Represented / N/A | K79: Tantor Media | L79: Noel Regis | M79: 46282 | N79: Sakshi Saxena | O79: 46286 | P79: 1_White Hot Kiss.docx | Q79: 79_The Dark Elements | S79: Batch 1 Review
A80: Fairhaven Falls | B80: Honey Phillips | C80: Werewolf / Shifter Romance ( Done ) | D80: https://www.goodreads.com/series/377729-fairhaven-falls | E80: 86400 | F80: 4.04 | G80: 12 | H80: 2340 | I80: Amazon.com Services LLC Additional items, like pre-orders, may be ordered individually Items included | J80: New Keywords - Amazon | L80: Sakshi Saxena | P80: 1_Cupcakes_for_My_Orc_Enemy_-_Honey_Phillips.docx | Q80: Fairhaven Falls | S80: Batch 2 Review
A81: Kara Gillian | B81: Diana Rowland | C81: Paranormal Romance ( Done ) | D81: https://www.goodreads.com/series/46544-kara-gillian | E81: 86355 | F81: 3.83 | G81: 9 | H81: 3142 | I81: ) Format: Audible Audiobook | J81: New Keywords - Amazon | L81: Sakshi Saxena | P81: 1_Mark_of_the_Demon_-_Diana_Rowland.docx | Q81: Kara Gillian | S81: Batch 2 Review
A82: Damaged Souls: A Reverse Harem Fantasy Romance (Saints Academy Book 2) | B82: Kayla Edwards | C82: Modern Low Fantasy | D82: https://www.goodreads.com/series/335398-house-of-devils | E82: 85699 | F82: 3.76 | G82: 6 | H82: 3081 | I82: Scarlett Press | K82: Podium Audio | L82: Noel Regis | M82: 46282 | N82: Sakshi Saxena | O82: 46286 | P82: 1_City of Gods and Monsters.docx | Q82: 82_House of Devils | S82: Batch 1 Review
A83: The Inheritance Trilogy | B83: N. K. Jemisin | C83: Mythology, Legend & Fairy Tale Retelling | D83: https://www.goodreads.com/series/46971-inheritance-trilogy | E83: 83334 | F83: 3.89 | G83: 4 | H83: 1488 | I83: Aubrey Velasquez | J83: Self-Represented / N/A | K83: Indie / Self-Published | L83: Sakshi Saxena | P83: 1_The_Hundred_Thousand_Kingdoms_-_N_K_Jemisin.docx | Q83: Inheritance Trilogy | S83: Batch 2 Review
A84: Cambric Creek: Sweet & Steamy Monster Romance | B84: C.M. Nascosta | C84: Werewolf / Shifter Romance | D84: https://www.goodreads.com/series/324507-cambric-creek | E84: 80068 | F84: 3.56 | G84: 5 | H84: 1328 | I84: Tantor Media | J84: Self-Represented / N/A | K84: Tantor Media | L84: Noel Regis | M84: 46282 | N84: Sakshi Saxena | O84: 46286 | P84: 1_Morning Glory Milking Farm.docx | Q84: 84_Cambric Creek | S84: Batch 1 Review
A85: Psy-Changeling | B85: Nalini Singh | C85: Werewolf / Shifter Romance | D85: https://www.goodreads.com/series/41454-psy-changeling | E85: 79221 | F85: 4.08 | G85: 25 | H85: 9672 | I85: Penguin Random House | K85: Tantor Media | L85: Noel Regis | M85: 46282 | N85: Sakshi Saxena | O85: 46286 | P85: 1_Slave to Sensation.docx | Q85: 85_Psy-Changeling | S85: Batch 1 Review
A86: The Ashen | B86: Dawn Rasmussen | C86: High Fantasy Court Adventure | D86: https://www.goodreads.com/series/372821-the-ashen | E86: 79115 | F86: 4.21 | G86: 3 | H86: 1674 | I86: ) Format: Audible Audiobook | J86: Metamorphosis Literary Agency | L86: Sakshi Saxena | P86: 1_The_Road_of_Bones_-_Demi_Winters.docx | Q86: The Ashen | S86: Batch 2 Review
A87: Monsters & Muses | B87: Sav R. Miller | C87: Monster Romance ( Non-Shifter ) | D87: https://www.goodreads.com/series/324608-monsters-muses | E87: 77665 | F87: 3.49 | G87: 6 | H87: 2296 | I87: Sourcebooks Casablanca | J87: New Keywords - Amazon | L87: Sakshi Saxena | P87: 1_Promises_and_Pomegranates_-_Sav_R_Miller.docx | Q87: Monsters Muses | S87: Batch 2 Review
A88: A Witch in Wolf Wood | B88: Lindsay Buroker | C88: Paranormal Romance ( Done ) | D88: https://www.goodreads.com/series/326859-a-witch-in-wolf-wood | E88: 77581 | F88: 3.93 | G88: 6 | H88: 2656 | I88: ), Vivienne Leheny (Narrator) Format: Audible Audiobook | J88: New Keywords - Amazon | L88: Sakshi Saxena | P88: Mind Over Magic A 1_Paranormal Womens Fiction Novel.docx | Q88: A Witch in Wolf Wood | S88: Batch 2 Review
A89: Harbinger | B89: Jennifer L. Armentrout | C89: Werewolf / Shifter Romance | D89: https://www.goodreads.com/series/253512-the-harbinger | E89: 74151 | F89: 4.03 | G89: 3 | H89: 1564 | I89: HarperCollins | J89: Self-Represented / N/A | K89: Indie / Self-Published | L89: Sakshi Saxena | P89: 1_Storm_and_Fury_-_Jennifer_L_Armentrout.docx | Q89: The Harbinger | S89: Batch 2 Review
A90: Gods Monsters | B90: Amber V. Nicole | C90: High-Stakes Games & Deadly Trials (Done) | D90: https://www.goodreads.com/series/344354-gods-monsters | E90: 68914 | F90: 4.12 | G90: 5 | H90: 2554 | I90: Penguin Random House | K90: Penguin Random House | L90: Noel Regis | M90: 46282 | N90: Sakshi Saxena | O90: 46286 | P90: 1_The Book of Azrael.docx | Q90: 90_Gods & Monsters | S90: Batch 1 Review
A91: Tiger Curse | B91: Hattie Jacks | C91: High Fantasy Court Adventure | D91: https://www.goodreads.com/series/47592-the-tiger-saga | E91: 67880 | F91: 4.05 | G91: 9 | H91: 3826 | I91: Indie / Self-Published | J91: New Keywords - Amazon | L91: Sakshi Saxena | P91: 1_Tiger_Saga_1_Tigers_Curse_-_Colleen_Houck.docx | Q91: The Tiger Saga | S91: Batch 2 Review
A92: The Underworld Saga | B92: Eva Pohler | C92: Mythology, Legend & Fairy Tale Retelling | D92: https://www.goodreads.com/series/91690-underworld-saga | E92: 65923 | F92: 3.64 | G92: 11 | H92: 4302 | I92: Eva Pohler Books | J92: New Keywords - Amazon | L92: Sakshi Saxena | P92: 1_Thanatos (Eva Pohler).docx | Q92: Underworld Saga | S92: Batch 2 Review
A93: Falling Kingdoms | B93: Morgan Rhodes | C93: High Fantasy Court Adventure | D93: https://www.goodreads.com/series/68150-falling-kingdoms | E93: 63545 | F93: 3.77 | G93: 6 | H93: 2412 | I93: Indie / Self-Published | J93: New Keywords - Amazon | L93: Sakshi Saxena | P93: 1_Falling_Kingdoms_-_Morgan_Rhodes.docx | Q93: Falling Kingdoms | S93: Batch 2 Review
A94: Fairy-tale Inheritance Series | B94: Stephen King | C94: Subjective | D94: https://www.goodreads.com/series/150426-fairy-tale-inheritance | E94: 62362 | F94: 3.8 | G94: 6 | H94: 1943 | I94: Indie / Self-Published | J94: New Keywords - Amazon | L94: Sakshi Saxena | P94: 1_Cinderellas_Dress_-_Shonna_Slayton.docx | Q94: Fairy Tale Inheritance | S94: Batch 2 Review
A95: Merry Gentry | B95: Meredith Fraser | C95: High Fantasy Court Adventure | D95: https://www.goodreads.com/series/40414-merry-gentry | E95: 61712 | F95: 4.02 | G95: 10 | H95: 3420 | I95: Berkley | J95: Metamorphosis Literary Agency | L95: Sakshi Saxena | P95: 1_A_Kiss_of_Shadows_Merry_Gentry_1_-_Laurell_K_Hamilton.docx | Q95: Merry Gentry | S95: Batch 2 Review
A96: Ravenhood Legacy | B96: Kate Stewart | C96: High Fantasy Court Adventure | D96: https://www.goodreads.com/series/372640-ravenhood-legacy | E96: 56519 | F96: 4.51 | G96: 3 | H96: 1440 | I96: Kensington Publishers | K96: Podium Audio | L96: Noel Regis | M96: 46282 | N96: Sakshi Saxena | O96: 46286 | P96: 1_One Last Rainy Day The Legacy of a Prince.docx | Q96: 96_Ravenhood Legacy Trilogy by Kate Stewart | S96: Batch 1 Review
A97: Wrath Book 1 of 3: Wrath | B97: Becky Moynihan | C97: Subjective | D97: https://www.goodreads.com/series/314390-entangled-with-fae | E97: 56198 | F97: 3.79 | G97: 5 | H97: 2255 | I97: Indie / Self-Published | J97: New Keywords - Amazon | L97: Sakshi Saxena | P97: 1_Curse_of_the_Wolf_King_-_Tessonja_Odette.docx | Q97: Entangled with Fae | S97: Batch 2 Review
A98: Die for Me | B98: Amy Plum | C98: Mythology, Legend & Fairy Tale Retelling | D98: https://www.goodreads.com/series/50245-revenants | E98: 56137 | F98: 3.97 | G98: 4 | H98: 1314 | I98: Indie / Self-Published | J98: Self-Represented / N/A | K98: Indie / Self-Published | L98: Sakshi Saxena | P98: 1_Die for Me (Amy Plum).docx | Q98: The Wolves of Ruin | S98: Batch 2 Review
A99: The Wolves of Ruin | B99: Sable Sorensen | C99: High Fantasy Court Adventure | D99: https://www.goodreads.com/series/406768-the-wolves-of-ruin | E99: 54380 | F99: 4.46 | G99: 7 | H99: 2613 | I99: Indie / Self-Published | J99: New Keywords - Amazon | L99: Sakshi Saxena | P99: 1_Dire_Bound_-_by_Sable_Sorensen.docx | Q99: The Wolves of Ruin | S99: Batch 2 Review
A100: New York Ruthless | B100: Sadie Kincaid | C100: Gothic Dark Romantasy | D100: https://www.goodreads.com/series/338189-new-york-ruthless | E100: 52627 | F100: 3.89 | G100: 5 | H100: 1392 | I100: Red House Press Ltd | K100: Podium Audio | L100: Noel Regis | M100: 46282 | N100: Sakshi Saxena | O100: 46286 | P100: 1_Ryan Rule.docx | Q100: 100_New York Ruthless | S100: Batch 1 Review
...

Sheet Books not found
A1: Series Name | B1: Missing Book Numbers | C1: Goodreads Series Link | D1: POC | E1: Date | F1: Status
A2: Akora | B2: All Books (1–5) | C2: https://www.goodreads.com/series/43414-akora | D2: Sakshi Saxena | E2: 46281 | F2: Done
A3: Rubyverse Reading Order | B3: All Books (1–5) | C3: https://www.goodreads.com/series/434234-rubyverse-reading-order | D3: Sakshi Saxena | E3: 46281 | F3: Done
A4: Shifter Nation Box Sets | B4: All Books (1–5) | C4: https://www.goodreads.com/series/234894-shifter-nation-box-sets | D4: Sakshi Saxena | E4: 46281 | F4: Done
A5: Agnyeoreul Jugyeo Jwo Comic | B5: All Books (1–5) | C5: https://www.goodreads.com/series/336854-agnyeoreul-jugyeo-jwo-comic | D5: Sakshi Saxena | E5: 46281 | F5: Korea
A6: Futsutsuka Na Akujo Dewa Gozaimasu Ga Suug | B6: All Books (1–5) | C6: https://www.goodreads.com/series/356817-futsutsuka-na-akujo-dewa-gozaimasu-ga-suug | D6: Sakshi Saxena | E6: 46281 | F6: Done
A7: House Of Quercus | B7: All Books (1–5) | C7: https://www.goodreads.com/series/247507-house-of-quercus | D7: Sakshi Saxena | E7: 46281 | F7: Done
A8: No Kemono | B8: All Books (1–5) | C8: https://www.goodreads.com/series/293898-no-kemono | D8: Sakshi Saxena | E8: 46281 | F8: Done
A9: Tensei Akujo No Kuro Rekishi | B9: All Books (1–5) | C9: https://www.goodreads.com/series/300963-tensei-akujo-no-kuro-rekishi | D9: Sakshi Saxena | E9: 46281 | F9: Korea
A10: Tensei Oujo Wa Kyou Mo Hata O Tatakioru Novel | B10: All Books (1–5) | C10: https://www.goodreads.com/series/249669-tensei-oujo-wa-kyou-mo-hata-o-tatakioru-novel | D10: Sakshi Saxena | E10: 46281 | F10: Korea
A11: Villains | B11: Book 1 | C11: https://www.goodreads.com/series/162322-villains | D11: Sakshi Saxena | E11: 46281 | F11: Done
A12: Chaos Magic | B12: Book 1 | C12: https://www.goodreads.com/series/365832-chaos-magic | D12: Sakshi Saxena | E12: 46281 | F12: Done
A13: The Protectors | B13: Book 1, Book 2 | C13: https://www.goodreads.com/series/197556-the-protectors | D13: Sakshi Saxena | E13: 46281 | F13: Done
... A17: Pledged To Him | B17: Book 1, Book 5 | C17: https://www.goodreads.com/series/446204-pledged-to-him | D17: Sakshi Saxena | E17: 46281 | F17: Done
A18: The Shadowhunter Chronicles | B18: Book 3, Book 4 | C18: {=_xlfn.XLOOKUP(A18,'Picks for Review (Sep 26)'!A:A,'Picks for Review (Sep 26)'!D:D)} | D18: Anushka Baisya | E18: 46281 | F18: Missing (Book 3, Book 4)
A19: Kingdom Of The Wicked | B19: Book 4 | C19: {=_xlfn.XLOOKUP(A19,'Picks for Review (Sep 26)'!A:A,'Picks for Review (Sep 26)'!D:D)} | D19: Anushka Baisya | E19: 46281 | F19: Missing (Book 4)
A20: Serpent Dove | B20: Book 4, Book 5 | C20: {=_xlfn.XLOOKUP(A20,'Picks for Review (Sep 26)'!A:A,'Picks for Review (Sep 26)'!D:D)} | D20: Anushka Baisya | E20: 46281 | F20: Missing (Book 4, Book 5)
A21: The Roots Of Chaos | B21: Book 3, Book 4 | C21: {=_xlfn.XLOOKUP(A21,'Picks for Review (Sep 26)'!A:A,'Picks for Review (Sep 26)'!D:D)} | D21: Anushka Baisya | E21: 46281 | F21: Missing (Book 3, Book 4)
A22: Emily Wilde | B22: Book 4, Book 5 | C22: {=_xlfn.XLOOKUP(A22,'Picks for Review (Sep 26)'!A:A,'Picks for Review (Sep 26)'!D:D)} | D22: Anushka Baisya | E22: 46281 | F22: Missing (Book 4, Book 5)
A23: Avalon Publication Order | B23: Book 1, Book 2, Book 3, Book 4, Book 5 | C23: {=_xlfn.XLOOKUP(A23,'Picks for Review (Sep 26)'!A:A,'Picks for Review (Sep 26)'!D:D)} | D23: Anushka Baisya | E23: 46281 | F23: Missing (Book 1, Book 2, Book 3, Book 4, Book 5) | G23: No Links
A24: Villains Of Lore | B24: Book 3, Book 4, Book 5 | C24: {=_xlfn.XLOOKUP(A24,'Picks for Review (Sep 26)'!A:A,'Picks for Review (Sep 26)'!D:D)} | D24: Anushka Baisya | E24: 46281 | F24: Missing (Book 3, Book 4, Book 5) | G24: Till Book 3 is available on goodreads
A25: The Chronicles Of Ixia | B25: Book 4 | C25: {=_xlfn.XLOOKUP(A25,'Picks for Review (Sep 26)'!A:A,'Picks for Review (Sep 26)'!D:D)} | D25: Anushka Baisya | E25: 46281 | F25: Missing (Book 4) | G25: Updated
A26: The Shadow Walkers Saga | B26: Book 3 | C26: {=_xlfn.XLOOKUP(A26,'Picks for Review (Sep 26)'!A:A,'Picks for Review (Sep 26)'!D:D)} | D26: Anushka Baisya | E26: 46281 | F26: Missing (Book 3) | G26: Updated
A27: The Daevabad Trilogy | B27: Book 4, Book 5 | C27: {=_xlfn.XLOOKUP(A27,'Picks for Review (Sep 26)'!A:A,'Picks for Review (Sep 26)'!D:D)} | D27: Anushka Baisya | E27: 46281 | F27: Missing (Book 4, Book 5) | G27: Till Book 3 is available on goodreads
A28: The Eating Woods | B28: Book 3, Book 4, Book 5 | C28: {=_xlfn.XLOOKUP(A28,'Picks for Review (Sep 26)'!A:A,'Picks for Review (Sep 26)'!D:D)} | D28: Anushka Baisya | E28: 46281 | F28: Missing (Book 3, Book 4, Book 5) | G28: Till Book 3 is available on goodreads ; not able to find book 3
A29: Dark Prince Road | B29: Book 4, Book 5 | C29: {=_xlfn.XLOOKUP(A29,'Picks for Review (Sep 26)'!A:A,'Picks for Review (Sep 26)'!D:D)} | D29: Anushka Baisya | E29: 46281 | F29: Missing (Book 4, Book 5) | G29: Till Book 3 is available on goodreads
A30: Bloodwing Academy | B30: Book 4, Book 5 | C30: {=_xlfn.XLOOKUP(A30,'Picks for Review (Sep 26)'!A:A,'Picks for Review (Sep 26)'!D:D)} | D30: Anushka Baisya | E30: 46281 | F30: Missing (Book 4, Book 5) | G30: Till Book 3 is available on goodreads
A31: These Hollow Vows | B31: Book 3, Book 5 | C31: {=_xlfn.XLOOKUP(A31,'Picks for Review (Sep 26)'!A:A,'Picks for Review (Sep 26)'!D:D)} | D31: Anushka Baisya | E31: 46281 | F31: Missing (Book 3, Book 5) | G31: Till Book 4 is available on goodreads
A32: Inheritance Trilogy | B32: Book 4 | C32: {=_xlfn.XLOOKUP(A32,'Picks for Review (Sep 26)'!A:A,'Picks for Review (Sep 26)'!D:D)} | D32: Anushka Baisya | E32: 46281 | F32: Missing (Book 4)
A33: Monsters Muses | B33: Book 4 | C33: {=_xlfn.XLOOKUP(A33,'Picks for Review (Sep 26)'!A:A,'Picks for Review (Sep 26)'!D:D)} | D33: Anushka Baisya | E33: 46281 | F33: Missing (Book 4)
A34: Underworld Saga | B34: Book 5 | C34: {=_xlfn.XLOOKUP(A34,'Picks for Review (Sep 26)'!A:A,'Picks for Review (Sep 26)'!D:D)} | D34: Anushka Baisya | E34: 46281 | F34: Missing (Book 5)
A35: The Wolves Of Ruin | B35: Book 3, Book 4 | C35: {=_xlfn.XLOOKUP(A35,'Picks for Review (Sep 26)'!A:A,'Picks for Review (Sep 26)'!D:D)} | D35: Anushka Baisya | E35: 46281 | F35: Missing (Book 3, Book 4) | G35: Till Book 3 is available on goodreads ; not able to find book 3
A36: Fae Kings Of Eden | B36: Book 5 | C36: {=_xlfn.XLOOKUP(A36,'Picks for Review (Sep 26)'!A:A,'Picks for Review (Sep 26)'!D:D)} | D36: Anushka Baisya | E36: 46281 | F36: Missing (Book 5) | G36: Till Book 4 is available on goodreads
A37: The Treasure Of Paragon | B37: Book 5 | C37: {=_xlfn.XLOOKUP(A37,'Picks for Review (Sep 26)'!A:A,'Picks for Review (Sep 26)'!D:D)} | D37: Anushka Baisya | E37: 46281 | F37: Missing (Book 5) | G37: updated
A38: Thorne Hill | B38: Book 2, Book 3, Book 4 | C38: {=_xlfn.XLOOKUP(A38,'Picks for Review (Sep 26)'!A:A,'Picks for Review (Sep 26)'!D:D)} | D38: Anushka Baisya | E38: 46281 | F38: Missing (Book 2, Book 3, Book 4)
A39: The Tether Trilogy | B39: Book 4, Book 5 | C39: {=_xlfn.XLOOKUP(A39,'Picks for Review (Sep 26)'!A:A,'Picks for Review (Sep 26)'!D:D)} | D39: Anushka Baisya | E39: 46281 | F39: Missing (Book 4, Book 5) | G39: Till Book 3 is available on goodreads
A40: Boston Uncommon | B40: Book 4, Book 5 | C40: {=_xlfn.XLOOKUP(A40,'Picks for Review (Sep 26)'!A:A,'Picks for Review (Sep 26)'!D:D)} | D40: Anushka Baisya | E40: 46281 | F40: Missing (Book 4, Book 5) | G40: updated
A41: Love And Light | B41: Book 2, Book 5 | C41: {=_xlfn.XLOOKUP(A41,'Picks for Review (Sep 26)'!A:A,'Picks for Review (Sep 26)'!D:D)} | D41: Anushka Baisya | E41: 46281 | F41: Missing (Book 2, Book 5) | G41: updated
A42: Grizzlies Gone Wild | B42: Book 3, Book 4, Book 5 | C42: {=_xlfn.XLOOKUP(A42,'Picks for Review (Sep 26)'!A:A,'Picks for Review (Sep 26)'!D:D)} | D42: Anushka Baisya | E42: 46281 | F42: Missing (Book 3, Book 4, Book 5) | G42: updated
A43: Kings Of Avalier | B43: Book 5 | C43: {=_xlfn.XLOOKUP(A43,'Picks for Review (Sep 26)'!A:A,'Picks for Review (Sep 26)'!D:D)} | D43: Anushka Baisya | E43: 46281 | F43: Missing (Book 5) | G43: Till Book 4 is available on goodreads
A44: Feline Royals | B44: Book 1 | C44: https://www.goodreads.com/series/268601-feline-royals | E44: 46281
A45: 悪役令嬢ですが攻略対象の様子が異常すぎる (Comic) Series | B45: All Books (1–5) | C45: https://www.goodreads.com/series/326634-comic | E45: 46281
A48: The Hollowmere Legacy | B48: Unavailable on public digital repositories | C48: https://www.goodreads.com/series/442416-the-hollowmere-legacy | D48: Sakshi Saxena | E48: 46281 | F48: done
A49: Blood Legacy Series | B49: 4 books complete, 1 book not available | C49: https://www.goodreads.com/series/296852-blood-legacy | D49: Sakshi Saxena | E49: 46281 | F49: done
A50: Viking Bloodlines Saga | B50: 2 books complete, 3 books not available | C50: https://www.goodreads.com/series/411566-viking-bloodlines-saga | D50: Sakshi Saxena | E50: 46281 | F50: Book 2.3.4 NA
A51: Mysterious Arts | B51: 3 books complete, 2 books not available | C51: https://www.goodreads.com/series/363248-mysterious-arts | D51: Sakshi Saxena | E51: 46281 | F51: Book 5 na
A52: The Shadow Atlas | B52: 2 books complete, 1 book not available | C52: https://www.goodreads.com/series/343295-the-shadow-atlas | D52: Sakshi Saxena | E52: 46281 | F52: done
A53: Annals of the Dragon Dreamer | B53: 3 books complete, 2 books not available | C53: https://www.goodreads.com/series/371468-annals-of-the-dragon-dreamer | D53: Sakshi Saxena | E53: 46281 | F53: Book 5 na
A54: The Brides of Bella Rosa | B54: 4 books complete, 1 book not available | C54: https://www.goodreads.com/series/115277-the-brides-of-bella-rosa | D54: Sakshi Saxena | E54: 46281 | F54: done
A55: Spellbound Universe | B55: Unavailable on public digital repositories | C55: https://www.goodreads.com/series/435521-spellbound-universe | D55: Sakshi Saxena | E55: 46281 | F55: Book 2.3.4,5 NA
A56: Prime Omegaverse | B56: 2 books complete, 3 books not available | C56: https://www.goodreads.com/series/443900-prime-omegaverse | D56: Sakshi Saxena | E56: 46281 | F56: done
A57: Dark Faeverse | B57: 2 books complete, 3 books not available | C57: https://www.goodreads.com/series/443903-dark-faeverse | D57: Sakshi Saxena | E57: 46281 | F57: done
A58: A LitRPG Harem Saga of Levels, Love, and Legendary Quests | B58: Unavailable on public digital repositories | C58: https://www.goodreads.com/series/419460-a-litrpg-harem-saga-of-levels-love-and-legendary-quests | D58: Sakshi Saxena | E58: 46281 | F58: done
A59: Savage Oaths | B59: 4 books complete, 1 book not available | C59: https://www.goodreads.com/series/438303-savage-oaths | D59: Sakshi Saxena | E59: 46281 | F59: Book 5 na
... A61: Cold Blades Book 1 of 1: Cold Blades | B61: Unavailable on public digital repositories | C61: https://www.goodreads.com/series/430461-nissai | D61: Vanshika V | E61: 46281 | F61: GR link is not correct
A62: Sundown Motorcycle Club | B62: 4 books complete, 1 book not available | C62: https://www.goodreads.com/series/368849-sundown-motorcycle-club | D62: Vanshika V | E62: 46281 | F62: Z lib not workinh | G62: https://drive.google.com/drive/folders/12Fz4evHedfA8qw6IsL3Ble_ajMNb7Hd-?usp=drive_link
A63: District of Wolf Desires | B63: 1 book complete, 4 books not available | C63: https://www.goodreads.com/series/409140-district-of-wolf-desires | D63: Vanshika V | E63: 46281
A64: EARTHBORN MONSTER LORD | B64: Unavailable on public digital repositories | C64: https://www.goodreads.com/series/435525-earthborn-monster-lord | D64: Vanshika V | E64: 46281 | F64: done | G64: https://drive.google.com/drive/folders/17l_kIDtD4NXKxsoWmeGCsyf48aq9Q9Qn?usp=drive_link
A65: From Two-Bit Baddie to Total Heartthrob: This Villainess Will Cross-Dress to Impress! | B65: 3 books complete, 2 books not available | C65: https://www.goodreads.com/series/398542-novel | D65: Vanshika V | E65: 46281 | F65: Not correct GR
A66: Liminal Mysteries | B66: 3 books complete, 2 books not available | C66: https://www.goodreads.com/series/409021-liminal-mysteries | D66: Vanshika V | E66: 46281 | F66: Done | G66: https://drive.google.com/drive/folders/1iGXbhsdS7LiaYDRJiKE7ycuHKY9bDbNv?usp=drive_link
A67: Dungeon Builder's Harem | B67: 3 books complete, 2 books not available | C67: https://www.goodreads.com/series/357833-dungeon-builder-s-harem | D67: Vanshika V | E67: 46281 | F67: done
A68: Hell of a Time | B68: 1 book complete, 1 book not available | C68: https://www.goodreads.com/series/448380-hell-of-a-time | D68: Vanshika V | E68: 46281 | F68: Not found
A69: Mafia & Scars | B69: Unavailable on public digital repositories | C69: https://www.goodreads.com/series/447430-mafia-scars | D69: Vanshika V | E69: 46281 | F69: Not found
A70: Their Precious Omega | B70: Book 4, 5 not found | C70: https://www.goodreads.com/series/384199-their-precious-omega | D70: Vanshika V | E70: 46281 | F70: done | G70: https://drive.google.com/drive/folders/19C9p23RuWNq-aPtsepTjL3yqZAxvC9Rf?usp=drive_link
A71: My Hero Academia: Vigilantes | B71: Book 1-5 all not found | C71: https://www.goodreads.com/series/199545-illegals-vigilante-boku-no-hero-academia-illegals | D71: Vanshika V | E71: 46281 | F71: Not correct GR
A72: Vancouver Havoc series Book 1 of 4: Vancouver Havoc series | B72: Book 3,4 not found | D72: Anushka Baisya | E72: 46281 | F72: Only book 3 found
A73: V-Clan | B73: Book 4 not found | C73: https://www.goodreads.com/series/323132-v-clan | D73: Anushka Baisya | E73: 46281 | F73: Done
A74: Succubus Divinity | B74: Book 1-5 all not found | C74: https://www.goodreads.com/book/show/234554747-succubus-divinity | D74: Anushka Baisya | E74: 46281 | F74: Not found
A75: Twisted Kings MC | B75: book 5 not found | C75: https://www.goodreads.com/series/401927-twisted-kings-mc | D75: Anushka Baisya | E75: 46281 | F75: Done
A76: Love Sequence | B76: Book 4-5 not found | C76: https://www.goodreads.com/series/399702-love-sequence | D76: Anushka Baisya | E76: 46281 | F76: Done
A77: WarBride | B77: Book 4 not found | C77: https://www.goodreads.com/series/395081-warbride | D77: Anushka Baisya | E77: 46281 | F77: Done
A78: Mating Season Series | B78: Book 4 not found | C78: https://www.goodreads.com/series/397063-mating-season | D78: Anushka Baisya | E78: 46281 | F78: Done
A79: Spookshow | B79: book 5 not found | C79: https://www.goodreads.com/series/164031-spookshow | D79: Anushka Baisya | E79: 46281 | F79: Done
A80: Charmed Away Temp Agency | B80: Book 4-5 not found | C80: https://www.goodreads.com/series/411961-charmed-away-temp-agency | D80: Anushka Baisya | E80: 46281 | F80: Done
A81: Supernatural Community | B81: book 5 not found | C81: https://www.goodreads.com/series/278088-supernatural-community | D81: Anushka Baisya | E81: 46281 | F81: Done
A82: Seven Deadly Demons | B82: book 3-4 not found | C82: https://www.goodreads.com/series/363922-seven-deadly-demons | D82: Anushka Baisya | E82: 46281 | F82: Done
A83: The Kingdoms of Gyldren | B83: 5 | C83: https://www.goodreads.com/series/338003-the-kingdoms-of-gyldren | D83: Sakshi Saxena | E83: 46282 | F83: Done
A84: Rise of the Cheat Potion Maker | B84: 5 | C84: https://www.goodreads.com/series/349821-rise-of-the-cheat-potion-maker | D84: Sakshi Saxena | E84: 46282 | F84: Done
A85: The Witch's Monsters | B85: 4 | C85: https://www.goodreads.com/series/313790-the-witch-s-monsters | D85: Sakshi Saxena | E85: 46282 | F85: Done
A86: Rise of the Pride | B86: 1 | C86: https://www.goodreads.com/series/198974-rise-of-the-pride | D86: Sakshi Saxena | E86: 46282 | F86: Done
A87: Gothic Love Stories | B87: 2 | C87: https://www.goodreads.com/series/114464-gothic-love-stories | D87: Sakshi Saxena | E87: 46282 | F87: Done
A88: Rites of Possession | B88: 4 | C88: https://www.goodreads.com/series/381649-rites-of-possession | D88: Sakshi Saxena | E88: 46282 | F88: Done
A89: Past Life Hero | B89: 1, 4, | C89: https://www.goodreads.com/series/403312-past-life-hero | D89: Sakshi Saxena | E89: 46282 | F89: Done
A90: The Buried and the Bound | B90: 3 | C90: https://www.goodreads.com/series/324232-the-buried-and-the-bound | D90: Sakshi Saxena | E90: 46282 | F90: Done
A91: Sold to the Raksha | B91: 3 | C91: https://www.goodreads.com/series/337115-sold-to-the-raksha | D91: Sakshi Saxena | E91: 46282 | F91: Done
A92: Kingdom of Blighted Thorns | B92: 3 | C92: https://www.goodreads.com/series/393596-kingdom-of-blighted-thorns | D92: Sakshi Saxena | E92: 46282 | F92: Done
A93: The Magi Accounts | B93: 5 | C93: https://www.goodreads.com/series/333937-the-magi-accounts | D93: Sakshi Saxena | E93: 46282 | F93: Done
A94: The Dark Forgotten | B94: 46058 | C94: https://www.goodreads.com/series/46164-the-dark-forgotten | D94: Sakshi Saxena | E94: 46282 | F94: Done
A95: The Lost Girl | B95: 46117 | C95: https://www.goodreads.com/series/428800-the-lost-girl | D95: Sakshi Saxena | E95: 46282 | F95: Done
A96: Court of Broken Bonds | B96: 46117 | C96: https://www.goodreads.com/series/307550-court-of-broken-bonds | D96: Sakshi Saxena | E96: 46282 | F96: Done
A97: Soul Mates | B97: 38356 | C97: https://www.goodreads.com/series/43142-soul-mates | D97: Sakshi Saxena | E97: 46282 | F97: NA
A98: Midlife Magic and Mates | B98: 5 | C98: https://www.goodreads.com/series/348267-midlife-magic-and-mates | D98: Sakshi Saxena | E98: 46282 | F98: Done
A99: International Billionaires | B99: 46027 | C99: https://www.goodreads.com/series/175055-international-billionaires | D99: Sakshi Saxena | E99: 46282 | F99: Done
A100: Supernatural Speakeasy | B100: 46025 | C100: https://www.goodreads.com/series/279109-supernatural-speakeasy | D100: Sakshi Saxena | E100: 46282 | F100: Done
A101: Timeless | B101: 5 | C101: https://www.goodreads.com/series/68238-timeless | D101: Sakshi Saxena | E101: 46282 | F101: Book 5 NA im GR
... A103: Fix-It Witches | B103: 5 | C103: https://www.goodreads.com/series/307007-fix-it-witches | D103: Sakshi Saxena | E103: 46282 | F103: Done
A104: Sinner's Bay | B104: 1, 2, 3, 4, 5 | C104: https://www.goodreads.com/series/378672-sinner-s-bay | D104: Sakshi Saxena | E104: 46282 | F104: NA
A105: Exemplar Hall | B105: 2, 3, 4, 5 | C105: https://www.goodreads.com/series/287133-exemplar-hall | D105: Sakshi Saxena | E105: 46282 | F105: Done
A106: Royally Unexpected | B106: 1, 2, 3, 4, 5 | C106: https://www.goodreads.com/series/296103-royally-unexpected | D106: Sakshi Saxena | E106: 46282 | F106: Done
A107: Maya's Blog | B107: 1, 2, 3, 4, 5 | C107: https://www.goodreads.com/series/432878-maya-s-blog | D107: Sakshi Saxena | E107: 46282 | F107: Done
...

Sheet Batch 1 - 229
A1: Series Name | B1: Author | C1: Sub-Genre | D1: Book Series (GoodReads URL) | E1: GoodReads No. of Ratings | F1: Goodreads Book 1 Ratings | G1: Total Primary Books | H1: Total primary Books Page Count | I1: Imprint / Publisher - Book | J1: Agencies | K1: Imprint / Publisher - Audiobook | L1: Crawling POC | M1: Crawling Date | N1: Links addition POC | O1: Links Date | P1: Book 1 Link | Q1: Books (1 - 5) Links
A2: Green Creek | B2: Kelly Bennett | C2: Paranormal Romance | D2: https://www.goodreads.com/series/206510-green-creek | E2: 118376 | F2: 4.18 | G2: 4 | H2: 118376 | I2: Indie / Self-Published | J2: Metamorphosis Literary Agency | L2: Vanshika V | M2: 46283 | N2: Vanshika V | P2: https://docs.google.com/document/d/102Co9URvI7NHwz65ofheImstJmx3_C2w/edit?usp=drive_link&ouid=101023058405307348147&rtpof=true&sd=true | Q2: https://drive.google.com/drive/folders/15WyC66FwRnei2POYs01P4BHDFr_5dLPr?usp=drive_link
A3: Air Awakens | B3: Elise Fender Burns | C3: High Fantasy Court Adventure | D3: https://www.goodreads.com/series/155275-air-awakens | E3: 63472 | F3: 3.97 | G3: 5 | H3: 63472 | I3: Indie / Self-Published | J3: Metamorphosis Literary Agency | L3: Vanshika V | M3: 46283 | N3: Vanshika V | P3: https://docs.google.com/document/d/1a42Nqridsbx5sLJgnfsjtz_tM0HKN4Lm/edit?usp=drive_link&ouid=101023058405307348147&rtpof=true&sd=true | Q3: https://drive.google.com/drive/folders/1Z8o5jSlW3Bq8CpAyuYG0Opo3jnRKwAqb?usp=drive_link
A4: Warrior Security | B4: Brittany Cooper | C4: High-Stakes Games & Deadly Trials | D4: https://www.goodreads.com/series/426999-warrior-security | E4: 2310 | F4: 4.47 | G4: 5 | H4: 2310 | I4: Indie / Self-Published | J4: Metamorphosis Literary Agency | L4: Vanshika V | M4: 46283 | N4: Vanshika V | P4: https://docs.google.com/document/d/1uGe-oUialP2el1Y3fhEazOkMe1ixL1Sf/edit?usp=drive_link&ouid=101023058405307348147&rtpof=true&sd=true | Q4: https://drive.google.com/drive/folders/1GRRhk2RsoERxTDphHtU0G_6kKP5UTafA?usp=drive_link
A5: Fire And Fang | B5: Lindsay Flanagan | C5: High Fantasy Court Adventure | D5: https://www.goodreads.com/series/428113-fire-and-fang | E5: 3087 | F5: 4.07 | G5: 5 | H5: 3087 | I5: Indie / Self-Published | J5: Metamorphosis Literary Agency | L5: Vanshika V | M5: 46283 | N5: Vanshika V | P5: https://docs.google.com/document/d/1pDpQYoA6iNGrpTRf35YkQ72AulEuFaRE/edit?usp=drive_link&ouid=101023058405307348147&rtpof=true&sd=true | Q5: https://drive.google.com/drive/folders/11Ac4Iz28Vn5AQpHld3YGDFg2606IfaR6?usp=drive_link
A6: Shatter Me | B6: Tahereh Mafi | C6: Paranormal Romance | D6: https://www.goodreads.com/series/65730-shatter-me | E6: 1260128 | F6: 3.84 | G6: 12 | H6: 2481 | I6: Storytide | K6: Storytide | L6: Noel Regis | M6: 46282 | P6: 1_Shatter Me.docx | Q6: 11_Shatter Me
A7: This Woven Kingdom | B7: Tiffany W. Killoren | C7: Mythology, Legend & Fairy Tale Retelling | D7: https://www.goodreads.com/series/319224-this-woven-kingdom | E7: 119741 | F7: 4.28 | G7: 5 | H7: 119741 | I7: Indie / Self-Published | J7: Metamorphosis Literary Agency | L7: Vanshika V | M7: 46283 | N7: Vanshika V | P7: https://docs.google.com/document/d/1wxQ6oyhK93uhZ1Vu_KLr2C3GVXtcOz_k/edit?usp=drive_link&ouid=101023058405307348147&rtpof=true&sd=true | Q7: https://drive.google.com/drive/folders/11ZUWyaB1f9-L9YCg_WmD7oXTFWU3wwEU?usp=drive_link
A8: Tiffany Black Mysteries | B8: Tiffany W. Killoren | C8: Cozy / Cottagecore Romantasy | D8: https://www.goodreads.com/series/124119-tiffany-black-mysteries | E8: 10545 | F8: 3.71 | G8: 37 | H8: 10545 | I8: Indie / Self-Published | J8: Metamorphosis Literary Agency | L8: Vanshika V | M8: 46283 | N8: Vanshika V | P8: https://docs.google.com/document/d/1ALVv-mpE7V69_4xV4EZZQBBOL08me4xH/edit?usp=drive_link&ouid=101023058405307348147&rtpof=true&sd=true | Q8: https://drive.google.com/drive/folders/1mH43uDPXFbMxk1g9WCgnxqnt-IJgjqmS?usp=drive_link
A9: Arcane Society | B9: Mike Krentz | C9: Paranormal Romance | D9: https://www.goodreads.com/series/57569-arcane-society | E9: 16119 | F9: 3.91 | G9: 12 | H9: 16119 | I9: Indie / Self-Published | J9: Metamorphosis Literary Agency | L9: Vanshika V | M9: 46283 | N9: Vanshika V | P9: https://docs.google.com/document/d/1WKhrsKagyScv3YdVnxwWaAPu3H37_vc6/edit?usp=drive_link&ouid=101023058405307348147&rtpof=true&sd=true | Q9: https://drive.google.com/drive/folders/1BCNS4Cq-JEWdGzXyBnoiW81CzBAbnWoS?usp=drive_link
A10: Fae & Alchemy | B10: Callie Hart | C10: High Fantasy Court Adventure | D10: https://www.goodreads.com/series/392242-fae-alchemy | E10: 987885 | F10: 4.3 | G10: 4 | H10: 3216 | I10: Podium Audio | J10: New Keywords - Amazon | L10: Noel Regis | M10: 46282 | P10: 1_Quicksilver_-_Callie_Hart.docx | Q10: Fae & Alchemy Series
A11: Red Rising | B11: Pierce Brown | C11: Paranormal Romance | D11: https://www.goodreads.com/series/117100-red-rising-saga | E11: 853673 | F11: 4.27 | G11: 18 | H11: 8359 | I11: Recorded Books | K11: Recorded Books | L11: Noel Regis | M11: 46282 | N11: Sakshi Saxena | O11: 46286 | P11: 1_Red Rising.docx | Q11: 17_Red Rising Saga by Pierce Brown
A12: The Witchlands | B12: Kathy MacMillan | C12: High Fantasy Court Adventure | D12: https://www.goodreads.com/series/124183-the-witchlands | E12: 53820 | F12: 3.84 | G12: 5 | H12: 53820 | I12: Indie / Self-Published | J12: Metamorphosis Literary Agency | L12: Vanshika V | M12: 46283 | N12: Vanshika V | P12: https://docs.google.com/document/d/1adWWq7op5vLWMCttQ1VPvc5T4dOFtTJJ/edit?usp=drive_link&ouid=101023058405307348147&rtpof=true&sd=true | Q12: https://drive.google.com/drive/folders/18PRRzh_bCalyoHm28jlcBL3s1HXZsokb?usp=drive_link
A13: The Captive | B13: Erica Spiller | C13: Paranormal Romance | D13: https://www.goodreads.com/series/86676-the-captive | E13: 21690 | F13: 4.02 | G13: 8 | H13: 21690 | I13: Indie / Self-Published | J13: Metamorphosis Literary Agency | L13: Vanshika V | M13: 46283 | N13: Vanshika V | P13: https://docs.google.com/document/d/1AZ72q7C8i_7omvj052THx2y2GU2asMRf/edit?usp=drive_link&ouid=101023058405307348147&rtpof=true&sd=true | Q13: https://drive.google.com/drive/folders/1N4b9VEqoo2FBz5hKijQbMEwgVsajsyoz?usp=drive_link
A14: The Others | B14: Annie Smith | C14: Werewolf / Shifter Romance | D14: https://www.goodreads.com/series/99557-the-others | E14: 65629 | F14: 4.25 | G14: 10 | H14: 65629 | I14: Indie / Self-Published | J14: Jane Rotrosen Agency | L14: Vanshika V | M14: 46283 | N14: Vanshika V | P14: https://docs.google.com/document/d/12wZLqtIre7YvQctzS7xuAqT-CWOjX2GN/edit?usp=drive_link&ouid=101023058405307348147&rtpof=true&sd=true | Q14: https://drive.google.com/drive/folders/1_up8L0uC7UerTxoII-taECBEt7OvsSrC?usp=drive_link
A15: Blood And Ash World Reading Order | B15: Asha Lemmie | C15: High Fantasy Court Adventure | D15: https://www.goodreads.com/series/426746-blood-and-ash-world-reading-order | E15: 897900 | F15: 4.21 | G15: 11 | H15: 897900 | I15: Indie / Self-Published | J15: Jane Rotrosen Agency | L15: Vanshika V | M15: 46283 | N15: Vanshika V | P15: https://docs.google.com/document/d/135ekbg0UiYUSyVy8jO6tQ5AlJfQuRkV8/edit?usp=drive_link&ouid=101023058405307348147&rtpof=true&sd=true | Q15: https://drive.google.com/drive/folders/15Lw_RHugBnrWsrOGJ7oRPjcoMipkUPbM?usp=drive_link
A16: Ravenhood Legacy Trilogy | B16: Curtiss Ann Matlock | C16: High Fantasy Court Adventure | D16: https://www.goodreads.com/series/372640-ravenhood-legacy-trilogy | E16: 60193 | F16: 4.52 | G16: 3 | H16: 60193 | I16: Indie / Self-Published | J16: Jane Rotrosen Agency | L16: Vanshika V | M16: 46283 | N16: Vanshika V | P16: https://docs.google.com/document/d/1YkcNeT5boR5hp_Lr3OKZQHp-7p4a93vS/edit?usp=drive_link&ouid=101023058405307348147&rtpof=true&sd=true | Q16: https://drive.google.com/drive/folders/1WZJ1zyPhIBhPxS9GBC-1smJcFWeK30hX?usp=drive_link
A17: The Iron Fey | B17: Julie Garwood | C17: High Fantasy Court Adventure | D17: https://www.goodreads.com/series/47329-the-iron-fey | E17: 219403 | F17: 3.87 | G17: 10 | H17: 219403 | I17: Indie / Self-Published | J17: Jane Rotrosen Agency | L17: Vanshika V | M17: 46283 | N17: Vanshika V | P17: https://docs.google.com/document/d/1YafY33HU-RojH2WvpBBn-RiwK9oDIvKe/edit?usp=drive_link&ouid=101023058405307348147&rtpof=true&sd=true | Q17: https://drive.google.com/drive/folders/1YjJfGoDVMlRhji1WdLfrqE4lTkwqkVw0?usp=drive_link
A18: The Marionettes | B18: Katie Lynch | C18: Paranormal Romance | D18: https://www.goodreads.com/series/320243-the-marionettes | E18: 9696 | F18: 3.88 | G18: 4 | H18: 9696 | I18: Indie / Self-Published | J18: Jane Rotrosen Agency | L18: Vanshika V | M18: 46283 | N18: Vanshika V | P18: https://docs.google.com/document/d/1prG7-cor9WE9I-H8dKnBTomzoCU8YK-t/edit?usp=drive_link&ouid=101023058405307348147&rtpof=true&sd=true | Q18: https://drive.google.com/drive/folders/1jFopVdx_P4ISQ_xIB2AUTJI0l0vNy03X?usp=drive_link
A19: Cassandra Palmer | B19: Matthew Palmer | C19: Urban / Contemporary Fantasy Romance | D19: https://www.goodreads.com/series/49237-cassandra-palmer | E19: 37083 | F19: 3.72 | G19: 14 | H19: 37083 | I19: Indie / Self-Published | J19: Jane Rotrosen Agency | L19: Vanshika V | M19: 46283 | N19: Vanshika V | P19: https://docs.google.com/document/d/1E8h2XWibVtYByhgI5qhzIFNRJMz2p55X/edit?usp=drive_link&ouid=101023058405307348147&rtpof=true&sd=true | Q19: https://drive.google.com/drive/folders/1WZ1OLSkrK9l-rWgXg6Hx7YzLEyKMLhSz?usp=drive_link
A20: Meg Langslow | B20: Meg Shaffer | C20: Cozy / Cottagecore Romantasy | D20: https://www.goodreads.com/series/41805-meg-langslow | E20: 14392 | F20: 3.89 | G20: 41 | H20: 14392 | I20: Indie / Self-Published | J20: Jane Rotrosen Agency | L20: Vanshika V | M20: 46283 | N20: Vanshika V | P20: https://docs.google.com/document/d/1KyUk6Z2rCFSa20m2bM2ayySgkswWdYw0/edit?usp=drive_link&ouid=101023058405307348147&rtpof=true&sd=true | Q20: https://drive.google.com/drive/folders/1jAYGNYCy4bjjfdMkmc6J--mysTfXq5GF?usp=drive_link
A21: 1 800 Where R You | B21: Meg Shaffer | C21: Paranormal Romance | D21: https://www.goodreads.com/series/40569-1-800-where-r-you | E21: 17799 | F21: 4.05 | G21: 7 | H21: 17799 | I21: Indie / Self-Published | J21: Jane Rotrosen Agency | L21: Vanshika V | M21: 46283 | N21: Vanshika V | P21: https://docs.google.com/document/d/1a_DBroEYhDYUZZ_9pA2J-tEKP-7lpp7b/edit?usp=drive_link&ouid=101023058405307348147&rtpof=true&sd=true | Q21: https://drive.google.com/drive/folders/1ORWEGkxAzBEPEiIJ5U7D_jACG9kTicZD?usp=drive_link
A22: Aunt Dimity Mystery | B22: Nancy Atherton | C22: Cozy / Cottagecore Romantasy | D22: https://www.goodreads.com/series/42315-aunt-dimity-mystery | E22: 15716 | F22: 3.95 | G22: 25 | H22: 15716 | I22: Indie / Self-Published | J22: Jane Rotrosen Agency | L22: Vanshika V | M22: 46283 | N22: Vanshika V | P22: https://docs.google.com/document/d/1k537Q7hk_uLa8koJCiopQKCD7n0VZVvU/edit?usp=drive_link&ouid=101023058405307348147&rtpof=true&sd=true | Q22: https://drive.google.com/drive/folders/1t2XtLfUaXUijVJvATgs_M6fbj1ClrCxB?usp=drive_link
A23: Goddess Summoning | B23: PC Cast | C23: Mythology, Legend & Fairy Tale Retelling | D23: https://www.goodreads.com/series/40627-goddess-summoning | E23: 12053 | F23: 3.84 | G23: 7 | H23: 12053 | I23: Indie / Self-Published | J23: Jane Rotrosen Agency | L23: Vanshika V | M23: 46283 | N23: Vanshika V | P23: https://docs.google.com/document/d/1m5ddGHE0oC5Yhr-UlhC-AyhhskRA7LT0/edit?usp=drive_link&ouid=101023058405307348147&rtpof=true&sd=true | Q23: https://drive.google.com/drive/folders/1egk-g5YU6w5PXma37P3eAij3X2xp5NLa?usp=drive_link
... A29: Sweet | B29: Wendy Francis | C29: Paranormal Romance | D29: https://www.goodreads.com/series/83847-sweet | E29: 78102 | F29: 4.07 | G29: 4 | H29: 78102 | I29: Indie / Self-Published | J29: Jane Rotrosen Agency | L29: Vanshika V | M29: 46283 | N29: Vanshika V | P29: https://docs.google.com/document/d/1cLsmb1DanTTriXKLm_yIc0RdsGv0hukn/edit?usp=drive_link&ouid=101023058405307348147&rtpof=true&sd=true | Q29: https://drive.google.com/drive/folders/1A9PP1ZXzw2XKdTQG6BJbBKozIKwMrqdv?usp=drive_link
A30: Dark Verse | B30: RuNyx | C30: Gothic Dark Romantasy | D30: https://www.goodreads.com/series/287221-dark-verse | E30: 146216 | F30: 3.97 | G30: 7 | H30: 4312 | I30: P1: Amazon Digital Services | P2: Smashwords | K30: Podium Audio | L30: Noel Regis | M30: 46282 | N30: Sakshi Saxena | O30: 46286 | P30: 1_The Predator.docx | Q30: 62_Dark Verse
A31: Bloodwing Academy | B31: Briar Boleyn | C31: Gothic Dark Romantasy | D31: https://www.goodreads.com/series/390267-bloodwing-academy | E31: 127131 | F31: 3.91 | G31: 3 | H31: 1418 | I31: Podium Audio | J31: Self-Represented / N/A | K31: Podium Audio | L31: Noel Regis | M31: 46282 | N31: Sakshi Saxena | O31: 46286 | P31: 1_On Wings of Blood.docx | Q31: 67_Bloodwing Academy
A32: Crave | B32: Tracy Wolff | C32: Mythology, Legend & Fairy Tale Retelling | D32: https://www.goodreads.com/series/286781-crave | E32: 119076 | F32: 3.76 | G32: 21 | H32: 11803 | I32: Entangled Publishing | K32: Tantor Media | L32: Noel Regis | M32: 46282 | N32: Sakshi Saxena | O32: 46286 | P32: 1_Crave.docx | Q32: 71_Crave
A33: Perfectly Imperfect | B33: Neva Altaj | C33: Urban / Contemporary Fantasy Romance | D33: https://www.goodreads.com/series/343844-perfectly-imperfect | E33: 118006 | F33: 3.73 | G33: 13 | H33: 4497 | I33: Neva Altaj | K33: Podium Audio | L33: Noel Regis | M33: 46282 | N33: Sakshi Saxena | O33: 46286 | P33: 1_Painted Scars.docx | Q33: 72_Perfectly Imperfect
A34: Covenant Series | B34: Jennifer L. Armentrout | C34: Mythology, Legend & Fairy Tale Retelling | D34: https://www.goodreads.com/series/53954-covenant | E34: 116532 | F34: 4.06 | G34: 5 | H34: 1580 | I34: Self Published | K34: Tantor Media | L34: Noel Regis | M34: 46282 | N34: Sakshi Saxena | O34: 46286 | P34: 1_Half-Blood.docx | Q34: 73_Covenant
A35: Alliance | B35: S.J. Tilly | C35: Urban / Contemporary Fantasy Romance | D35: https://www.goodreads.com/series/362029-alliance | E35: 95274 | F35: 3.81 | G35: 4 | H35: 1668 | I35: Amazon Digital Services | K35: Podium Audio | L35: Noel Regis | M35: 46282 | N35: Sakshi Saxena | O35: 46286 | P35: 1_Nero.docx | Q35: 78_Alliance
A36: The Dark Elements | B36: Jennifer L. Armentrout | C36: Gothic Dark Romantasy | D36: https://www.goodreads.com/series/98903-the-dark-elements | E36: 91654 | F36: 4.16 | G36: 3 | H36: 1219 | I36: Tantor Audio | J36: Self-Represented / N/A | K36: Tantor Media | L36: Noel Regis | M36: 46282 | N36: Sakshi Saxena | O36: 46286 | P36: 1_White Hot Kiss.docx | Q36: 79_The Dark Elements
A37: Damaged Souls: A Reverse Harem Fantasy Romance (Saints Academy Book 2) | B37: Kayla Edwards | C37: Modern Low Fantasy | D37: https://www.goodreads.com/series/335398-house-of-devils | E37: 85699 | F37: 3.76 | G37: 6 | H37: 3081 | I37: Scarlett Press | K37: Podium Audio | L37: Noel Regis | M37: 46282 | N37: Sakshi Saxena | O37: 46286 | P37: 1_City of Gods and Monsters.docx | Q37: 82_House of Devils
A38: Cambric Creek: Sweet & Steamy Monster Romance | B38: C.M. Nascosta | C38: Werewolf / Shifter Romance | D38: https://www.goodreads.com/series/324507-cambric-creek | E38: 80068 | F38: 3.56 | G38: 5 | H38: 1328 | I38: Tantor Media | J38: Self-Represented / N/A | K38: Tantor Media | L38: Noel Regis | M38: 46282 | N38: Sakshi Saxena | O38: 46286 | P38: 1_Morning Glory Milking Farm.docx | Q38: 84_Cambric Creek
A39: Psy-Changeling | B39: Nalini Singh | C39: Werewolf / Shifter Romance | D39: https://www.goodreads.com/series/41454-psy-changeling | E39: 79221 | F39: 4.08 | G39: 25 | H39: 9672 | I39: Penguin Random House | K39: Tantor Media | L39: Noel Regis | M39: 46282 | N39: Sakshi Saxena | O39: 46286 | P39: 1_Slave to Sensation.docx | Q39: 85_Psy-Changeling
A40: Gods Monsters | B40: Amber V. Nicole | C40: High-Stakes Games & Deadly Trials (Done) | D40: https://www.goodreads.com/series/344354-gods-monsters | E40: 68914 | F40: 4.12 | G40: 5 | H40: 2554 | I40: Penguin Random House | K40: Penguin Random House | L40: Noel Regis | M40: 46282 | N40: Sakshi Saxena | O40: 46286 | P40: 1_The Book of Azrael.docx | Q40: 90_Gods & Monsters
A41: Ravenhood Legacy | B41: Kate Stewart | C41: High Fantasy Court Adventure | D41: https://www.goodreads.com/series/372640-ravenhood-legacy | E41: 56519 | F41: 4.51 | G41: 3 | H41: 1440 | I41: Kensington Publishers | K41: Podium Audio | L41: Noel Regis | M41: 46282 | N41: Sakshi Saxena | O41: 46286 | P41: 1_One Last Rainy Day The Legacy of a Prince.docx | Q41: 96_Ravenhood Legacy Trilogy by Kate Stewart
A42: New York Ruthless | B42: Sadie Kincaid | C42: Gothic Dark Romantasy | D42: https://www.goodreads.com/series/338189-new-york-ruthless | E42: 52627 | F42: 3.89 | G42: 5 | H42: 1392 | I42: Red House Press Ltd | K42: Podium Audio | L42: Noel Regis | M42: 46282 | N42: Sakshi Saxena | O42: 46286 | P42: 1_Ryan Rule.docx | Q42: 100_New York Ruthless
A43: Ti N Gu N C F | B43: Ninan Tan | C43: High Fantasy Court Adventure | D43: https://www.goodreads.com/series/324340-ti-n-gu-n-c-f | E43: 50031 | F43: 4.58 | G43: 8 | H43: 3425 | I43: Indie / Self-Published | J43: Metamorphosis Literary Agency | L43: Noel Regis | M43: 46282 | N43: Noel Regis | P43: 1_Heaven Official's Blessing Tian Guan Ci Fu, Vol. 1.docx | Q43: 天官赐福 [Tiān Guān Cì Fú]
A44: Kings of Mafia | B44: Michelle Heard | C44: Gothic Dark Romantasy | D44: https://www.goodreads.com/series/352300-kings-of-mafia | E44: 43705 | F44: 3.82 | G44: 10 | H44: 3464 | I44: MA Heard | K44: Podium Audio | L44: Noel Regis | M44: 46282 | N44: Sakshi Saxena | O44: 46286 | P44: 1_Tempted by the Devil.docx | Q44: 106_Kings of Mafia
A45: He Who Fights with Monsters | B45: Shirtaloon | C45: High Fantasy Court Adventure | D45: https://www.goodreads.com/series/319859-he-who-fights-with-monsters | E45: 43242 | F45: 4.33 | G45: 13 | H45: 8121 | I45: Self Published | K45: Podium Audio | L45: Noel Regis | M45: 46282 | N45: Sakshi Saxena | O45: 46286 | P45: 1_He Who Fights with Monsters.docx | Q45: 107_He Who Fights with Monsters
A46: Savage Lands | B46: Stacey Marie Brown | C46: High Fantasy Court Adventure | D46: https://www.goodreads.com/series/301855-savage-lands | E46: 41945 | F46: 4.08 | G46: 8 | H46: 3273 | I46: P1: Twisted Fairy Publishing | P2: Self Published | P3: Amazon Digital Services | K46: Podium Audio | L46: Noel Regis | M46: 46282 | N46: Sakshi Saxena | O46: 46286 | P46: 1_Savage Lands.docx | Q46: 108_Savage Lands
A47: Soulbound | B47: Hailey Turner | C47: Mythology, Legend & Fairy Tale Retelling | D47: https://www.goodreads.com/series/242470-soulbound | E47: 38168 | F47: 4.13 | G47: 8 | H47: 4910 | I47: ), Gary Furlong (Narrator) Format: Audible Audiobook | J47: New Keywords - Amazon | L47: Noel Regis | M47: 46282 | N47: Noel Regis | P47: 1_A Ferry of Bones & Gold.docx | Q47: Soulbound
A48: Kings of Avalier | B48: Leia Stone | C48: Gothic Dark Romantasy | D48: https://www.goodreads.com/series/348076-kings-of-avalier | E48: 37884 | F48: 3.64 | G48: 4 | H48: 1373 | I48: Indie / Self-Published | J48: Seymour | K48: Audible Studios | L48: Noel Regis | M48: 46282 | N48: Noel Regis | P48: 1_The Last Dragon King.docx | Q48: Kings of Avalier
A49: Ruthless People | B49: J. J. McAvoy | C49: High Fantasy Court Adventure | D49: https://www.goodreads.com/series/125840-ruthless-people | E49: 37354 | F49: 3.87 | G49: 4 | H49: 1811 | I49: Indie / Self-Published | J49: New Keywords - Amazon | L49: Noel Regis | M49: 46282 | N49: Noel Regis | P49: 1_Ruthless People.docx | Q49: Ruthless People
A50: The Royal Coven | B50: Juno Dawson | C50: Urban / Contemporary Fantasy Romance | D50: https://www.goodreads.com/series/309884-her-majesty-s-royal-coven | E50: 36589 | F50: 3.82 | G50: 3 | H50: 1449 | I50: Indie / Self-Published | J50: Self-Represented / N/A | K50: Audible Studios | L50: Noel Regis | M50: 46282 | N50: Noel Regis | P50: 1_Her Majesty's Royal Coven.docx | Q50: Her Majesty's Royal Coven
A51: Men of the North | B51: Lillian Lark | C51: High Fantasy Court Adventure | D51: https://www.goodreads.com/series/210714-men-of-the-north | E51: 36564 | F51: 3.81 | G51: 17 | H51: 6830 | I51: Indie / Self-Published | J51: New Keywords - Amazon | L51: Noel Regis | M51: 46282 | N51: Noel Regis | P51: 1_The Protector.docx | Q51: Men of the North
A52: Fae of Snow & Ice | B52: Krista Street | C52: Gothic Dark Romantasy | D52: https://www.goodreads.com/series/376683-fae-of-snow-ice | E52: 36405 | F52: 4.12 | G52: 4 | H52: 1522 | I52: Indie / Self-Published | J52: Self-Represented / N/A | K52: Indie / Self-Published | L52: Noel Regis | M52: 46282 | N52: Noel Regis | P52: 1_Court of Winter.docx | Q52: Fae of Snow & Ice
A53: The House Witch | B53: Delemhach | C53: Monster Romance (Non-Shifter) | D53: https://www.goodreads.com/series/351251-the-house-witch | E53: 36260 | F53: 4.1 | G53: 4 | H53: 1620 | I53: Self Published | K53: Podium Audio | L53: Noel Regis | M53: 46282 | N53: Sakshi Saxena | O53: 46286 | P53: 1_The House Witch.docx | Q53: The House Witch
A54: M D O Z Sh | B54: Ninan Tan | C54: High Fantasy Court Adventure | D54: https://www.goodreads.com/series/324303-m-d-o-z-sh | E54: 35363 | F54: 4.55 | G54: 5 | H54: 2046 | I54: Indie / Self-Published | J54: Metamorphosis Literary Agency | L54: Noel Regis | M54: 46282 | N54: Noel Regis | P54: 1_Burn.docx | Q54: Dark in You
A55: The Dark in You | B55: Suzanne Wright | C55: Gothic Dark Romantasy | D55: https://www.goodreads.com/series/154603-dark-in-you | E55: 34858 | F55: 4.05 | G55: 11 | H55: 4019 | I55: Piatkus | J55: New Keywords - Amazon | L55: Noel Regis | M55: 46282 | N55: Noel Regis | P55: 1_Kings of Quarantine.docx | Q55: Brutal Boys of Everlake Prep
A56: Brutal Boys of Everlake Prep | B56: Caroline Peckham | C56: Dark Academia Romantasy | D56: https://www.goodreads.com/series/286127-brutal-boys-of-everlake-prep | E56: 34490 | F56: 4.14 | G56: 5 | H56: 2906 | I56: Caroline Peckham / Susanne Valenti | K56: Caroline Peckham / Susanne Valenti | L56: Noel Regis | M56: 46282 | N56: Sakshi Saxena | O56: 46286 | P56: 1_Kings of Quarantine.docx | Q56: Brutal Boys of Everlake Prep
A57: Mythos Academy | B57: Jennifer Estep | C57: War College / Military Academy | D57: https://www.goodreads.com/series/51545-mythos-academy | E57: 34140 | F57: 3.94 | G57: 6 | H57: 2167 | I57: Kensington Teen | J57: New Keywords - Amazon | L57: Noel Regis | M57: 46282 | N57: Noel Regis | P57: 1_Touch of Frost.docx | Q57: Mythos Academy
A58: Kitty Norville | B58: Brenda Trim | C58: High Fantasy Court Adventure | D58: https://www.goodreads.com/series/40485-kitty-norville | E58: 34051 | F58: 3.69 | G58: 17 | H58: 5523 | I58: Indie / Self-Published | J58: New Keywords - Amazon | L58: Noel Regis | M58: 46282 | N58: Noel Regis | P58: 1_Kitty and the Midnight Hour.docx | Q58: Kitty Norville
A59: The Talon Saga | B59: Julie Kagawa | C59: Gothic Dark Romantasy | D59: https://www.goodreads.com/series/96817-talon | E59: 33995 | F59: 3.76 | G59: 5 | H59: 2054 | I59: Blackstone Audio, Inc. | J59: New Keywords - Amazon | L59: Noel Regis | M59: 46282 | N59: Noel Regis | P59: 1_Talon.docx | Q59: Talon
A60: Only a Monster | B60: Vanessa Len | C60: Werewolf / Shifter Romance | D60: https://www.goodreads.com/series/287491-monsters | E60: 32725 | F60: 3.85 | G60: 3 | H60: 1360 | I60: HarperCollins | J60: Self-Represented / N/A | K60: Indie / Self-Published | L60: Noel Regis | M60: 46282 | N60: Noel Regis | P60: 1_Only a Monster.docx | Q60: Monsters
A61: The Ashes of Thezmarr | B61: Helen Scheuerer | C61: Gothic Dark Romantasy | D61: https://www.goodreads.com/series/404372-the-ashes-of-thezmarr | E61: 32028 | F61: 4.14 | G61: 3 | H61: 1437 | I61: Dreamscape Media | J61: Self-Represented / N/A | K61: Indie / Self-Published | L61: Noel Regis | M61: 46282 | N61: Noel Regis | P61: 1_Iron & Embers.docx | Q61: The Ashes of Thezmarr
A62: Star Touched: Fae Bound | B62: Natalie Ann | C62: High Fantasy Court Adventure | D62: https://www.goodreads.com/series/430831-star-touched-fae-bound | E62: 31651 | F62: 4.26 | G62: 7 | H62: 2162 | I62: Indie / Self-Published | J62: New Keywords - Amazon | L62: Noel Regis | M62: 46282 | N62: Noel Regis | P62: 1_Golden Star.docx | Q62: Star Touched Fae Bound
A63: North Shore | B63: Lola King | C63: Urban / Contemporary Fantasy Romance | D63: https://www.goodreads.com/series/369464-north-shore | E63: 31386 | F63: 3.76 | G63: 4 | H63: 2169 | I63: King \u0026 Hunter | K63: Podium Audio | L63: Noel Regis | M63: 46282 | N63: Sakshi Saxena | O63: 46286 | P63: 1_Beautiful_Fiend_-_Lola_King.docx | Q63: 127_North Shore
A64: Living Ice | B64: Dmitry Sheleg | C64: High-Stakes Games & Deadly Trials (Done) | D64: https://www.goodreads.com/series/392527-living-ice | E64: 30512 | F64: 4.33 | G64: 9 | H64: 3116 | I64: Indie / Self-Published | J64: New Keywords - Amazon | L64: Noel Regis | M64: 46282 | N64: Noel Regis | P64: 1_The Heir of an Ancient Bloodline.docx | Q64: Living Ice
A65: The Five Crowns of Okrith | B65: Mia Harlan | C65: High Fantasy Court Adventure | D65: https://www.goodreads.com/series/324191-five-crowns-of-okrith | E65: 30330 | F65: 3.68 | G65: 5 | H65: 1934 | I65: Indie / Self-Published | J65: New Keywords - Amazon | L65: Noel Regis | M65: 46282 | N65: Noel Regis | P65: 1_The High Mountain Court.docx | Q65: Five Crowns of Okrith
A66: Sins of the Zodiac | B66: Elayna R. Gallea | C66: High Fantasy Court Adventure | D66: https://www.goodreads.com/series/392054-sins-of-the-zodiac | E66: 30238 | F66: 4.02 | G66: 4 | H66: 2013 | I66: Indie / Self-Published | J66: New Keywords - Amazon | L66: Noel Regis | M66: 46282 | N66: Noel Regis | P66: 1_Never Keep.docx | Q66: Sins of the Zodiac
A67: Of Dragons and Fae | B67: Jasmine Walt | C67: Werewolf / Shifter Romance | D67: https://www.goodreads.com/series/328132-of-dragons-and-fae | E67: 29007 | F67: 3.77 | G67: 3 | H67: 1271 | I67: Dynamo Press | J67: Self-Represented / N/A | K67: Indie / Self-Published | L67: Noel Regis | M67: 46282 | N67: Noel Regis | P67: 1_Promised in Fire.docx | Q67: Of Dragons and Fae
A68: Tempting Monsters | B68: Kathryn Moon | C68: Werewolf / Shifter Romance | D68: https://www.goodreads.com/series/316521-tempting-monsters | E68: 28753 | F68: 3.89 | G68: 3 | H68: 1449 | I68: Indie / Self-Published | J68: Self-Represented / N/A | K68: Audible Studios | L68: Noel Regis | M68: 46282 | N68: Noel Regis | P68: 1_A Lady of Rooksgrave Manor.docx | Q68: Tempting Monsters
A69: The League | B69: Vera Rivers | C69: High Fantasy Court Adventure | D69: https://www.goodreads.com/series/118772-the-league-nemesis-rising | E69: 28569 | F69: 4.18 | G69: 13 | H69: 6058 | I69: Indie / Self-Published | J69: New Keywords - Amazon | L69: Noel Regis | M69: 46282 | N69: Noel Regis | P69: 1_Born of Night.docx | Q69: The League Nemesis Rising
A70: Elemental Mysteries/World | B70: Elizabeth Hunter | C70: Urban / Contemporary Fantasy Romance | D70: https://www.goodreads.com/series/79846-elemental-mysteries | E70: 28410 | F70: 4.03 | G70: 5 | H70: 1539 | I70: Recurve Press LLC | J70: Self-Represented / N/A | K70: Indie / Self-Published | L70: Noel Regis | M70: 46282 | N70: Noel Regis | P70: 1_A Hidden Fire.docx | Q70: Elemental Mysteries
A71: Monstrous | B71: Lily Mayne | C71: Monster Romance (Non-Shifter) | D71: https://www.goodreads.com/series/319053-monstrous | E71: 28035 | F71: 4.21 | G71: 8 | H71: 3014 | I71: Self Published | K71: Podium Audio | L71: Noel Regis | M71: 46282 | N71: Sakshi Saxena | O71: 46286 | P71: 1_Soul_Eater_-_Lily_Mayne.docx | Q71: Monstrous Series
A72: Nightshade Duology | B72: Keri Lake | C72: Gothic Dark Romantasy | D72: https://www.goodreads.com/series/346395-nightshade | E72: 27817 | F72: 3.95 | G72: 2 | H72: 1362 | I72: Indie / Self-Published | J72: Self-Represented / N/A | K72: Indie / Self-Published | L72: Noel Regis | M72: 46282 | N72: Noel Regis | P72: 1_Nightshade_-_Keri_Lake.docx | Q72: Nightshade
A73: The Elite Kings' Club | B73: Amo Jones | C73: Dark Academia Romantasy | D73: https://www.goodreads.com/series/195195-elite-king-s-club | E73: 27370 | F73: 3.81 | G73: 8 | H73: 2070 | I73: P1: Te Amorangi | P2: Self Published | K73: Podium Audio | L73: Noel Regis | M73: 46282 | N73: Sakshi Saxena | O73: 46286 | P73: 1_The Silver Swan.docx | Q73: 137_Elite King's Club
A74: All The Pretty Monsters | B74: Kristy Cunning | C74: Paranormal Romance | D74: https://www.goodreads.com/series/251041-all-the-pretty-monsters | E74: 26364 | F74: 4.22 | G74: 6 | H74: 2012 | I74: Self Published | K74: Tantor Media | L74: Noel Regis | M74: 46282 | N74: Sakshi Saxena | O74: 46286 | P74: 1_Gypsy Blood.docx | Q74: 138_All the Pretty Monsters
A75: Naughtier and Naughtier | B75: Jade West | C75: Urban / Contemporary Fantasy Romance | D75: https://www.goodreads.com/series/403339-naughtier-and-naughtier | E75: 26153 | F75: 3.8 | G75: 5 | H75: 1841 | I75: Self Published | K75: Podium Audio | L75: Noel Regis | M75: 46282 | N75: Sakshi Saxena | O75: 46286 | P75: 1_The Naughty List.docx | Q75: 139_Naughtier and Naughtier
A76: Hagenheim Series | B76: Scarlett Reid | C76: High Fantasy Court Adventure | D76: https://www.goodreads.com/series/135500-hagenheim | E76: 25941 | F76: 3.84 | G76: 11 | H76: 3363 | I76: Indie / Self-Published | J76: New Keywords - Amazon | L76: Noel Regis | M76: 46282 | N76: Noel Regis | P76: 1_The Healer's Apprentice.docx | Q76: Hagenheim
A77: Villains and Virtues | B77: A. K. Caggiano | C77: High Fantasy Court Adventure | D77: https://www.goodreads.com/series/357374-villains-virtues | E77: 25668 | F77: 4.04 | G77: 3 | H77: 1244 | I77: Dreamscape Media | J77: Self-Represented / N/A | K77: Indie / Self-Published | L77: Noel Regis | M77: 46282 | N77: Noel Regis | P77: 1_Throne in the Dark.docx | Q77: Villains & Virtues
A78: The Lost Sentinel | B78: Ivy Asher | C78: Werewolf / Shifter Romance | D78: https://www.goodreads.com/series/249686-the-lost-sentinel | E78: 25658 | F78: 4.27 | G78: 4 | H78: 1408 | I78: Indie / Self-Published | J78: Self-Represented / N/A | K78: Audible Studios | L78: Noel Regis | M78: 46282 | N78: Noel Regis | P78: 1_The Lost and the Chosen.docx | Q78: The Lost Sentinel
A79: She Can | B79: Calia Read | C79: High Fantasy Court Adventure | D79: https://www.goodreads.com/series/90574-she-can | E79: 25651 | F79: 4.21 | G79: 5 | H79: 1691 | I79: Indie / Self-Published | J79: Jane Rotrosen Agency | L79: Noel Regis | M79: 46282 | N79: Noel Regis | P79: 1_She_Can_Run_-_Melinda_Leigh.docx | Q79: She Can.... Series
A80: King's Dark Tidings | B80: Kel Kade | C80: High Fantasy Court Adventure | D80: https://www.goodreads.com/series/172856-king-s-dark-tidings | E80: 25490 | F80: 4.22 | G80: 7 | H80: 3524 | I80: Dark Rover Publishing, LLC | K80: Podium Audio | L80: Noel Regis | M80: 46282 | N80: Sakshi Saxena | O80: 46286 | P80: 1_Free the Darkness.docx | Q80: 144_King's Dark Tidings
A81: Starlight Grove | B81: Catherine Cowles | C81: Dark Academia Romantasy | D81: https://www.goodreads.com/series/420132-starlight-grove | E81: 25350 | F81: 4.29 | G81: 5 | H81: 1296 | I81: Self Published | K81: Self Published | L81: Noel Regis | M81: 46282 | N81: Sakshi Saxena | O81: 46286 | P81: 1_Across the Vanishing Sky.docx | Q81: 146_Starlight Grove
A82: The Poisoner Series | B82: I.V. Ophelia | C82: Gothic Dark Romantasy | D82: https://www.goodreads.com/series/393307-the-poisoner | E82: 25186 | F82: 3.7 | G82: 3 | H82: 1280 | I82: Simon Maverick | J82: Self-Represented / N/A | K82: Indie / Self-Published | L82: Noel Regis | M82: 46282 | N82: Noel Regis | P82: 1_The Poisoner.docx | Q82: The Poisoner
A83: Joe Hennessy Legal Thriller | B83: Peter O'Mahoney | C83: Urban / Contemporary Fantasy Romance | D83: https://www.goodreads.com/series/342269-joe-hennessy-legal-thriller | E83: 25121 | F83: 4.21 | G83: 6 | H83: 2168 | I83: Roam Free Publishing | K83: Podium Audio | L83: Noel Regis | M83: 46282 | N83: Sakshi Saxena | O83: 46286 | P83: 1_The Southern Lawyer.docx | Q83: 148_Joe Hennessy Legal Thriller
A84: Blood of a Fae | B84: Briar Boleyn | C84: Gothic Dark Romantasy | D84: https://www.goodreads.com/series/356627-blood-of-a-fae | E84: 25025 | F84: 3.88 | G84: 4 | H84: 1526 | I84: Podium Audio | J84: Self-Represented / N/A | K84: Podium Audio | L84: Noel Regis | M84: 46282 | N84: Sakshi Saxena | O84: 46286 | P84: 1_Queen of Roses.docx | Q84: 149_Blood of a Fae
A85: GhostWalker | B85: Christine Feehan | C85: High Fantasy Court Adventure | D85: https://www.goodreads.com/series/41874-ghostwalker | E85: 23069 | F85: 4.09 | G85: 20 | H85: 7295 | I85: ) Format: Audible Audiobook | J85: New Keywords - Amazon | L85: Noel Regis | M85: 46282 | N85: Noel Regis | P85: 1_Shadow Game.docx | Q85: GhostWalker
A86: The Saints | B86: Michelle Heard | C86: Gothic Dark Romantasy | D86: https://www.goodreads.com/series/322421-the-saints | E86: 22216 | F86: 4.05 | G86: 5 | H86: 1779 | I86: MA Heard | K86: Podium Audio | L86: Noel Regis | M86: 46282 | N86: Sakshi Saxena | O86: 46286 | P86: 1_Merciless Saints.docx | Q86: 151_The Saints
A87: Waterfire Saga | B87: Jennifer Donnelly | C87: Mythology, Legend & Fairy Tale Retelling | D87: https://www.goodreads.com/series/121038-waterfire-saga | E87: 21696 | F87: 3.83 | G87: 4 | H87: 1402 | I87: Indie / Self-Published | J87: Self-Represented / N/A | K87: Indie / Self-Published | L87: Noel Regis | M87: 46282 | N87: Noel Regis | P87: 1_Deep Blue.docx | Q87: Waterfire Saga by Jennifer Donnelly
A88: Reverse Harem Omegaverse Duology | B88: Lola Rock | C88: High Fantasy Court Adventure | D88: https://www.goodreads.com/series/323745-pack-darling | E88: 21630 | F88: 4.19 | G88: 3 | H88: 1275 | I88: Indie / Self-Published | J88: Self-Represented / N/A | K88: Podium Audio | L88: Noel Regis | M88: 46282 | N88: Noel Regis | P88: 1_Pack Darling Part One.docx | Q88: Pack Darling
A89: Clean Billionaire Romance Series | B89: Bree Livingston | C89: Subjective | D89: fhttps://www.goodreads.com/series/238821-clean-billionaire-romance | E89: 283 | I89: Indie / Self-Published | J89: New Keywords - Amazon | L89: Noel Regis | M89: 46282 | N89: Sakshi Saxena | O89: 46286 | P89: 1_Her Pretend Billionaire Boyfriend.docx | Q89: Clean Billionaire Romance
A90: The Alpha Territories | B90: Shannon Mayer | C90: Werewolf / Shifter Romance | D90: https://www.goodreads.com/series/356354-the-alpha-territories | E90: 21172 | F90: 4.19 | G90: 7 | H90: 2244 | I90: Self Published | K90: Hijinks Ink Publishing | L90: Noel Regis | M90: 46282 | N90: Sakshi Saxena | O90: 46286 | P90: 1_Taken by Fate.docx | Q90: 155_The Alpha Territories
A91: Guides to Villainy and Love | B91: Tiffany Hunt | C91: Gothic Dark Romantasy | D91: https://www.goodreads.com/series/421763-guides-to-villainy-and-love | E91: 21053 | F91: 3.97 | G91: 2 | H91: 1220 | I91: Podium Audio | J91: Self-Represented / N/A | K91: Podium Audio | L91: Noel Regis | M91: 46282 | N91: Sakshi Saxena | O91: 46286 | P91: 1_The Dark Lord's Guide to Dating (and Other War Crimes).docx | Q91: 156_Guides to Villainy and Love
A92: Seven Series | B92: Dannika Dark | C92: Werewolf / Shifter Romance ( Done ) | D92: https://www.goodreads.com/series/108527-seven | E92: 20663 | F92: 4.01 | G92: 8 | H92: 3365 | I92: ) Format: Audible Audiobook | J92: New Keywords - Amazon | L92: Noel Regis | M92: 46282 | N92: Noel Regis | P92: Book 1 - Seven Years.docx | Q92: Seven Series
A93: Hot Damned | B93: Robyn Peterman | C93: Paranormal Romance ( Done ) | D93: https://www.goodreads.com/series/111569-hot-damned | E93: 20635 | F93: 4.01 | G93: 20 | H93: 5409 | I93: ) Format: Audible Audiobook | J93: New Keywords - Amazon | L93: Noel Regis | M93: 46282 | N93: Noel Regis | P93: 1_Fashionably Dead.docx | Q93: Hot Damned
A94: Dragons of Telera | B94: Lisa Daniels | C94: Werewolf / Shifter Romance ( Done ) | D94: https://www.goodreads.com/series/193953-dragons-of-telera | E94: 20387 | F94: 3.72 | G94: 9 | H94: 1452 | I94: ), Virtual Voice (Narrator) Format: Audible Audiobook | J94: New Keywords - Amazon | L94: Noel Regis | M94: 46282 | N94: Noel Regis | P94: 1_Annora's Dragon.docx | Q94: Dragons of Telera
A95: Witching Savannah | B95: J. D. Horn | C95: Gothic Dark Romantasy | D95: https://www.goodreads.com/series/108730-witching-savannah | E95: 19778 | F95: 3.83 | G95: 4 | H95: 1340 | I95: Indie / Self-Published | J95: Self-Represented / N/A | K95: Audible Studios | L95: Noel Regis | M95: 46282 | N95: Noel Regis | P95: 1_The Line.docx | Q95: Witching Savannah
A96: A Tale of the Five Hundred Kingdoms | B96: M.J. Haag | C96: High Fantasy Court Adventure | D96: https://www.goodreads.com/series/40365-five-hundred-kingdoms | E96: 19580 | F96: 4 | G96: 9 | H96: 3798 | I96: Indie / Self-Published | J96: New Keywords - Amazon | L96: Noel Regis | M96: 46282 | N96: Noel Regis | P96: 1_The Fairy Godmother.docx | Q96: Five Hundred Kingdoms
A97: Creepy Hollow | B97: Gail Z. Martin | C97: High Fantasy Court Adventure | D97: https://www.goodreads.com/series/75158-creepy-hollow | E97: 19388 | F97: 3.95 | G97: 16 | H97: 12172 | I97: Indie / Self-Published | J97: New Keywords - Amazon | L97: Noel Regis | M97: 46282 | N97: Noel Regis | P97: 1_The Faerie Guardian.docx | Q97: Creepy Hollow
A98: Underworld Gods | B98: Karina Halle | C98: Paranormal Romance | D98: https://www.goodreads.com/series/332973-underworld-gods | E98: 18620 | G98: 4 | H98: 1236 | I98: Tantor Audio | J98: Self-Represented / N/A | K98: Tantor Media | L98: Noel Regis | M98: 46282 | N98: Sakshi Saxena | O98: 46286 | P98: 1_River of Shadows.docx | Q98: 163_Underworld Gods
A99: Crown of the Seven Realms | B99: A.L. Hampton | C99: — | D99: https://www.goodreads.com/series/419313-the-crown-of-the-seven-realms | E99: 18184 | F99: 3.67 | G99: 5 | H99: 3481 | I99: Indie / Self-Published | J99: New Keywords - Amazon | L99: Noel Regis | M99: 46282 | N99: Noel Regis | P99: 1_Dark Awakening.docx | Q99: The Crown of the Seven Realms
A100: The Secret Circle | B100: L. J. Smith | C100: Urban Coven Romance | D100: https://www.goodreads.com/series/41928-the-secret-circle | E100: 18104 | F100: 3.78 | G100: 6 | H100: 1817 | I100: ) Format: Audible Audiobook | J100: New Keywords - Amazon | L100: Noel Regis | M100: 46282 | N100: Noel Regis | P100: 1_The Initiation.docx | Q100: The Secret Circle
A101: The Boys | B101: Micalea Smeltzer | C101: Urban / Contemporary Fantasy Romance | D101: https://www.goodreads.com/series/293136-the-boys | E101: 18077 | F101: 3.65 | G101: 6 | H101: 2518 | I101: Self Published | K101: Podium Audio | L101: Noel Regis | M101: 46282 | N101: Sakshi Saxena | O101: 46286 | P101: 1_Bad Boys Break Hearts.docx | Q101: 166_The Boys
A102: Corrupted Royals | B102: Michelle Heard | C102: Gothic Dark Romantasy | D102: https://www.goodreads.com/series/352299-corrupted-royals | E102: 17646 | F102: 3.82 | G102: 5 | H102: 1369 | I102: MA Heard | K102: Podium Audio | L102: Noel Regis | M102: 46282 | N102: Sakshi Saxena | O102: 46286 | P102: 1_Destroy Me.docx | Q102: 167_Corrupted Royals
A103: The Lost Queen | B103: Signe Pike | C103: Mythology, Legend & Fairy Tale Retelling | D103: https://www.goodreads.com/series/233809-the-lost-queen | E103: 17536 | F103: 4.16 | G103: 3 | H103: 1402 | I103: Atria Books | J103: Self-Represented / N/A | K103: Indie / Self-Published | L103: Noel Regis | M103: 46282 | N103: Noel Regis | P103: 1_The Lost Queen.docx | Q103: The Lost Queen
A104: The Seven Kingdoms | B104: Kamery Solomon | C104: High Fantasy Court Adventure | D104: https://www.goodreads.com/series/164757-seven-kingdoms-tales | E104: 673 | F104: 3.88 | G104: #N/A | H104: #N/A | I104: #N/A | J104: New Keywords - Amazon | L104: Noel Regis | M104: 46282 | N104: Sakshi Saxena | O104: 46286 | P104: 1_The Dragon's Treasure.docx | Q104: 169_Seven Kingdoms Tales
A105: The Monster Stalker Series | B105: January Rayne | C105: Werewolf / Shifter Romance | D105: https://www.goodreads.com/series/374979-monster-stalker | E105: 17274 | F105: 3.49 | G105: 4 | H105: 1322 | I105: Indie / Self-Published | J105: Self-Represented / N/A | K105: Indie / Self-Published | L105: Noel Regis | M105: 46282 | N105: Noel Regis | P105: 1_Honeysuckles.docx | Q105: Monster Stalker
...

Sheet Batch 2 - 239
A1: Series Name | B1: Author | C1: Sub-Genre | D1: Book Series (GoodReads URL) | E1: GoodReads No. of Ratings | F1: Goodreads Book 1 Ratings | G1: Total Primary Books | H1: Total primary Books Page Count | I1: Imprint / Publisher - Book | J1: Agencies | K1: Imprint / Publisher - Audiobook | L1: Crawling POC | M1: Crawling Date | N1: Links addition POC | O1: Links Date | P1: Book 1 Link | Q1: Books (1 - 5) Links | R1: Check | S1: Batch Number
A2: Grimm Cove | B2: Allyson Voller | C2: War College / Military Academy | D2: https://www.goodreads.com/series/283257-grimm-cove | E2: 5633 | F2: 4.28 | G2: 7 | H2: 3253 | I2: ) Format: Audible Audiobook | J2: New Keywords - Amazon | L2: Anvita Belawal | M2: 46287 | N2: Vanshika V | P2: https://docs.google.com/document/d/1D1lP5ohPnLWRo2ix-7m9UGcX20TDb_iJ/edit?usp=drive_link&ouid=101023058405307348147&rtpof=true&sd=true | Q2: https://drive.google.com/drive/folders/18Fd2l03ZEwdYRezrQG--EeXrMtXG2ZmJ?usp=drive_link | R2: =IF(E2=H2,"Don't Proceed","Proceed")
A3: Solar Dragons Need Love, Too! | B3: Virgil Knightley | C3: Romantasy | D3: https://www.goodreads.com/series/348358-solar-dragons-need-love-too | E3: 5580 | F3: 4.23 | G3: 8 | H3: 2389 | I3: Eldritch Blade | J3: New Keywords - Amazon | L3: Anvita Belawal | M3: 46287 | N3: Vanshika V | P3: https://docs.google.com/document/d/1TFI-vQdDvWlP3Ehjx8yOklOT5Q0_a-gh/edit?usp=drive_link&ouid=101023058405307348147&rtpof=true&sd=true | Q3: https://drive.google.com/drive/folders/1PLZZRRhW2R0aL4NwUl9C9DtvXuPyO2e1?usp=drive_link | R3: =IF(E3=H3,"Don't Proceed","Proceed")
A4: Cora Roberts | B4: Adaline Winters | C4: Paranormal Romance | D4: https://www.goodreads.com/series/365903-cora-roberts | E4: 5579 | G4: 5 | H4: 1368 | I4: Indie / Self-Published | J4: Self-Represented / N/A | K4: Tantor Media | L4: Anvita Belawal | M4: 46287 | N4: Vanshika V | P4: https://docs.google.com/document/d/1rRG2x5zeSbaI1LaHHa-PreqXBG28TEN-/edit?usp=drive_link&ouid=101023058405307348147&rtpof=true&sd=true | Q4: https://drive.google.com/drive/folders/1xB24WnEwcdY6339a5LnsrT2UP__H5T-j?usp=drive_link | R4: =IF(E4=H4,"Don't Proceed","Proceed")
A5: Bewitched by Chocolate Cozy Fantasy Witch Mysteries | B5: H.Y. Hanna | C5: Gothic Dark Romantasy | D5: https://www.goodreads.com/series/198475-bewitched-by-chocolate | E5: 5421 | F5: 4.12 | G5: 9 | H5: 3560 | I5: H.Y. Hanna | J5: New Keywords - Amazon | L5: Anvita Belawal | M5: 46287 | N5: Vanshika V | P5: https://docs.google.com/document/d/1zCCWwUhcG2yadr5oH7pd-a3vHm2SKL8Q/edit?usp=drive_link&ouid=101023058405307348147&rtpof=true&sd=true | Q5: https://drive.google.com/drive/folders/1K093KyAnkb8ydJONVS66fz5I9CKwvpTl?usp=drive_link | R5: =IF(E5=H5,"Don't Proceed","Proceed")
A6: Banished Midlife Dragon Shifters | B6: Alicia Banks | C6: Werewolf / Shifter Romance ( Done ) | D6: https://www.goodreads.com/series/377942-banished-midlife-dragon-shifters | E6: 5410 | F6: 4.58 | G6: 6 | H6: 1289 | I6: Indie / Self-Published | J6: New Keywords - Amazon | L6: Anvita Belawal | M6: 46287 | N6: Vanshika V | P6: https://docs.google.com/document/d/1fIHAM0zrQGal-kxZma4jsYvivoK_lIee/edit?usp=drive_link&ouid=101023058405307348147&rtpof=true&sd=true | Q6: https://drive.google.com/drive/folders/1n1G0ApQH1qwjMNZpddviDGLmdsuNInyP?usp=drive_link | R6: =IF(E6=H6,"Don't Proceed","Proceed")
A7: Souls Trilogy by Harley Laroux | B7: Harley LaRoux | C7: High-Stakes Games & Deadly Trials (Done) | D7: https://www.goodreads.com/series/315325-souls-trilogy | E7: 5403 | F7: 4.02 | G7: 3 | H7: 1652 | I7: Indie / Self-Published | J7: New Keywords - Amazon | L7: Anvita Belawal | M7: 46287 | N7: Vanshika V | P7: https://docs.google.com/document/d/1sTG1wwJfUyuhE0Au_S1t_AuW3TO0af3d/edit?usp=drive_link&ouid=101023058405307348147&rtpof=true&sd=true | Q7: https://drive.google.com/drive/folders/1kx06NHE9WOiCvhEqWgFyEAymr5ZFylAJ?usp=drive_link | R7: =IF(E7=H7,"Don't Proceed","Proceed")
A8: A Throne for Sisters | B8: Morgan Rice | C8: High Fantasy Court Adventure | D8: https://www.goodreads.com/series/223508-a-throne-for-sisters | E8: 5307 | F8: 3.46 | G8: 8 | H8: 1453 | I8: Indie / Self-Published | J8: Self-Represented / N/A | K8: Indie / Self-Published | L8: Anvita Belawal | M8: 46287 | N8: Vanshika V | P8: https://docs.google.com/document/d/1rWM2RUo8weRip-_wik-9nJv_ljn5eddl/edit?usp=drive_link&ouid=101023058405307348147&rtpof=true&sd=true | Q8: https://drive.google.com/drive/folders/1DAePey26qFxpOvVAOQDLsT_PdWeakn4t?usp=drive_link | R8: =IF(E8=H8,"Don't Proceed","Proceed")
A9: Possessive Monsters | B9: Maggie Mayhem | C9: Monster Romance ( Non-Shifter ) | D9: https://www.goodreads.com/series/362691-possessive-monsters | E9: 5288 | F9: 3.94 | G9: 8 | H9: 2009 | I9: Amazon.com Services LLC Explore more items Feral Shifters | J9: New Keywords - Amazon | L9: Anvita Belawal | M9: 46287 | N9: Vanshika V | P9: https://docs.google.com/document/d/1XLGDaG2j-3ER2q2LY9KPTjSuWAkG5TLk/edit?usp=drive_link&ouid=101023058405307348147&rtpof=true&sd=true | Q9: https://drive.google.com/drive/folders/1fS66x_MD9OBCM5Ynf7ufrcyCy-s3HhEr?usp=drive_link | R9: =IF(E9=H9,"Don't Proceed","Proceed")
A10: Immortal Ops | B10: Mandy M. Roth | C10: War College / Military Academy | D10: https://www.goodreads.com/series/47805-immortal-ops | E10: 5273 | F10: 3.91 | G10: 11 | H10: 2745 | I10: The Raven Books | J10: New Keywords - Amazon | L10: Anvita Belawal | M10: 46287 | N10: Vanshika V | P10: https://docs.google.com/document/d/1H3mkEHwshrv43LQ6pS9Kd6fvxrubmVl1/edit?usp=drive_link&ouid=101023058405307348147&rtpof=true&sd=true | Q10: https://drive.google.com/drive/folders/1fbLl54z4PohTCGd5yyV77zWDxwsYJG36?usp=drive_link | R10: =IF(E10=H10,"Don't Proceed","Proceed")
A11: Federal Bureau of Magic | B11: Annabel Chase | C11: Paranormal Romance ( Done ) | D11: https://www.goodreads.com/series/256584-federal-bureau-of-magic | E11: 5220 | F11: 4.15 | G11: 15 | H11: 4839 | I11: ) Format: Audible Audiobook | J11: New Keywords - Amazon | L11: Anvita Belawal | M11: 46287 | N11: Vanshika V | P11: https://docs.google.com/document/d/1p8g8iwoWqq0-7AlvZ9RrTJJXtXxbBuV9/edit?usp=drive_link&ouid=101023058405307348147&rtpof=true&sd=true | Q11: https://drive.google.com/drive/folders/1zArALSBbVzyioEv3pEuFxHq6rKIyxJT3?usp=drive_link | R11: =IF(E11=H11,"Don't Proceed","Proceed")
A12: Mackenzie Green Series | B12: JS Kennedy | C12: High Fantasy Court Adventure | D12: https://www.goodreads.com/series/352234-mackenzie-green | E12: 5208 | F12: 4.22 | G12: 5 | H12: 1932 | I12: Indie / Self-Published | J12: New Keywords - Amazon | L12: Anvita Belawal | M12: 46287 | N12: Vanshika V | P12: https://docs.google.com/document/d/1jwS0VqK3QNVu4FiXNOym5aDBy96ujPbN/edit?usp=drive_link&ouid=101023058405307348147&rtpof=true&sd=true | Q12: https://drive.google.com/drive/folders/1r7tNCriRKAIk-XKVhIMNwAQGCqpwkwyS?usp=drive_link | R12: =IF(E12=H12,"Don't Proceed","Proceed")
A13: Rise of the Warlords | B13: Gena Showalter | C13: Mythology, Legend & Fairy Tale Retelling | D13: https://www.goodreads.com/series/295817-rise-of-the-warlords | E13: 5182 | F13: 4.15 | G13: 4 | H13: 1510 | I13: HQN Books | J13: Self-Represented / N/A | K13: Indie / Self-Published | L13: Anvita Belawal | M13: 46287 | N13: Vanshika V | P13: https://docs.google.com/document/d/1KPYMhRmiG04oi_4DczbDUotwL2i7H9mQ/edit?usp=drive_link&ouid=101023058405307348147&rtpof=true&sd=true | Q13: https://drive.google.com/drive/folders/1k6aXQKZeFe7cyEKYDOM0-kIwM2FYVcBj?usp=drive_link | R13: =IF(E13=H13,"Don't Proceed","Proceed")
A14: The Companion series | B14: Karen Moderow | C14: High Fantasy Court Adventure | D14: https://www.goodreads.com/series/315433-the-companion | E14: 5127 | F14: 3.87 | G14: 6 | H14: 1951 | I14: Indie / Self-Published | J14: New Keywords - Amazon | L14: Anvita Belawal | M14: 46287 | N14: Vanshika V | P14: https://docs.google.com/document/d/1ZmOyEU3TzZce-joodj4kRejjedbC-Rlx/edit?usp=drive_link&ouid=101023058405307348147&rtpof=true&sd=true | Q14: https://drive.google.com/drive/folders/1h3ANH9Jfk7vDPwk_qRERJKwaDSFTe1qf?usp=drive_link | R14: =IF(E14=H14,"Don't Proceed","Proceed")
A15: Demigods Academy series | B15: Elisa S. Amore | C15: War College / Military Academy | D15: https://www.goodreads.com/series/274428-demigods-academy | E15: 5090 | F15: 4.19 | G15: 12 | H15: 2844 | I15: Amore Publishing | J15: New Keywords - Amazon | L15: Anvita Belawal | M15: 46287 | N15: Vanshika V | P15: https://docs.google.com/document/d/1Wy_kLGEzEdE_FKq_fygCtV63IqQDpcWf/edit?usp=drive_link&ouid=101023058405307348147&rtpof=true&sd=true | Q15: https://drive.google.com/drive/folders/1ja6Xlq0k98D0kgBtEDxPGGnZzIuSCrV0?usp=drive_link | R15: =IF(E15=H15,"Don't Proceed","Proceed")
A16: Sons of Sin | B16: Helen Hardt | C16: High Fantasy Court Adventure | D16: https://www.goodreads.com/series/75749-sons-of-sin | E16: 5080 | F16: 3.8 | G16: 4 | H16: 1628 | I16: Indie / Self-Published | J16: New Keywords - Amazon | L16: Anvita Belawal | M16: 46287 | N16: Vanshika V | P16: https://docs.google.com/document/d/1Vxc6n6t2_bhGfP5V_h4ruPcqC95623FC/edit?usp=drive_link&ouid=101023058405307348147&rtpof=true&sd=true | Q16: https://drive.google.com/drive/folders/1SF53QhlN5riFrMClGCkySNdAR_nhNVIq?usp=drive_link | R16: =IF(E16=H16,"Don't Proceed","Proceed")
A17: The Omega Book Club | B17: Veronica Samek | C17: Werewolf / Shifter Romance | D17: https://www.goodreads.com/series/423936-the-omega-book-club | E17: 5060 | F17: 3.77 | G17: 5 | H17: 1203 | I17: Indie / Self-Published | J17: Self-Represented / N/A | K17: Indie / Self-Published | L17: Anvita Belawal | M17: 46287 | N17: Vanshika V | P17: https://docs.google.com/document/d/1SmzR1Nr0kX2yh_FaKTwgiK2m1E_iwUnw/edit?usp=drive_link&ouid=101023058405307348147&rtpof=true&sd=true | Q17: https://drive.google.com/drive/folders/19C9nOjxeHx561xeFfDxSQixdPAbShrH7?usp=drive_link | R17: =IF(E17=H17,"Don't Proceed","Proceed")
A18: The Splintered Bond | B18: Merri Bright | C18: Werewolf / Shifter Romance | D18: https://www.goodreads.com/series/428579-the-splintered-bond | E18: 5020 | G18: 5 | H18: 1695 | I18: Indie / Self-Published | J18: Self-Represented / N/A | K18: Indie / Self-Published | L18: Anvita Belawal | M18: 46287 | N18: Sakshi Saxena | P18: https://docs.google.com/document/d/1up4RHzmHZF_YWDXy1nib3ylrN6vErHsZ/edit?usp=drive_link&ouid=101023058405307348147&rtpof=true&sd=true | Q18: The Splintered Bond | R18: =IF(E18=H18,"Don't Proceed","Proceed")
A19: A Harper Harlow Mystery | B19: Lily Harper Hart | C19: Hidden Magic Romance | D19: https://www.goodreads.com/series/161135-harper-harlow | E19: 4990 | F19: 4.22 | G19: 21 | H19: 4406 | I19: HarperHart Publications | J19: New Keywords - Amazon | L19: Anvita Belawal | M19: 46287 | N19: Sakshi Saxena | P19: https://docs.google.com/document/d/13cJcbkN0w-on9pmpyuQIyeUB6H8TO3WS/edit?usp=drive_link&ouid=101023058405307348147&rtpof=true&sd=true | Q19: A Harper Harlow Mystery | R19: =IF(E19=H19,"Don't Proceed","Proceed")
A20: Starfall Academy | B20: Lyra Mishon | C20: War College / Military Academy | D20: https://www.goodreads.com/series/431968-starfall-academy | E20: 4986 | F20: 4.01 | G20: 4 | H20: 1402 | I20: Indie / Self-Published | J20: Self-Represented / N/A | K20: Indie / Self-Published | L20: Anvita Belawal | M20: 46287 | N20: Sakshi Saxena | P20: https://docs.google.com/document/d/11P4uAvZugRVIuHO1SuymxuuHfIunksnh/edit?usp=drive_link&ouid=101023058405307348147&rtpof=true&sd=true | Q20: Starfall Academy | R20: =IF(E20=H20,"Don't Proceed","Proceed")
A21: The Andari Chronicles | B21: Krista Luna | C21: Subjective | D21: https://www.goodreads.com/series/180512-andari-chronicles | E21: 4943 | F21: 4.09 | G21: 8 | H21: 3695 | I21: Indie / Self-Published | J21: New Keywords - Amazon | L21: Anvita Belawal | M21: 46287 | N21: Sakshi Saxena | P21: https://docs.google.com/document/d/1VZ4PjuKBKifnb_XE4aPR60Uyy9ak_nZ2/edit?usp=drive_link&ouid=101023058405307348147&rtpof=true&sd=true | Q21: The Andari Chronicles | R21: =IF(E21=H21,"Don't Proceed","Proceed")
A22: The Chronicles of Kerrigan | B22: WJ May | C22: High Fantasy Court Adventure | D22: https://www.goodreads.com/series/74270-the-chronicles-of-kerrigan | E22: 4935 | F22: 3.95 | G22: 12 | H22: 2849 | I22: Dark Shadow Publishing | J22: New Keywords - Amazon | L22: Anvita Belawal | M22: 46287 | N22: Sakshi Saxena | P22: https://docs.google.com/document/d/1g1Lm3JKllhCMpwTEfaoOGqEYnLQwSwCY/edit?usp=drive_link&ouid=101023058405307348147&rtpof=true&sd=true | Q22: The Chronicles of Kerrigan | R22: =IF(E22=H22,"Don't Proceed","Proceed")
A23: The Invisible College | B23: Jeff Wheeler | C23: High Fantasy Court Adventure | D23: https://www.goodreads.com/series/411086-the-invisible-college | E23: 4933 | F23: 4.2 | G23: 4 | H23: 1480 | I23: 47North | J23: Self-Represented / N/A | K23: Podium Audio | L23: Anvita Belawal | M23: 46287 | N23: Sakshi Saxena | P23: https://docs.google.com/document/d/1hZEpwLVZjOv2Pd6lL01M2TXoKz6PcoxJ/edit?usp=drive_link&ouid=101023058405307348147&rtpof=true&sd=true | Q23: The Invisible College | R23: =IF(E23=H23,"Don't Proceed","Proceed")
A24: Shadow Series | B24: T. M. Hart | C24: Gothic Dark Romantasy | D24: https://www.goodreads.com/series/210098-shadow | E24: 4886 | F24: 3.89 | G24: 4 | H24: 1279 | I24: Indie / Self-Published | J24: Self-Represented / N/A | K24: Audible Studios | L24: Anvita Belawal | M24: 46287 | N24: Sakshi Saxena | P24: https://docs.google.com/document/d/1WQDbN9jTidoPYH4MXYy6qm8eepLUpehP/edit?usp=drive_link&ouid=101023058405307348147&rtpof=true&sd=true | Q24: Shadow Series | R24: =IF(E24=H24,"Don't Proceed","Proceed")
A25: I Bring the Fire | B25: C. Gockel | C25: Gothic Dark Romantasy | D25: https://www.goodreads.com/series/95355-i-bring-the-fire | E25: 4859 | F25: 3.78 | G25: 8 | H25: 3242 | I25: Amazon Digital Services | J25: New Keywords - Amazon | L25: Anvita Belawal | M25: 46287 | N25: Sakshi Saxena | P25: https://docs.google.com/document/d/1qKNS7hdv75OzjXXihyAs-QogxPksJhOb/edit?usp=drive_link&rtpof=true&sd=true | Q25: I Bring the Fire | R25: =IF(E25=H25,"Don't Proceed","Proceed")
A26: The Killian Blade Series | B26: Stella Brie | C26: Urban Fantasy Romance | D26: https://www.goodreads.com/series/309871-killian-blade | E26: 4831 | F26: 4.2 | G26: 6 | H26: 1913 | I26: Stella Brie | J26: New Keywords - Amazon | L26: Anvita Belawal | M26: 46287 | N26: Sakshi Saxena | P26: https://docs.google.com/document/d/1OsGpVyoFnU6lzLPC-g3uDMqOwKA1bDUD/edit?usp=drive_link&ouid=101023058405307348147&rtpof=true&sd=true | Q26: The Killian Blade Series | R26: =IF(E26=H26,"Don't Proceed","Proceed")
A27: PSI-Ops/Immortal Ops | B27: Mandy M. Roth | C27: War College / Military Academy | D27: https://www.goodreads.com/series/137832-immortal-ops-psi-ops | E27: 4753 | F27: 4.12 | G27: 8 | H27: 3263 | I27: Raven Happy Hour, LLC | J27: New Keywords - Amazon | L27: Anvita Belawal | M27: 46287 | N27: Sakshi Saxena | P27: https://docs.google.com/document/d/1svKaAQD3a52-B0EHuRygSWBkw1vCE17H/edit?usp=drive_link&ouid=101023058405307348147&rtpof=true&sd=true | Q27: PSI-Ops_Immortal Ops | R27: =IF(E27=H27,"Don't Proceed","Proceed")
A28: Shadow Quest | B28: Kiersten Fay | C28: Gothic Dark Romantasy | D28: https://www.goodreads.com/series/60693-shadow-quest | E28: 4722 | F28: 3.92 | G28: 4 | H28: 1718 | I28: ), Henry Jones (Narrator) Format: Audible Audiobook | J28: New Keywords - Amazon | L28: Anvita Belawal | M28: 46287 | N28: Sakshi Saxena | P28: https://docs.google.com/document/d/1SVoEvGe4GwJfGZsiiQZWsQ9ccJQbWrgd/edit?usp=drive_link&ouid=101023058405307348147&rtpof=true&sd=true | Q28: Shadow Quest | R28: =IF(E28=H28,"Don't Proceed","Proceed")
A29: A space opera adventure in the Star Kingdom Universe | B29: Bella Klaus | C29: High Fantasy Court Adventure | D29: https://www.goodreads.com/series/261857-star-kingdom | E29: 4683 | F29: 4.18 | G29: 9 | H29: 3619 | I29: Indie / Self-Published | J29: New Keywords - Amazon | L29: Anvita Belawal | M29: 46287 | N29: Sakshi Saxena | P29: https://docs.google.com/document/d/1-4QAHv0VUXZ-OXcwD1C05ToAaQj4uLQb/edit?usp=drive_link&ouid=101023058405307348147&rtpof=true&sd=true | Q29: A space opera adventure in the Star Kingdom Universe | R29: =IF(E29=H29,"Don't Proceed","Proceed")
A30: Jaga and the Devil | B30: Layla Fae | C30: Gothic Dark Romantasy | D30: https://www.goodreads.com/series/396473-jaga-and-the-devil | E30: 4675 | F30: 4.08 | G30: 3 | H30: 1744 | I30: ) Format: Audible Audiobook | J30: New Keywords - Amazon | L30: Anvita Belawal | M30: 46287 | N30: Sakshi Saxena | P30: https://docs.google.com/document/d/13G1VjmPAob8kjI-EcNlVGXRiYXUec2bl/edit?usp=drive_link&ouid=101023058405307348147&rtpof=true&sd=true | Q30: Jaga and the Devil | R30: =IF(E30=H30,"Don't Proceed","Proceed")
A31: Dragon Riders of Elantia | B31: Jasmine Walt | C31: High Fantasy Court Adventure | D31: https://www.goodreads.com/series/247789-dragon-riders-of-elantia | E31: 4457 | F31: 4.18 | G31: 6 | H31: 1546 | I31: Dynamo Press | J31: Self-Represented / N/A | K31: Indie / Self-Published | L31: Anvita Belawal | M31: 46287 | N31: Vanshika V | P31: https://docs.google.com/document/d/1cidwwxCp6DNnWWCH4_WIlQrFw1aoHtVP/edit?usp=drive_link&ouid=101023058405307348147&rtpof=true&sd=true | Q31: https://drive.google.com/drive/folders/1iuKouMCNp5kc5pN4EiO86IAUYCfXgVCW?usp=drive_link | R31: =IF(E31=H31,"Don't Proceed","Proceed")
A32: Fated Mates of the Kalixian Warriors | B32: Presley Hall | C32: War College / Military Academy | D32: https://www.goodreads.com/series/287380-fated-mates-of-the-kalixian-warriors | E32: 4416 | F32: 3.79 | G32: 11 | H32: 2775 | I32: ), Meg Price (Narrator), C.J. Grey (Narrator) Format: Audible Audiobook | J32: New Keywords - Amazon | L32: Anvita Belawal | M32: 46287 | N32: Vanshika V | P32: https://docs.google.com/document/d/1fU3A3jL3XownZJPLdp9-vzwJIjo0DGlx/edit?usp=drive_link&ouid=101023058405307348147&rtpof=true&sd=true | Q32: https://drive.google.com/drive/folders/1tHlyDWWk1-EP41yl7yRQop5WGua4DS7p?usp=drive_link | R32: =IF(E32=H32,"Don't Proceed","Proceed")
A33: Dragon Gate | B33: Lindsay Buroker | C33: War College / Military Academy | D33: https://www.goodreads.com/series/315969-dragon-gate | E33: 4382 | F33: 4.35 | G33: 6 | H33: 3357 | I33: ), Vivienne Leheny (Narrator) Format: Audible Audiobook | J33: New Keywords - Amazon | L33: Anvita Belawal | M33: 46287 | N33: Vanshika V | P33: https://docs.google.com/document/d/19kBUs4mdlhlAVss6u0SPsyHFLnQUwP4E/edit?usp=drive_link&ouid=101023058405307348147&rtpof=true&sd=true | Q33: https://drive.google.com/drive/folders/1ub7cSKnTpvMdGNp8dcXlTevRhkQDD5dR?usp=drive_link | R33: =IF(E33=H33,"Don't Proceed","Proceed")
A34: Demon Days, Vampire Nights World | B34: K.F. Breene | C34: Paranormal Romance ( Done ) | D34: https://www.goodreads.com/series/236329-demon-days-vampire-nights | E34: 4346 | F34: 4.15 | G34: 11 | H34: 4259 | I34: ) Format: Audible Audiobook | J34: New Keywords - Amazon | L34: Anvita Belawal | M34: 46287 | N34: Vanshika V | P34: https://docs.google.com/document/d/19nkgtLmeZLuwCZW1jhMwU6OsMEK5VCQd/edit?usp=drive_link&ouid=101023058405307348147&rtpof=true&sd=true | Q34: https://drive.google.com/drive/folders/10j9EENylymYmX8q2eJBD6vaRB2HD6BSf?usp=drive_link | R34: =IF(E34=H34,"Don't Proceed","Proceed")
A35: Premonition Pointe | B35: Deanna Chase | C35: Urban / Contemporary Fantasy Romance | D35: https://www.goodreads.com/series/283848-premonition-pointe | E35: 4325 | F35: 4.26 | G35: 6 | H35: 1493 | I35: Bayou Moon Press, LLC | J35: Self-Represented / N/A | K35: Indie / Self-Published | L35: Anvita Belawal | M35: 46287 | N35: Vanshika V | P35: https://docs.google.com/document/d/19BM4q7FGC5CUMNY6WZE2aNME3c7UweQm/edit?usp=drive_link&ouid=101023058405307348147&rtpof=true&sd=true | Q35: https://drive.google.com/drive/folders/1y3rl2wOr7r0OrSLlt-pNRR2ZXF5ERhPQ?usp=drive_link | R35: =IF(E35=H35,"Don't Proceed","Proceed")
A36: Dark Fae Academy Series | B36: G. Bailey | C36: Gothic Dark Romantasy | D36: https://www.goodreads.com/series/277772-dark-fae-academy | E36: 4298 | F36: 3.95 | G36: 6 | H36: 1353 | I36: Indie / Self-Published | J36: Self-Represented / N/A | K36: Indie / Self-Published | L36: Anvita Belawal | M36: 46287 | N36: Vanshika V | P36: https://docs.google.com/document/d/1y5IYi3T4ZVoacWbNjyi12sT-Bs_7MqxD/edit?usp=drive_link&ouid=101023058405307348147&rtpof=true&sd=true | Q36: https://drive.google.com/drive/folders/1prRKYyKMAnyPPl39e2qGyJCWCkQLf-Fu?usp=drive_link | R36: =IF(E36=H36,"Don't Proceed","Proceed")
A37: Blue Halo | B37: Nyssa Kathryn | C37: War College / Military Academy | D37: https://www.goodreads.com/series/336733-blue-halo | E37: 4246 | F37: 4.33 | G37: 8 | H37: 2217 | I37: NW Partners PTY LTD, Blue Nose Publishing | J37: New Keywords - Amazon | L37: Anvita Belawal | M37: 46287 | N37: Vanshika V | P37: https://docs.google.com/document/d/1_Gc_YtOzihGoK5AA8ZDSZrna3Z3YBP-R/edit?usp=drive_link&ouid=101023058405307348147&rtpof=true&sd=true | Q37: https://drive.google.com/drive/folders/1Wsb01nygNktmGl70qyAt4XSQzNiUYR8W?usp=drive_link | R37: =IF(E37=H37,"Don't Proceed","Proceed")
A38: Bound by the Veil | B38: Helen Scott | C38: Gothic Dark Romantasy | D38: https://www.goodreads.com/series/371485-bound-by-the-veil | E38: 4187 | F38: 3.72 | G38: 5 | H38: 1279 | I38: Amazon Digital Services | J38: Self-Represented / N/A | K38: Podium Audio | L38: Anvita Belawal | M38: 46287 | N38: Vanshika V | P38: https://docs.google.com/document/d/19-YGDwHHAigGsLwbjofR39xJ6FUXw4Q8/edit?usp=drive_link&ouid=101023058405307348147&rtpof=true&sd=true | Q38: https://drive.google.com/drive/folders/1G7oj48kBZI0eRipbkpoPXjK2wXJYsZQk?usp=drive_link | R38: =IF(E38=H38,"Don't Proceed","Proceed")
A39: The Coven: Academy Magic | B39: by Chandelle LaVaun | C39: Hidden Magic Romance | D39: https://www.goodreads.com/series/256280-the-coven-academy-magic | E39: 4166 | F39: 4.34 | G39: 5 | H39: 1957 | I39: Amazon.com Services LLC Items included | J39: New Keywords - Amazon | L39: Anvita Belawal | M39: 46287 | N39: Vanshika V | P39: https://docs.google.com/document/d/1etGUJeyrMIhm8w8w_X7S7bjaxLQg3d_2/edit?usp=drive_link&ouid=101023058405307348147&rtpof=true&sd=true | Q39: https://drive.google.com/drive/folders/1TzoXB6N3TFaaMSj6wUId305kyf6M6Z2l?usp=drive_link | R39: =IF(E39=H39,"Don't Proceed","Proceed")
A40: The Zheninghai Chronicles | B40: Anastasis Blythe | C40: High Fantasy Court Adventure | D40: https://www.goodreads.com/series/350713-the-zheninghai-chronicles | E40: 4107 | F40: 4.28 | G40: 6 | H40: 2365 | I40: Indie / Self-Published | J40: New Keywords - Amazon | L40: Anvita Belawal | M40: 46287 | N40: Vanshika V | P40: https://docs.google.com/document/d/1k5xjz-KBPsqBZxfYv3M-e_HmLLUti6wc/edit?usp=drive_link&ouid=101023058405307348147&rtpof=true&sd=true | Q40: https://drive.google.com/drive/folders/1YUMEzBSg4Fh8K_eqLdYI1uRLJ4k3RLor?usp=drive_link | R40: =IF(E40=H40,"Don't Proceed","Proceed")
A41: Posy | B41: Mary Ann Weir | C41: Werewolf / Shifter Romance | D41: https://www.goodreads.com/series/363550-five-fangs | E41: 4072 | G41: 5 | H41: 1487 | I41: Indie / Self-Published | J41: Self-Represented / N/A | K41: Indie / Self-Published | L41: Anvita Belawal | M41: 46287 | N41: Vanshika V | P41: Not found | R41: =IF(E41=H41,"Don't Proceed","Proceed")
A42: Refurbished Fairy Tales | B42: S.R. Nulton | C42: Romantasy | D42: https://www.goodreads.com/series/267589-refurbished-fairy-tales | E42: 4038 | F42: 4.06 | G42: 11 | H42: 3057 | I42: Indie / Self-Published | J42: New Keywords - Amazon | L42: Anvita Belawal | M42: 46287 | N42: Vanshika V | P42: Not found | R42: =IF(E42=H42,"Don't Proceed","Proceed")
A43: Royal Houses | B43: K.A. Linde | C43: High Fantasy Court Adventure | D43: https://www.goodreads.com/series/244593-royal-houses | E43: 4031 | F43: 3.9 | G43: 5 | H43: 2363 | I43: Indie / Self-Published | J43: New Keywords - Amazon | L43: Anvita Belawal | M43: 46287 | N43: Vanshika V | P43: https://docs.google.com/document/d/1Nv1bdtx4QFF8uTpgj7zYL4LNG_Jml11n/edit?usp=drive_link&ouid=101023058405307348147&rtpof=true&sd=true | Q43: https://drive.google.com/drive/folders/1EOX8Uv_oaj0Z5dhi7p2IoLTDUhAmHa2m?usp=drive_link | R43: =IF(E43=H43,"Don't Proceed","Proceed")
A44: Warlock | B44: Daniel Kensington | C44: Urban Fantasy Romance | D44: https://www.goodreads.com/series/404952-warlock | E44: 3992 | F44: 4.59 | G44: 3 | H44: 1634 | I44: Royal Guard Publishing LLC | J44: New Keywords - Amazon | L44: Anvita Belawal | M44: 46287 | N44: Vanshika V | P44: https://docs.google.com/document/d/1EmISN5pr7INGzrJaYCJ8nh3s4U_-CIqu/edit?usp=drive_link&ouid=101023058405307348147&rtpof=true&sd=true | Q44: https://drive.google.com/drive/folders/1z1A3HJ57pxHqmmRaQ1_kygCVhsp3XUzE?usp=drive_link | R44: =IF(E44=H44,"Don't Proceed","Proceed")
A45: Vampire Royals of New York | B45: Sarah Piper | C45: High Fantasy Court Adventure | D45: https://www.goodreads.com/series/300159-vampire-royals-of-new-york | E45: 3987 | F45: 3.89 | G45: 6 | H45: 2078 | I45: Two Gnomes Media | J45: New Keywords - Amazon | L45: Anvita Belawal | M45: 46287 | N45: Vanshika V | P45: https://docs.google.com/document/d/1Jw6EuAjB2u1ZSrz5lZ0hiPXRkaRPqmgF/edit?usp=drive_link&ouid=101023058405307348147&rtpof=true&sd=true | Q45: https://drive.google.com/drive/folders/169CliP5wD-YPb0s300F1z1ZKGEZdD-HD?usp=drive_link | R45: =IF(E45=H45,"Don't Proceed","Proceed")
A46: Spooky Boys | B46: Fae Quin | C46: Monster Romance ( Non-Shifter ) | D46: https://www.goodreads.com/series/350648-spooky-boys | E46: 3946 | F46: 3.89 | G46: 4 | H46: 1969 | I46: ) Format: Audible Audiobook | J46: New Keywords - Amazon | L46: Anvita Belawal | M46: 46287 | N46: Vanshika V | P46: https://docs.google.com/document/d/1AgbR6xbj0D035AVRzCHV-Ny0NwcNqBdI/edit?usp=drive_link&ouid=101023058405307348147&rtpof=true&sd=true | Q46: https://drive.google.com/drive/folders/1GUWp5vfqszTkE9SZuJpbRU42QddWGzPG?usp=drive_link | R46: =IF(E46=H46,"Don't Proceed","Proceed")
A47: The Dragon Kings of Fire and Ice | B47: Amelia Shaw | C47: Werewolf / Shifter Romance | D47: https://www.goodreads.com/series/315067-fire-and-ice | E47: 3931 | F47: 3.52 | G47: 10 | H47: 1445 | I47: Indie / Self-Published | J47: Self-Represented / N/A | K47: Indie / Self-Published | L47: Anvita Belawal | M47: 46287 | N47: Noel Regis | P47: https://docs.google.com/document/d/1y6LD-3p0uA4TY-KDu3ZHEAvPCz2PiaWR/edit?usp=drive_link&ouid=101023058405307348147&rtpof=true&sd=true | Q47: The Dragon Kings of Fire and Ice | R47: =IF(E47=H47,"Don't Proceed","Proceed")
A48: The Imogen Gray Series | B48: Lauretta Hignett | C48: Werewolf / Shifter Romance | D48: https://www.goodreads.com/series/344265-imogen-gray | E48: 3853 | F48: 4.35 | G48: 5 | H48: 1334 | I48: Indie / Self-Published | J48: Self-Represented / N/A | K48: LCH Publishing Pty Ltd | L48: Anvita Belawal | M48: 46287 | N48: Noel Regis | P48: https://docs.google.com/document/d/1Maa-AmFBpmcqDe7OdDmmqX1a_iARBKGd/edit?usp=drive_link&ouid=101023058405307348147&rtpof=true&sd=true | Q48: The Imogen Gray Series | R48: =IF(E48=H48,"Don't Proceed","Proceed")
A49: A Winterbourne Brotherhood Shifter Romance Book 1 of 2: A Winterbourne Brother... | B49: by Meg Anne | C49: Werewolf / Shifter Romance | D49: https://www.goodreads.com/series/382445-the-mate-games-death | E49: 3834 | F49: 4.12 | G49: 4 | H49: 1589 | I49: Indie / Self-Published | J49: Self-Represented / N/A | K49: Indie / Self-Published | L49: Anvita Belawal | M49: 46287 | N49: Noel Regis | P49: https://docs.google.com/document/d/1lxvPQhYcfXwDKU432UmSq9cGoU-N_bba/edit?usp=drive_link&ouid=101023058405307348147&rtpof=true&sd=true | R49: =IF(E49=H49,"Don't Proceed","Proceed")
A50: Shades of Ruin and Magic | B50: Meg Xuemei X | C50: Subjective | D50: https://www.goodreads.com/series/379435-shades-of-ruin-and-magic | E50: 3817 | F50: 4.35 | G50: 6 | H50: 2028 | I50: House of Shades and Fantasy | J50: New Keywords - Amazon | L50: Anvita Belawal | M50: 46287 | N50: Noel Regis | P50: https://docs.google.com/document/d/18gFDArJA8yRkycaAXKNztgRdDmhDmy3q/edit?usp=drive_link&ouid=101023058405307348147&rtpof=true&sd=true | Q50: Shades of Ruin and Magic | R50: =IF(E50=H50,"Don't Proceed","Proceed")
A51: Seaside Wolf Pack | B51: C.C. Masters | C51: Werewolf / Shifter Romance | D51: https://www.goodreads.com/series/221203-seaside-wolf-pack | E51: 3779 | F51: 3.95 | G51: 6 | H51: 1468 | I51: Indie / Self-Published | J51: Self-Represented / N/A | K51: Indie / Self-Published | L51: Anvita Belawal | M51: 46287 | N51: Noel Regis | P51: https://docs.google.com/document/d/1pdA2mDUJ_3rXGRyezz-kVuiqwyPzMhxE/edit?usp=drive_link&ouid=101023058405307348147&rtpof=true&sd=true | Q51: Seaside Wolf Pack | R51: =IF(E51=H51,"Don't Proceed","Proceed")
A52: Desolation | B52: Kortney Keisel | C52: High Fantasy Court Adventure | D52: https://www.goodreads.com/series/313028-desolation | E52: 3707 | F52: 4.01 | G52: 4 | H52: 1224 | I52: Indie / Self-Published | J52: Self-Represented / N/A | K52: Indie / Self-Published | L52: Anvita Belawal | M52: 46287 | N52: Noel Regis | P52: https://docs.google.com/document/d/1QugoJBB3Y2g83fsYOe46Ea3r8EFRHORx/edit?usp=drive_link&ouid=101023058405307348147&rtpof=true&sd=true | Q52: Desolation | R52: =IF(E52=H52,"Don't Proceed","Proceed")
A53: Manga | B53: Hinoki Kino | C53: Korean Romance Fantasy / Isekai | D53: https://www.goodreads.com/series/331974-7-manga | E53: 3625 | F53: 4.37 | G53: 9 | H53: 1660 | I53: Dokico | J53: New Keywords - Amazon | L53: Anvita Belawal | M53: 46287 | N53: Noel Regis | P53: https://docs.google.com/document/d/1DI_83T3PA7-vevFgU7c9BAUHcrpwQlBx/edit?usp=drive_link&ouid=101023058405307348147&rtpof=true&sd=true | Q53: Manga | R53: =IF(E53=H53,"Don't Proceed","Proceed")
A54: Le Beau Series | B54: V.A. Dold | C54: War College / Military Academy | D54: https://www.goodreads.com/series/124674-le-beau-brothers | E54: 3606 | F54: 3.86 | G54: 9 | H54: 2383 | I54: Vadold | J54: New Keywords - Amazon | L54: Anvita Belawal | M54: 46287 | N54: Noel Regis | P54: https://docs.google.com/document/d/1gD84Zaax-H9fphUdSAPqCL9d0zn3KjvZ/edit?usp=drive_link&ouid=101023058405307348147&rtpof=true&sd=true | Q54: Le Beau Series | R54: =IF(E54=H54,"Don't Proceed","Proceed")
A55: The Daughters of the Earth | B55: Susan Carroll | C55: Gothic Dark Romantasy | D55: https://www.goodreads.com/series/40695-the-dark-queen-saga | E55: 3513 | F55: 3.87 | G55: 6 | H55: 2993 | I55: Oliver Heber Books | J55: New Keywords - Amazon | L55: Anvita Belawal | M55: 46287 | N55: Noel Regis | P55: https://docs.google.com/document/d/1mfCcMbi5-fQfI09H2cPRPK3KYy8bTKRg/edit?usp=drive_link&ouid=101023058405307348147&rtpof=true&sd=true | Q55: The Daughters of the Earth | R55: =IF(E55=H55,"Don't Proceed","Proceed")
A56: The Masks of Under | B56: Kathryn Ann Kingsley | C56: Werewolf / Shifter Romance | D56: https://www.goodreads.com/series/257607-the-masks-of-under | E56: 3488 | F56: 3.82 | G56: 6 | H56: 1537 | I56: Second Sky | J56: Self-Represented / N/A | K56: Indie / Self-Published | L56: Anvita Belawal | M56: 46287 | N56: Anushka Baisya | P56: https://docs.google.com/document/d/1fDjf30taMloZyeXGmdCipPQTEVthjBvd/edit?usp=drive_link&ouid=101023058405307348147&rtpof=true&sd=true | Q56: The Masks of Under | R56: =IF(E56=H56,"Don't Proceed","Proceed")
A57: Timeless Fairy Tales | B57: K. M. Shea | C57: Werewolf / Shifter Romance | D57: https://www.goodreads.com/series/135228-timeless-fairy-tales | E57: 3484 | F57: 4.12 | G57: 11 | H57: 2945 | I57: Indie / Self-Published | J57: New Keywords - Amazon | L57: Anvita Belawal | M57: 46287 | N57: Anushka Baisya | P57: https://docs.google.com/document/d/17-PJuANvHXmbLI25R2VFJaQOyv3idk3s/edit?usp=drive_link&ouid=101023058405307348147&rtpof=true&sd=true | Q57: Timeless Fairy Tales | R57: =IF(E57=H57,"Don't Proceed","Proceed")
A58: The Fae Universe | B58: Meg Xuemei X | C58: Mythology, Legend & Fairy Tale Retelling | D58: https://www.goodreads.com/series/314927-the-fae-universe | E58: 3472 | F58: 3.75 | G58: 14 | H58: 3482 | I58: Indie / Self-Published | J58: New Keywords - Amazon | L58: Anvita Belawal | M58: 46287 | N58: Anushka Baisya | P58: https://docs.google.com/document/d/1T8KPjbvLEiOvskP8ob94kS6dMkUjr9Yq/edit?usp=drive_link&ouid=101023058405307348147&rtpof=true&sd=true | Q58: The Fae Universe | R58: =IF(E58=H58,"Don't Proceed","Proceed")
A59: The Killigrew Street Case Files | B59: TJ Rose | C59: Paranormal Romance | D59: https://www.goodreads.com/series/413536-the-killigrew-street-case-files | E59: 3458 | G59: 4 | H59: 1521 | I59: Indie / Self-Published | J59: Self-Represented / N/A | K59: Tantor Media | L59: Anvita Belawal | M59: 46287 | N59: Anushka Baisya | P59: https://docs.google.com/document/d/1oPmz-q8vxspotu8zTpFEMAXF4WujRPde/edit?usp=drive_link&ouid=101023058405307348147&rtpof=true&sd=true | Q59: The Killigrew Street Case Files | R59: =IF(E59=H59,"Don't Proceed","Proceed")
A60: The Chosen One | B60: Macy Blake | C60: Werewolf / Shifter Romance | D60: https://www.goodreads.com/series/239269-the-chosen-one | E60: 3433 | F60: 4 | G60: 6 | H60: 1402 | I60: Macy Blake | J60: Self-Represented / N/A | K60: Indie / Self-Published | L60: Anvita Belawal | M60: 46287 | N60: Anushka Baisya | P60: https://docs.google.com/document/d/1q-o5sQFSaFpHA3f0rcGeRp_NXTNiKN9I/edit?usp=drive_link&ouid=101023058405307348147&rtpof=true&sd=true | Q60: The Chosen One | R60: =IF(E60=H60,"Don't Proceed","Proceed")
A61: Fae-ted Kings | B61: Milana Jacks | C61: High Fantasy Court Adventure | D61: https://www.goodreads.com/series/377126-fae-ted-kings | E61: 3415 | F61: 3.92 | G61: 4 | H61: 1213 | I61: Milana Jacks, LLC | J61: Self-Represented / N/A | K61: Indie / Self-Published | L61: Anvita Belawal | M61: 46287 | N61: Anushka Baisya | P61: https://docs.google.com/document/d/1zKZH40_qsW-8Vis_NLTfLl3wMv8ET2NL/edit?usp=drive_link&ouid=101023058405307348147&rtpof=true&sd=true | Q61: Fae-ted Kings | R61: =IF(E61=H61,"Don't Proceed","Proceed")
A62: The Demons' Muse | B62: Auryn Hadley | C62: Paranormal Romance ( Done ) | D62: https://www.goodreads.com/series/228852-the-demons-muse | E62: 3388 | F62: 4.15 | G62: 5 | H62: 2489 | I62: Spotted Horse Productions | J62: New Keywords - Amazon | L62: Anvita Belawal | M62: 46287 | N62: Anushka Baisya | P62: https://docs.google.com/document/d/1pR6va2cf93uXEbuomDisyMFRX0jeVex1/edit?usp=drive_link&ouid=101023058405307348147&rtpof=true&sd=true | Q62: The Demons' Muse | R62: =IF(E62=H62,"Don't Proceed","Proceed")
A63: Warwitch Academy | B63: Virgil Knightley | C63: Romantasy | D63: https://www.goodreads.com/series/430733-warwitch-academy | E63: 3382 | F63: 4.36 | G63: 4 | H63: 1616 | I63: Royal Guard Publishing LLC | J63: New Keywords - Amazon | L63: Anvita Belawal | M63: 46287 | N63: Anushka Baisya | P63: https://docs.google.com/document/d/1j7JWroqVAOlASLjk1-uwaEkHyBcgcLbY/edit?usp=drive_link&ouid=101023058405307348147&rtpof=true&sd=true | Q63: Warwitch Academy | R63: =IF(E63=H63,"Don't Proceed","Proceed")
A64: Dark World: The Vampire Wish | B64: Michelle Madow | C64: High Fantasy Court Adventure | D64: https://www.goodreads.com/series/205576-dark-world-the-vampire-wish | E64: 3377 | F64: 3.93 | G64: 5 | H64: 1306 | I64: Dreamscape Publishing | J64: Self-Represented / N/A | K64: Indie / Self-Published | L64: Noel Regis | M64: 46287 | P64: Book 1 - Dark World The Vampire Wish.docx | Q64: Dark World The Vampire Wish | R64: =IF(E64=H64,"Don't Proceed","Proceed")
A65: Midnight Hunters | B65: Margot Hunt | C65: Werewolf / Shifter Romance | D65: https://www.goodreads.com/series/71583-midnight-hunters | E65: 3367 | F65: 3.99 | G65: 9 | H65: 2257 | I65: Indie / Self-Published | J65: Jane Rotrosen Agency | L65: Noel Regis | M65: 46287 | P65: Book 1 - The Hidden King.docx | Q65: Midnight Hunters | R65: =IF(E65=H65,"Don't Proceed","Proceed")
A66: Lost Fae | B66: May Dawson | C66: High Fantasy Court Adventure | D66: https://www.goodreads.com/series/298923-lost-fae | E66: 3364 | F66: 4.1 | G66: 4 | H66: 1597 | I66: Indie / Self-Published | J66: Self-Represented / N/A | K66: Indie / Self-Published | L66: Noel Regis | M66: 46287 | P66: Book 1 - Lost Fae.docx | Q66: Lost Fae | R66: =IF(E66=H66,"Don't Proceed","Proceed")
A67: Protection, Inc: Defenders Collection 1 | B67: Zoe Chant | C67: War College / Military Academy | D67: https://www.goodreads.com/series/164241-protection-inc | E67: 3352 | F67: 4.07 | G67: 7 | H67: 1473 | I67: Zoe Chant | J67: Self-Represented / N/A | K67: Podium Audio | L67: Noel Regis | M67: 46287 | P67: Book 1 - Protection Inc.docx | Q67: Protection Inc | R67: =IF(E67=H67,"Don't Proceed","Proceed")
A68: Forbidden Bond | B68: Cat Miller | C68: Gothic Dark Romantasy | D68: https://www.goodreads.com/series/84357-the-forbidden-bond | E68: 3346 | F68: 3.93 | G68: 3 | H68: 1295 | I68: Indie / Self-Published | J68: Self-Represented / N/A | K68: Audible Studios | L68: Noel Regis | M68: 46287 | P68: Book 1 - The Forbidden Bond.docx | Q68: The Forbidden Bond | R68: =IF(E68=H68,"Don't Proceed","Proceed")
A69: Saga Skolian Empire | B69: B.L. Brown | C69: Subjective | D69: https://www.goodreads.com/series/40379-saga-of-the-skolian-empire | E69: 3336 | F69: 3.74 | G69: 14 | H69: 5690 | I69: Indie / Self-Published | J69: New Keywords - Amazon | L69: Noel Regis | M69: 46287 | P69: Book 1 - Saga Of The Skolian Empire.docx | Q69: Saga Of The Skolian Empire | R69: =IF(E69=H69,"Don't Proceed","Proceed")
A70: Return to the Four Kingdoms | B70: Melanie Cellier | C70: High Fantasy Court Adventure | D70: https://www.goodreads.com/series/289847-return-to-the-four-kingdoms | E70: 3317 | F70: 4.25 | G70: 6 | H70: 1861 | I70: Indie / Self-Published | J70: New Keywords - Amazon | L70: Noel Regis | M70: 46287 | P70: Book 1 - Return To The Four Kingdoms.docx | Q70: Return To The Four Kingdoms | R70: =IF(E70=H70,"Don't Proceed","Proceed")
A71: Brides of the Moon Blade Clan | B71: Krista Luna | C71: Monster Romance ( Non-Shifter ) | D71: https://www.goodreads.com/series/385994-brides-of-the-moon-blade-clan | E71: 3305 | F71: 3.84 | G71: 6 | H71: 2086 | I71: Indie / Self-Published | J71: New Keywords - Amazon | L71: Noel Regis | M71: 46287 | P71: Book 1 - Brides Of The Moon Blade Clan.docx | Q71: Brides Of The Moon Blade Clan | R71: =IF(E71=H71,"Don't Proceed","Proceed")
A72: Wicked University | B72: Emma Dean | C72: War College / Military Academy | D72: https://www.goodreads.com/series/258881-university-of-morgana-academy-of-enchantments-and-witchcraft | E72: 3270 | F72: 4.14 | G72: 9 | H72: 2698 | I72: Emma Dean Romance | J72: New Keywords - Amazon | L72: Noel Regis | M72: 46287 | P72: Book 1 - University Of Morgana Academy Of Enchantments And Witchcraft.docx | Q72: University Of Morgana Academy Of Enchantments And Witchcraft | R72: =IF(E72=H72,"Don't Proceed","Proceed")
A73: The Heart of a Monster | B73: Eva Chase | C73: Werewolf / Shifter Romance | D73: https://www.goodreads.com/series/337170-the-heart-of-a-monster | E73: 3238 | F73: 3.86 | G73: 4 | H73: 1254 | I73: Indie / Self-Published | J73: JABberwocky Literary | K73: Audible Studios | L73: Noel Regis | M73: 46287 | P73: Book 1 - The Heart Of A Monster.docx | Q73: The Heart Of A Monster | R73: =IF(E73=H73,"Don't Proceed","Proceed")
A74: Tribute Brides of the Drexian Warriors | B74: Tana Stone | C74: War College / Military Academy | D74: https://www.goodreads.com/series/268208-tribute-brides-of-the-drexian-warriors | E74: 3226 | F74: 3.95 | G74: 10 | H74: 2232 | I74: Broadmoor Books | J74: New Keywords - Amazon | L74: Noel Regis | M74: 46287 | P74: Book 1 - Tribute Brides Of The Drexian Warriors.docx | Q74: Tribute Brides Of The Drexian Warriors | R74: =IF(E74=H74,"Don't Proceed","Proceed")
A75: Light Novel | B75: Inori | C75: Korean Romance Fantasy / Isekai | D75: https://www.goodreads.com/series/299342-i-m-in-love-with-the-villainess-light-novel | E75: 3196 | F75: 3.93 | G75: 5 | H75: 1813 | I75: Airship | J75: New Keywords - Amazon | L75: Noel Regis | M75: 46287 | P75: Book 1 - I M In Love With The Villainess Light Novel.docx | Q75: I M In Love With The Villainess Light Novel | R75: =IF(E75=H75,"Don't Proceed","Proceed")
A76: Immortal Hunters (5 books) | B76: Shaylin Gandhi | C76: Gothic Dark Romantasy | D76: https://www.goodreads.com/series/436604-immortal-hunters | E76: 3190 | F76: 3.98 | G76: 5 | H76: 2171 | I76: Briar Rose Publishing | J76: New Keywords - Amazon | L76: Noel Regis | M76: 46287 | P76: Book 1 - Immortal Hunters.docx | Q76: Immortal Hunters | R76: =IF(E76=H76,"Don't Proceed","Proceed")
A77: The Book of All Things | B77: Sarah M. Cradit | C77: High Fantasy Court Adventure | D77: https://www.goodreads.com/series/330123-the-book-of-all-things | E77: 3184 | F77: 3.48 | G77: 10 | H77: 4578 | I77: Storyville Press | J77: New Keywords - Amazon | L77: Noel Regis | M77: 46287 | P77: Book 1 - The Book Of All Things.docx | Q77: The Book Of All Things | R77: =IF(E77=H77,"Don't Proceed","Proceed")
A78: Awakened Fates | B78: Lucinda Dark | C78: Korean Romance Fantasy / Isekai | D78: https://www.goodreads.com/series/371074-awakened-fates | E78: 3183 | F78: 3.81 | G78: 3 | H78: 1254 | I78: Dreamscape Media | J78: Self-Represented / N/A | K78: Indie / Self-Published | L78: Noel Regis | M78: 46287 | P78: Book 1 - Awakened Fates.docx | Q78: Awakened Fates | R78: =IF(E78=H78,"Don't Proceed","Proceed")
A79: Black Arrowhead Series | B79: Dannika Dark | C79: Hidden Magic Romance | D79: https://www.goodreads.com/series/302052-black-arrowhead | E79: 3154 | F79: 4.28 | G79: 9 | H79: 3402 | I79: ) Format: Audible Audiobook | J79: New Keywords - Amazon | L79: Noel Regis | M79: 46287 | P79: Book 1 - Black Arrowhead.docx | Q79: Black Arrowhead | R79: =IF(E79=H79,"Don't Proceed","Proceed")
A80: The Merlin Mysteries | B80: Kim Richardson | C80: Paranormal Romance ( Done ) | D80: https://www.goodreads.com/series/430624-the-merlin-mysteries | E80: 3131 | F80: 4.39 | G80: 6 | H80: 2056 | I80: ), Kasi Hollowell (Narrator) Format: Audible Audiobook | J80: New Keywords - Amazon | L80: Noel Regis | M80: 46287 | P80: Book 1 - The Merlin Mysteries.docx | Q80: The Merlin Mysteries | R80: =IF(E80=H80,"Don't Proceed","Proceed")
A81: Savage | B81: Mila Young | C81: Werewolf / Shifter Romance | D81: https://www.goodreads.com/series/316366-savage | E81: 3112 | F81: 3.84 | G81: 4 | H81: 1270 | I81: Indie / Self-Published | J81: Self-Represented / N/A | K81: Audible Studios | L81: Noel Regis | M81: 46287 | P81: 1_Lost Wolf (Mila Young) (z-library.sk, 1lib.sk, z-lib.sk).docx | Q81: Savage | R81: =IF(E81=H81,"Don't Proceed","Proceed")
A82: A Medieval Tale | B82: Lina J. Potter | C82: High Fantasy Court Adventure | D82: https://www.goodreads.com/series/140692-a-medieval-tale | E82: 3106 | F82: 3.9 | G82: 10 | H82: 4330 | I82: Indie / Self-Published | J82: New Keywords - Amazon | L82: Noel Regis | M82: 46287 | P82: Book 1 - A Medieval Tale.docx | Q82: A Medieval Tale | R82: =IF(E82=H82,"Don't Proceed","Proceed")
A83: Spell Traveler Chronicles | B83: Avery Song | C83: War College / Military Academy | D83: https://www.goodreads.com/series/263854-spell-traveler-chronicles | E83: 3105 | F83: 4.17 | G83: 8 | H83: 2823 | I83: ), Lacy Laurel (Narrator) Format: Audible Audiobook | J83: New Keywords - Amazon | L83: Noel Regis | M83: 46287 | P83: Book 1 - Spell Traveler Chronicles.docx | Q83: Spell Traveler Chronicles | R83: =IF(E83=H83,"Don't Proceed","Proceed")
A84: Ruthless Warlords | B84: Gabrielle Bisset | C84: High Fantasy Court Adventure | D84: https://www.goodreads.com/series/306949-ruthless-warlords | E84: 3101 | F84: 3.82 | G84: 11 | H84: 9252 | I84: Indie / Self-Published | J84: New Keywords - Amazon | L84: Noel Regis | M84: 46287 | P84: Book 1 - Ruthless Warlords.docx | Q84: Ruthless Warlords | R84: =IF(E84=H84,"Don't Proceed","Proceed")
A85: A Tempest of Shadows | B85: Jane Washington | C85: Secret Magic World | D85: https://www.goodreads.com/series/309927-a-tempest-of-shadows | E85: 3092 | F85: 3.92 | G85: 5 | H85: 1749 | I85: ), Jennifer Sterling (Narrator) Format: Audible Audiobook | J85: New Keywords - Amazon | L85: Noel Regis | M85: 46287 | P85: Book 1 - A Tempest Of Shadows.docx | Q85: A Tempest Of Shadows | R85: =IF(E85=H85,"Don't Proceed","Proceed")
A86: Hopeless Blessed | B86: Lark Taylor | C86: Paranormal Romance | D86: https://www.goodreads.com/series/383082-hopeless-blessed | E86: 3076 | G86: 4 | H86: 1747 | I86: Indie / Self-Published | J86: Self-Represented / N/A | K86: Podium Audio | L86: Noel Regis | M86: 46287 | P86: Book 1 - Hopeless Blessed.docx | Q86: Hopeless Blessed | R86: =IF(E86=H86,"Don't Proceed","Proceed")
A87: Legacy Academy | B87: M Guida | C87: War College / Military Academy | D87: https://www.goodreads.com/series/300170-legacy-academy | E87: 3055 | F87: 4.09 | G87: 8 | H87: 1884 | I87: ) Format: Audible Audiobook | J87: New Keywords - Amazon | L87: Noel Regis | M87: 46287 | P87: Book 1 - Legacy Academy.docx | Q87: Legacy Academy | R87: =IF(E87=H87,"Don't Proceed","Proceed")
A88: Villains | B88: C. Spike Trotman | C88: Subjective | D88: https://www.goodreads.com/series/162322-villains | E88: 3054 | F88: 3.81 | G88: 12 | H88: 3600 | I88: Indie / Self-Published | J88: New Keywords - Amazon | L88: Noel Regis | M88: 46287 | P88: 1_Fairest of All (Villains 1) (Valentino Serena) (z-library.sk, 1lib.sk, z-lib.sk).docx | Q88: Villains | R88: =IF(E88=H88,"Don't Proceed","Proceed")
A89: Glamourist Histories | B89: Mary Robinette Kowal | C89: High Fantasy Court Adventure | D89: https://www.goodreads.com/series/68417-glamourist-histories | E89: 3029 | F89: 3.51 | G89: 5 | H89: 1877 | I89: Indie / Self-Published | J89: New Keywords - Amazon | L89: Noel Regis | M89: 46287 | P89: Book 1 - Glamourist Histories.docx | Q89: Glamourist Histories | R89: =IF(E89=H89,"Don't Proceed","Proceed")
A90: Force of Nature | B90: Amber Lynn Natusch | C90: Werewolf / Shifter Romance | D90: https://www.goodreads.com/series/174182-force-of-nature | E90: 3029 | F90: 3.85 | G90: 5 | H90: 1355 | I90: Indie / Self-Published | J90: Self-Represented / N/A | K90: Indie / Self-Published | L90: Noel Regis | M90: 46287 | P90: Book 1 - Force Of Nature.docx | Q90: Force Of Nature | R90: =IF(E90=H90,"Don't Proceed","Proceed")
A91: The Witch's Seal: The Ellwood Chronicles Prequel | B91: Michele Notaro | C91: Urban / Contemporary Fantasy Romance | D91: https://www.goodreads.com/series/241751-the-ellwood-chronicles | E91: 3021 | F91: 4.12 | G91: 5 | H91: 1270 | I91: Indie / Self-Published | J91: Self-Represented / N/A | K91: Indie / Self-Published | L91: Noel Regis | M91: 46287 | P91: Book 1 - The Ellwood Chronicles.docx | Q91: The Ellwood Chronicles | R91: =IF(E91=H91,"Don't Proceed","Proceed")
A92: The Four | B92: Layla Frost | C92: Werewolf / Shifter Romance | D92: https://www.goodreads.com/series/246755-the-four | E92: 3015 | F92: 4.02 | G92: 4 | H92: 1348 | I92: Indie / Self-Published | J92: Self-Represented / N/A | K92: Indie / Self-Published | L92: Noel Regis | M92: 46287 | P92: Book 1 - The Four.docx | Q92: The Four | R92: =IF(E92=H92,"Don't Proceed","Proceed")
A93: Dragon Firefighters | B93: Ashe Moon | C93: War College / Military Academy | D93: https://www.goodreads.com/series/321437-dragon-firefighters | E93: 2881 | F93: 3.96 | G93: 10 | H93: 2217 | I93: Independently Published | J93: New Keywords - Amazon | L93: Noel Regis | M93: 46287 | P93: Book 1 - Dragon Firefighters.docx | Q93: Dragon Firefighters | R93: =IF(E93=H93,"Don't Proceed","Proceed")
A94: The Realms | B94: C.M. Carney | C94: Korean Romance Fantasy / Isekai | D94: https://www.goodreads.com/series/228656-the-realms | E94: 2869 | F94: 4.13 | G94: 8 | H94: 3275 | I94: ), Armen Taylor (Narrator) Format: Audible Audiobook | J94: New Keywords - Amazon | L94: Noel Regis | M94: 46287 | P94: Book 1 - The Realms.docx | Q94: The Realms | R94: =IF(E94=H94,"Don't Proceed","Proceed")
A95: A Rock Canyon, Idaho | B95: Codi Gary | C95: War College / Military Academy | D95: https://www.goodreads.com/series/124425-rock-canyon-idaho | E95: 2866 | F95: 3.81 | G95: 8 | H95: 2556 | I95: Avon Impulse | J95: New Keywords - Amazon | L95: Noel Regis | M95: 46287 | P95: Book 1 - Rock Canyon Idaho.docx | Q95: Rock Canyon Idaho | R95: =IF(E95=H95,"Don't Proceed","Proceed")
A96: Kings & Villains | B96: I.T. Lucas | C96: High Fantasy Court Adventure | D96: https://www.goodreads.com/series/354613-kings-villains | E96: 2856 | F96: 4.04 | G96: 6 | H96: 2723 | I96: Indie / Self-Published | J96: New Keywords - Amazon | L96: Noel Regis | M96: 46287 | P96: Book 1 - Kings Villains.docx | Q96: Kings Villains | R96: =IF(E96=H96,"Don't Proceed","Proceed")
A97: Trilyn Alien Fairy Tales | B97: Khardine Gray | C97: Urban / Contemporary Fantasy Romance | D97: https://www.goodreads.com/series/266754-trilyn-alien-fairy-tales | E97: 2833 | F97: 3.63 | G97: 9 | H97: 2390 | I97: Indie / Self-Published | J97: New Keywords - Amazon | L97: Noel Regis | M97: 46287 | P97: Book 1 - Trilyn Alien Fairy Tales.docx | Q97: Trilyn Alien Fairy Tales | R97: =IF(E97=H97,"Don't Proceed","Proceed")
A98: The Twixt | B98: Dawn Metcalf | C98: Secret Magic World | D98: https://www.goodreads.com/series/93970-the-twixt | E98: 2790 | F98: 3.64 | G98: 4 | H98: 1628 | I98: Harlequin Teen | J98: New Keywords - Amazon | L98: Noel Regis | M98: 46287 | P98: Book 1 - The Twixt.docx | Q98: The Twixt | R98: =IF(E98=H98,"Don't Proceed","Proceed")
A99: The Monsters Among Us | B99: Debbie Cassidy | C99: Werewolf / Shifter Romance | D99: https://www.goodreads.com/series/303631-the-monsters-among-us | E99: 2765 | F99: 4.18 | G99: 5 | H99: 1280 | I99: Indie / Self-Published | J99: Self-Represented / N/A | K99: Tantor Media | L99: Noel Regis | M99: 46287 | P99: Book 1 - The Monsters Among Us.docx | Q99: The Monsters Among Us | R99: =IF(E99=H99,"Don't Proceed","Proceed")
A100: Celestine Chronicles | B100: Cebelius | C100: Gothic Dark Romantasy | D100: https://www.goodreads.com/series/244662-celestine-chronicles | E100: 2759 | F100: 4.21 | G100: 6 | H100: 2093 | I100: ), Tess Irondale (Narrator) Format: Audible Audiobook | J100: New Keywords - Amazon | L100: Noel Regis | M100: 46287 | P100: Book 1 - Celestine Chronicles.docx | Q100: Celestine Chronicles | R100: =IF(E100=H100,"Don't Proceed","Proceed")
...

Sheet Batch 3 - 249
A1: Series Name | B1: Author | C1: Sub-Genre | D1: Book Series (GoodReads URL) | E1: GoodReads No. of Ratings | F1: Goodreads Book 1 Ratings | G1: Total Primary Books | H1: Total primary Books Page Count | I1: Imprint / Publisher - Book | J1: Agencies | K1: Imprint / Publisher - Audiobook | L1: Crawling POC | M1: Crawling Date | N1: Links addition POC | O1: Links Date | P1: Book 1 Link | Q1: Books (1 - 5) Links | R1: Check | S1: Batch Number
A2: Briarborn Chronicles Book 1 of 1: Briarborn Chronicles | B2: Cordelia K. Castel | C2: High Fantasy Court Adventure | D2: https://www.goodreads.com/series/289649-the-princess-trials | E2: 15812 | F2: 3.79 | G2: 3 | H2: 1448 | I2: Indie / Self-Published | J2: Self-Represented / N/A | K2: Indie / Self-Published | L2: Noel Regis | M2: 46288 | N2: Noel Regis | P2: 1_The Princess Trials (Cordelia K. Castel).docx | Q2: The Princess Trials | R2: =IF(E2=H2,"Don't Proceed","Proceed")
A3: Once Upon a Billionaire | B3: Catelyn Meadows | C3: Mythology, Legend & Fairy Tale Retelling | D3: https://www.goodreads.com/series/281284-once-upon-a-billionaire | E3: 15524 | F3: 4.11 | G3: 8 | H3: 1757 | I3: Indie / Self-Published | J3: New Keywords - Amazon | L3: Noel Regis | M3: 46288 | N3: Noel Regis | P3: 1_Goldie and the Billionaire Bear.docx | Q3: Once Upon a Billionaire | R3: =IF(E3=H3,"Don't Proceed","Proceed")
A4: Crowns of the Fae | B4: R.L. Perez | C4: Mythology, Legend & Fairy Tale Retelling | D4: https://www.goodreads.com/series/389855-crowns-of-the-fae | E4: 15523 | F4: 4.13 | G4: 3 | H4: 1614 | I4: Indie / Self-Published | J4: New Keywords - Amazon | L4: Noel Regis | M4: 46288 | N4: Noel Regis | P4: 1_Crown of Slumber.docx | Q4: Crowns of the Fae | R4: =IF(E4=H4,"Don't Proceed","Proceed")
A5: Fated To Royalty | B5: Roxie Ray | C5: Werewolf / Shifter Romance | D5: https://www.goodreads.com/series/353917-fated-to-royalty | E5: 15100 | F5: 3.92 | G5: 3 | H5: 1285 | I5: Special Fiction Books | J5: Self-Represented / N/A | K5: Indie / Self-Published | L5: Noel Regis | M5: 46288 | N5: Noel Regis | P5: 1_The Alpha's Fated Encounter.docx | Q5: Fated to Royalty | R5: =IF(E5=H5,"Don't Proceed","Proceed")
A6: Kushiel's Legacy: Moirin Trilogy | B6: Jacqueline Carey | C6: High Fantasy Court Adventure | D6: https://www.goodreads.com/series/54528-naamah-trilogy | E6: 15032 | F6: 4.14 | G6: 3 | H6: 1831 | I6: Indie / Self-Published | J6: New Keywords - Amazon | L6: Noel Regis | M6: 46288 | N6: Noel Regis | P6: 1_Naamah's Kiss.docx | Q6: Naamah Trilogy by Jacqueline Carey | R6: =IF(E6=H6,"Don't Proceed","Proceed")
A7: Nevermore Bookshop Mysteries | B7: Steffanie Holmes | C7: Urban Fantasy Romance | D7: https://www.goodreads.com/series/256558-nevermore-bookshop-mysteries | E7: 14933 | F7: 3.9 | G7: 10 | H7: 2770 | I7: ) Format: Audible Audiobook | J7: New Keywords - Amazon | L7: Noel Regis | M7: 46288 | N7: Noel Regis | P7: 1_A Dead and Stormy Night.docx | Q7: Nevermore Bookshop Mysteries | R7: =IF(E7=H7,"Don't Proceed","Proceed")
A8: Blood and Salt | B8: Alexis Calder | C8: Werewolf / Shifter Romance | D8: https://www.goodreads.com/series/371023-blood-and-salt | E8: 14812 | F8: 3.96 | G8: 4 | H8: 1298 | I8: Illaria Publishing | J8: Self-Represented / N/A | K8: Indie / Self-Published | L8: Noel Regis | M8: 46288 | N8: Noel Regis | P8: 1_Kingdom of Blood and Salt.docx | Q8: Blood and Salt | R8: =IF(E8=H8,"Don't Proceed","Proceed")
A9: Monstrous Matches (7 books) | B9: Lillian Lark | C9: Monster Romance ( Non-Shifter ) | D9: https://www.goodreads.com/series/327677-monstrous-matches | E9: 14695 | F9: 3.91 | G9: 5 | H9: 1897 | I9: ), Nadia Day (Narrator) Format: Audible Audiobook | J9: New Keywords - Amazon | L9: Noel Regis | M9: 46288 | N9: Noel Regis | P9: 1_Stalked by the Kraken.docx | Q9: Monstrous Matches | R9: =IF(E9=H9,"Don't Proceed","Proceed")
A10: Fortuna Sworn | B10: Dominique Kristine | C10: High Fantasy Court Adventure | D10: https://www.goodreads.com/series/265782-fortuna-sworn | E10: 14692 | F10: 3.56 | G10: 6 | H10: 2776 | I10: Indie / Self-Published | J10: New Keywords - Amazon | L10: Noel Regis | M10: 46288 | P10: 1_Fortuna Sworn.docx | Q10: Fortuna Sworn | R10: =IF(E10=H10,"Don't Proceed","Proceed")
A11: Big Bad Wolf | B11: Charlie Adhara | C11: Werewolf / Shifter Romance | D11: https://www.goodreads.com/series/226484-big-bad-wolf | E11: 14475 | F11: 4.16 | G11: 5 | H11: 1435 | I11: Indie / Self-Published | J11: Self-Represented / N/A | K11: Audible Studios | L11: Noel Regis | M11: 46288 | P11: 1_The_Wolf_at_the_Door_-_Charlie_Adhara.docx | Q11: Big Bad Wolf | R11: =IF(E11=H11,"Don't Proceed","Proceed")
A12: The Vampire Journals | B12: Ellie Sanders | C12: Monster Romance (Non-Shifter) | D12: https://www.goodreads.com/series/74078-the-vampire-journals | E12: 14465 | F12: 3.37 | G12: 14 | H12: 2931 | I12: Indie / Self-Published | J12: Noah Lukeman | L12: Noel Regis | M12: 46288 | P12: 1_Turned.docx | Q12: The Vampire Journals | R12: =IF(E12=H12,"Don't Proceed","Proceed")
A13: Vampire Royals | B13: Leigh Walker | C13: Romantasy | D13: https://www.goodreads.com/series/227175-vampire-royals | E13: 14403 | F13: 3.95 | G13: 9 | H13: 3579 | I13: Indie / Self-Published | J13: New Keywords - Amazon | L13: Noel Regis | M13: 46288 | P13: 1_The Pageant.docx | Q13: Vampire Royals | R13: =IF(E13=H13,"Don't Proceed","Proceed")
A14: Magiford Supernatural City | B14: by K. M. Shea | C14: Urban Fantasy Romance | D14: https://www.goodreads.com/series/285840-hall-of-blood-and-mercy | E14: 14287 | F14: 4.3 | G14: 10 | H14: 1806 | I14: Amazon.com Services LLC Items included | J14: New Keywords - Amazon | L14: Noel Regis | M14: 46288 | P14: 1_Magic Forged.docx | Q14: Hall of Blood and Mercy | R14: =IF(E14=H14,"Don't Proceed","Proceed")
A15: The Other Witch | B15: Heather G. Harris | C15: Paranormal Romance ( Done ) | D15: https://www.goodreads.com/series/371745-the-other-witch | E15: 14271 | F15: 4.12 | G15: 4 | H15: 1372 | I15: Hellhound Press Limited | J15: New Keywords - Amazon | L15: Noel Regis | M15: 46288 | P15: 1_Hex of the Witch.docx | Q15: The Other Witch | R15: =IF(E15=H15,"Don't Proceed","Proceed")
A16: Wide Awake Princess | B16: Annie Lisenby | C16: Mythology, Legend & Fairy Tale Retelling | D16: https://www.goodreads.com/series/81725-wide-awake-princess | E16: 14259 | G16: 7 | H16: 1754 | I16: Indie / Self-Published | J16: Metamorphosis Literary Agency | L16: Noel Regis | M16: 46288 | P16: 1_The Wide-Awake Princess.docx | Q16: Wide-Awake Princess | R16: =IF(E16=H16,"Don't Proceed","Proceed")
A17: The Wide Green World Series | B17: Lois McMaster Bujold | C17: War College / Military Academy | D17: https://www.goodreads.com/series/44414-the-sharing-knife | E17: 13754 | F17: 3.76 | G17: 4 | H17: 1639 | I17: Blackstone Audio, Inc. | J17: New Keywords - Amazon | L17: Noel Regis | M17: 46288 | P17: 1_Beguilement.docx | Q17: The Sharing Knife | R17: =IF(E17=H17,"Don't Proceed","Proceed")
A18: inspired by "Little Red Riding Hood" | B18: Ellie Rhodes | C18: High Fantasy Court Adventure | D18: https://www.goodreads.com/series/411648-a-modern-fairytale | E18: 13551 | F18: 4.17 | G18: 10 | H18: 2222 | I18: Indie / Self-Published | J18: New Keywords - Amazon | L18: Noel Regis | M18: 46288 | P18: 1_The Vixen and the Vet.docx | Q18: A Modern Fairytale | R18: =IF(E18=H18,"Don't Proceed","Proceed")
A19: Partholon | B19: PC Cast | C19: Mythology, Legend & Fairy Tale Retelling | D19: https://www.goodreads.com/series/74221-partholon | E19: 12762 | F19: 4.09 | G19: 5 | H19: 2579 | I19: Indie / Self-Published | J19: Jane Rotrosen Agency | L19: Noel Regis | M19: 46288 | P19: 1_Divine By Mistake.docx | Q19: Partholon | R19: =IF(E19=H19,"Don't Proceed","Proceed")
A20: The Scarred Earth Saga | B20: G.A. Aiken | C20: Werewolf / Shifter Romance | D20: https://www.goodreads.com/series/250353-the-scarred-earth-saga | E20: 12631 | F20: 4.06 | G20: 4 | H20: 1294 | I20: Indie / Self-Published | J20: Kensington Publishers | K20: Indie / Self-Published | L20: Noel Regis | M20: 46288 | P20: 1_The Blacksmith Queen.docx | Q20: The Scarred Earth Saga by G.A. Aiken | R20: =IF(E20=H20,"Don't Proceed","Proceed")
A21: Shattered Crown | B21: Leigh Walker | C21: Subjective | D21: https://www.goodreads.com/series/421835-shattered-crown | E21: 12301 | F21: 3.98 | G21: 3 | H21: 1647 | I21: Indie / Self-Published | J21: New Keywords - Amazon | L21: Noel Regis | M21: 46288 | P21: 1_Smoke and Scar.docx | Q21: Shattered Crown | R21: =IF(E21=H21,"Don't Proceed","Proceed")
A22: Luna & Sol Omegaverse | B22: Emilia Emerson | C22: Gothic Dark Romantasy | D22: https://www.goodreads.com/series/365322-luna-sol-omegaverse | E22: 12138 | F22: 3.81 | G22: 3 | H22: 1806 | I22: Amazon.com Services LLC Customers who viewed this item also viewed A Pack for Winter | J22: New Keywords - Amazon | L22: Noel Regis | M22: 46288 | P22: 1_Forbidden Part One.docx | Q22: Luna & Sol Omegaverse | R22: =IF(E22=H22,"Don't Proceed","Proceed")
A23: Dragon Royals | B23: May Dawson | C23: Hidden Magic Romance | D23: https://www.goodreads.com/series/328146-dragon-royals | E23: 12091 | F23: 4.13 | G23: 5 | H23: 2280 | I23: ) Format: Audible Audiobook | J23: New Keywords - Amazon | L23: Noel Regis | M23: 46288 | P23: 1_Forbidden Honor.docx | Q23: Dragon Royals | R23: =IF(E23=H23,"Don't Proceed","Proceed")
A24: Tales From the Blood Coven | B24: Mari Mancusi | C24: Urban Coven Romance | D24: https://www.goodreads.com/series/40688-blood-coven-vampire | E24: 11954 | F24: 3.67 | G24: 8 | H24: 2082 | I24: CreateSpace Independent Publishing Platform | J24: New Keywords - Amazon | L24: Noel Regis | M24: 46288 | P24: 1_Boys That Bite.docx | Q24: Blood Coven Vampire | R24: =IF(E24=H24,"Don't Proceed","Proceed")
A25: The Althea Rose series | B25: Gena Showalter | C25: High Fantasy Court Adventure | D25: https://www.goodreads.com/series/163364-althea-rose-mystery | E25: 11809 | F25: 4.19 | G25: 9 | H25: 2451 | I25: Indie / Self-Published | J25: New Keywords - Amazon | L25: Noel Regis | M25: 46288 | P25: 1_One Tequila.docx | Q25: Althea Rose Mystery | R25: =IF(E25=H25,"Don't Proceed","Proceed")
A26: Kingdom of Runes | B26: Debbie Cassidy | C26: High Fantasy Court Adventure | D26: https://www.goodreads.com/series/259801-kingdom-of-runes | E26: 11722 | F26: 3.84 | G26: 5 | H26: 1861 | I26: Indie / Self-Published | J26: New Keywords - Amazon | L26: Noel Regis | M26: 46288 | P26: 1_Oath Taker.docx | Q26: Kingdom of Runes | R26: =IF(E26=H26,"Don't Proceed","Proceed")
A27: Elemental Masters | B27: Sarah White | C27: Mythology, Legend & Fairy Tale Retelling | D27: https://www.goodreads.com/series/40363-elemental-masters | E27: 11496 | F27: 4.04 | G27: 20 | H27: 6647 | I27: Indie / Self-Published | J27: Metamorphosis Literary Agency | L27: Noel Regis | M27: 46288 | P27: 1_The Serpent's Shadow.docx | Q27: Elemental Masters | R27: =IF(E27=H27,"Don't Proceed","Proceed")
A28: The Draga Court Series | B28: Emma Dean | C28: Romantasy | D28: https://www.goodreads.com/series/219016-draga-court | E28: 11496 | F28: 4.03 | G28: 6 | H28: 2153 | I28: Indie / Self-Published | J28: New Keywords - Amazon | L28: Noel Regis | M28: 46288 | P28: 1_Princess of Draga.docx | Q28: Draga Court | R28: =IF(E28=H28,"Don't Proceed","Proceed")
A29: Enchanted Legacies | B29: Kate King | C29: Werewolf / Shifter Romance | D29: https://www.goodreads.com/series/407429-enchanted-legacies | E29: 11260 | F29: 4.02 | G29: 4 | H29: 1506 | I29: Indie / Self-Published | J29: JABberwocky Literary | K29: Indie / Self-Published | L29: Noel Regis | M29: 46288 | P29: 1_A Thorn in Every Heart.docx | Q29: Enchanted Legacies | R29: =IF(E29=H29,"Don't Proceed","Proceed")
A30: The Thirteenth Sign | B30: Debbie Cassidy | C30: Paranormal Romance ( Done ) | D30: https://www.goodreads.com/series/297415-the-thirteenth-sign | E30: 11110 | F30: 4.18 | G30: 5 | H30: 1735 | I30: ) Format: Audible Audiobook | J30: New Keywords - Amazon | L30: Noel Regis | M30: 46288 | P30: 1_Witch Unexpected.docx | Q30: The Thirteenth Sign | R30: =IF(E30=H30,"Don't Proceed","Proceed")
A31: Fairy Tales Reimagined | B31: Laura Burton | C31: Mythology, Legend & Fairy Tale Retelling | D31: https://www.goodreads.com/series/317488-fairy-tales-reimagined | E31: 11052 | F31: 3.59 | G31: 8 | H31: 2377 | I31: Indie / Self-Published | J31: New Keywords - Amazon | L31: Noel Regis | M31: 46288 | P31: 1_Queen of Snow.docx | Q31: Fairy Tales Reimagined | R31: =IF(E31=H31,"Don't Proceed","Proceed")
A32: My Little Monster | B32: Robico | C32: Monster Romance ( Non-Shifter ) | D32: https://www.goodreads.com/series/88366-tonari-no-kaibutsu-kun | E32: 10917 | F32: 4.18 | G32: 13 | H32: 2249 | I32: Kodansha Comics | J32: New Keywords - Amazon | L32: Noel Regis | M32: 46288 | N32: Sakshi Saxena | O32: 46282 | P32: Korean | R32: =IF(E32=H32,"Don't Proceed","Proceed")
A33: Fairytales of Folkshore | B33: Lucy Tempest | C33: Urban / Contemporary Fantasy Romance | D33: https://www.goodreads.com/series/279139-fairytales-of-folkshore | E33: 10906 | F33: 4.15 | G33: 8 | H33: 2756 | I33: Indie / Self-Published | J33: New Keywords - Amazon | L33: Noel Regis | M33: 46288 | P33: 1_Thief of Cahraman.docx | Q33: Fairytales of Folkshore | R33: =IF(E33=H33,"Don't Proceed","Proceed")
A34: The Freckled Fate | B34: Tetyana Walker | C34: Gothic Dark Romantasy | D34: https://www.goodreads.com/series/391995-the-freckled-fate | E34: 10662 | F34: 3.89 | G34: 3 | H34: 1355 | I34: Bakumovka Publishing Company | J34: Self-Represented / N/A | K34: Indie / Self-Published | L34: Noel Regis | M34: 46288 | P34: 1_A Broken Promise.docx | Q34: The Freckled Fate | R34: =IF(E34=H34,"Don't Proceed","Proceed")
A35: Dark God: Reaper Academy: The Complete Duet | B35: Meg Xuemei X | C35: War College / Military Academy | D35: https://www.goodreads.com/series/336943-monsters-after-dark | E35: 10645 | F35: 4.13 | G35: 3 | H35: 1481 | I35: House of Shades and Fantasy | J35: Self-Represented / N/A | K35: Tantor Media | L35: Noel Regis | M35: 46288 | P35: 1_Shifter God.docx | Q35: Monsters After Dark | R35: =IF(E35=H35,"Don't Proceed","Proceed")
A36: Dark Seasons: Foolish Kingdoms | B36: Rektok Ross | C36: High Fantasy Court Adventure | D36: https://www.goodreads.com/series/204171-foolish-kingdoms | E36: 10619 | F36: 3.8 | G36: 6 | H36: 2534 | I36: Indie / Self-Published | J36: New Keywords - Amazon | L36: Noel Regis | M36: 46288 | P36: 1_Trick.docx | Q36: Foolish Kingdoms | R36: =IF(E36=H36,"Don't Proceed","Proceed")
A37: Biker Witches | B37: Angie Fox | C37: Urban Coven Romance | D37: https://www.goodreads.com/series/45692-demon-slayer | E37: 10457 | F37: 3.67 | G37: 8 | H37: 2239 | I37: ), Tavia Gilbert (Narrator) Format: Audible Audiobook | J37: New Keywords - Amazon | L37: Noel Regis | M37: 46288 | P37: 1_The Accidental Demon Slayer.docx | Q37: Demon Slayer | R37: =IF(E37=H37,"Don't Proceed","Proceed")
A38: Evermore Academy | B38: Audrey Grey | C38: War College / Military Academy | D38: https://www.goodreads.com/series/273634-evermore-academy | E38: 10262 | F38: 4.11 | G38: 3 | H38: 1286 | I38: Indie / Self-Published | J38: Self-Represented / N/A | K38: Audible Studios | L38: Noel Regis | M38: 46288 | P38: 1_Winter.docx | Q38: Evermore Academy | R38: =IF(E38=H38,"Don't Proceed","Proceed")
A39: Knights of Black Swan | B39: Victoria Danann | C39: Subjective | D39: https://www.goodreads.com/series/97847-knights-of-black-swan | E39: 10124 | F39: 3.94 | G39: 13 | H39: 4757 | I39: Indie / Self-Published | J39: New Keywords - Amazon | L39: Noel Regis | M39: 46288 | P39: 1_My Familiar Stranger.docx | Q39: Knights of Black Swan | R39: =IF(E39=H39,"Don't Proceed","Proceed")
A40: Supernatural Institute | B40: Krista Street | C40: Werewolf / Shifter Romance | D40: https://www.goodreads.com/series/304265-supernatural-institute | E40: 10063 | F40: 4.1 | G40: 4 | H40: 1340 | I40: Midnight Press | J40: Self-Represented / N/A | K40: Indie / Self-Published | L40: Noel Regis | M40: 46288 | P40: 1_Fated by Starlight.docx | Q40: Supernatural Institute | R40: =IF(E40=H40,"Don't Proceed","Proceed")
A41: Rosie O'Grady's Paranormal Bar and Grill | B41: BR Kingsolver | C41: Werewolf / Shifter Romance | D41: https://www.goodreads.com/series/263601-rosie-o-grady-s-paranormal-bar-and-grill | E41: 9979 | F41: 4.14 | G41: 5 | H41: 1320 | I41: Indie / Self-Published | J41: Self-Represented / N/A | K41: Tantor Media | L41: Noel Regis | M41: 46288 | P41: 1_Shadow Hunter.docx | Q41: Rosie O'Grady's Paranormal Bar and Grill | R41: =IF(E41=H41,"Don't Proceed","Proceed")
A42: PNR Series Boxed Sets | B42: Nadia Heaton | C42: Paranormal Romance ( Done ) | D42: https://www.goodreads.com/series/271883-flames-of-the-sea | E42: 9957 | F42: 4.4 | G42: 6 | H42: 1908 | I42: Amazon.com Services LLC Customers who viewed this item also viewed Wolf Pack Special Ops Elite Complete Series | J42: New Keywords - Amazon | L42: Noel Regis | M42: 46288 | P42: 1_Destined To Drown.docx | Q42: Flames of The Sea | R42: =IF(E42=H42,"Don't Proceed","Proceed")
A43: Vampire Towers | B43: Kelly St. Clare | C43: War College / Military Academy | D43: https://www.goodreads.com/series/275575-supernatural-battle-vampire-towers | E43: 9835 | F43: 4.19 | G43: 3 | H43: 1282 | I43: Indie / Self-Published | J43: Self-Represented / N/A | K43: Podium Audio | L43: Noel Regis | M43: 46288 | P43: 1_Blood Trial.docx | Q43: Supernatural Battle Vampire Towers | R43: =IF(E43=H43,"Don't Proceed","Proceed")
A44: Royal House of Shadows | B44: Gena Showalter | C44: High Fantasy Court Adventure | D44: https://www.goodreads.com/series/58249-royal-house-of-shadows | E44: 9631 | F44: 3.93 | G44: 5 | H44: 1604 | I44: Indie / Self-Published | J44: New Keywords - Amazon | L44: Noel Regis | M44: 46288 | P44: 1_Lord of the Vampires.docx | Q44: Royal House of Shadows | R44: =IF(E44=H44,"Don't Proceed","Proceed")
A45: Healer's Journey | B45: Annabelle Hawthorne | C45: Romantasy | D45: https://www.goodreads.com/series/434358-healer-s-journey | E45: 9631 | F45: 4.06 | G45: 3 | H45: 1615 | I45: Royal Guard Publishing LLC | J45: New Keywords - Amazon | L45: Noel Regis | M45: 46288 | P45: 1_Healer's Journey.docx | Q45: Healer's Journey | R45: =IF(E45=H45,"Don't Proceed","Proceed")
A46: Jacky Leon | B46: K.N. Banet | C46: High Fantasy Court Adventure | D46: https://www.goodreads.com/series/262274-jacky-leon | E46: 9580 | F46: 4.18 | G46: 12 | H46: 4215 | I46: Indie / Self-Published | J46: New Keywords - Amazon | L46: Noel Regis | M46: 46288 | P46: 1_Oath Sworn.docx | Q46: Jacky Leon | R46: =IF(E46=H46,"Don't Proceed","Proceed")
A47: Claimed by the Rival Alpha | B47: Lindsey Devin | C47: Werewolf / Shifter Romance | D47: https://www.goodreads.com/series/361153-mated-to-the-night | E47: 9450 | F47: 4.02 | G47: 3 | H47: 1290 | I47: Special Fiction Books | J47: Self-Represented / N/A | K47: Indie / Self-Published | L47: Noel Regis | M47: 46288 | P47: 1_Outside the Pack.docx | Q47: Mated to the Night | R47: =IF(E47=H47,"Don't Proceed","Proceed")
A48: The Atlantis Grail | B48: Vanessa Rasanen | C48: High Fantasy Court Adventure | D48: https://www.goodreads.com/series/143534-the-atlantis-grail | E48: 9415 | F48: 4.15 | G48: 4 | H48: 3573 | I48: Indie / Self-Published | J48: Metamorphosis Literary Agency | L48: Noel Regis | M48: 46288 | P48: 1_Qualify.docx | Q48: The Atlantis Grail | R48: =IF(E48=H48,"Don't Proceed","Proceed")
A49: Silvercrest Academy | B49: KC Kean | C49: Paranormal Romance | D49: https://www.goodreads.com/series/380956-silvercrest-academy | E49: 9364 | F49: 4.11 | G49: 4 | H49: 1934 | I49: Indie / Self-Published | J49: Self-Represented / N/A | L49: Noel Regis | M49: 46288 | P49: 1_Falling Shadows.docx | Q49: Silvercrest Academy | R49: =IF(E49=H49,"Don't Proceed","Proceed")
A50: Sins of the Zodiac Book 1 of 4: Sins of the Zodiac | B50: by Deanna Chase | C50: Paranormal Romance ( Done ) | D50: https://www.goodreads.com/series/246923-witches-of-keating-hollow | E50: 9355 | F50: 4.23 | G50: 19 | H50: 4371 | I50: Amazon.com Services LLC Additional items, like pre-orders, may be ordered individually Items included | J50: New Keywords - Amazon | L50: Noel Regis | M50: 46288 | P50: 1_Soul of the Witch.docx | Q50: Witches of Keating Hollow | R50: =IF(E50=H50,"Don't Proceed","Proceed")
A51: A Trial of Sorcerers | B51: Elise Kova | C51: Romance | D51: https://www.goodreads.com/series/296135-a-trial-of-sorcerers | E51: 9349 | F51: 4.07 | G51: 5 | H51: 1897 | I51: Indie / Self-Published | J51: The Bent Agency (Direct) | L51: Noel Regis | M51: 46288 | P51: 1_A Trial of Sorcerers.docx | Q51: A Trial of Sorcerers | R51: =IF(E51=H51,"Don't Proceed","Proceed")
A52: Supernatural Prison | B52: Jaymin Eve | C52: War College / Military Academy | D52: https://www.goodreads.com/series/184120-supernatural-prison-story | E52: 9205 | F52: 4.33 | G52: 4 | H52: 1261 | I52: Indie / Self-Published | J52: Self-Represented / N/A | K52: Audible Studios | L52: Noel Regis | M52: 46288 | P52: 1_Broken Compass.docx | Q52: Supernatural Prison Story | R52: =IF(E52=H52,"Don't Proceed","Proceed")
A53: Shadow Guild: The Rebel | B53: Linsey Hall | C53: Urban / Contemporary Fantasy Romance | D53: https://www.goodreads.com/series/288427-shadow-guild-the-rebel | E53: 9155 | F53: 4 | G53: 5 | H53: 1348 | I53: Bonnie Doon Press | J53: Self-Represented / N/A | K53: Indie / Self-Published | L53: Noel Regis | M53: 46288 | P53: 1_Once Bitten.docx | Q53: Shadow Guild The Rebel | R53: =IF(E53=H53,"Don't Proceed","Proceed")
A54: The Four Kingdoms Box Set | B54: Melanie Cellier | C54: Mythology, Legend & Fairy Tale Retelling | D54: https://www.goodreads.com/series/173630-the-four-kingdoms | E54: 9125 | F54: 4.13 | G54: 5 | H54: 1276 | I54: Indie / Self-Published | J54: Self-Represented / N/A | K54: Indie / Self-Published | L54: Noel Regis | M54: 46288 | P54: 1_The Princess Companion A Retelling of The Princess and the Pea.docx | Q54: The Four Kingdoms | R54: =IF(E54=H54,"Don't Proceed","Proceed")
A55: Fae von Wald und Wildnis | B55: Krista Street | C55: High Fantasy Court Adventure | D55: https://www.goodreads.com/series/407981-fae-of-woodlands-wild | E55: 9046 | F55: 4.19 | G55: 3 | H55: 1302 | I55: Midnight Press | J55: Self-Represented / N/A | K55: Indie / Self-Published | L55: Noel Regis | M55: 46288 | P55: 1_Kingdom of Faewood.docx | Q55: Fae of Woodlands & Wild | R55: =IF(E55=H55,"Don't Proceed","Proceed")
A56: The Other Realm | B56: Heather Morris | C56: High Fantasy Court Adventure | D56: https://www.goodreads.com/series/328321-the-other-realm | E56: 8960 | F56: 4.27 | G56: 7 | H56: 2077 | I56: Hellhound Press Limited | J56: Metamorphosis Literary Agency | L56: Noel Regis | M56: 46288 | P56: 1_Glimmer of the Other.docx | Q56: The Other Realm | R56: =IF(E56=H56,"Don't Proceed","Proceed")
A57: Enchanted Realms | B57: Harper Celebrate | C57: Mythology, Legend & Fairy Tale Retelling | D57: https://www.goodreads.com/series/379329-enchanted-realms | E57: 8918 | F57: 4.02 | G57: 5 | H57: 1613 | I57: Indie / Self-Published | J57: New Keywords - Amazon | L57: Noel Regis | M57: 46288 | P57: 1_Once Upon a Midnight Clear (Michelle Miles).docx | Q57: Enchanted Realms | R57: =IF(E57=H57,"Don't Proceed","Proceed")
A58: Flirting with Monsters: The Complete Series - Special Edition | B58: Eva Chase | C58: Werewolf / Shifter Romance | D58: https://www.goodreads.com/series/293678-flirting-with-monsters | E58: 8758 | F58: 3.81 | G58: 4 | H58: 1412 | I58: Ink Spark Press | J58: JABberwocky Literary | K58: Indie / Self-Published | L58: Noel Regis | M58: 46288 | P58: 1_Shadow Thief.docx | Q58: Flirting with Monsters | R58: =IF(E58=H58,"Don't Proceed","Proceed")
A59: The Witches of Scotland - An Urban Fantasy of Magick and Mystery in Modern Scotland | B59: Steven P Aitchison | C59: Urban / Contemporary Fantasy Romance | D59: https://www.goodreads.com/series/373050-the-dream-dancers-akashic-chronicles | E59: 8563 | F59: 3.92 | G59: 8 | H59: 1476 | I59: CYT Media LTD. | J59: Self-Represented / N/A | K59: Indie / Self-Published | L59: Noel Regis | M59: 46288 | P59: 1_The Witches of Scotland.docx | Q59: The Dream Dancers Akashic Chronicles | R59: =IF(E59=H59,"Don't Proceed","Proceed")
A60: Autopsy Of A Fairytale | B60: Wendy Million | C60: Paranormal Romance | D60: https://www.goodreads.com/series/383383-autopsy-of-a-fairytale | E60: 8550 | F60: 3.78 | G60: 7 | H60: 2014 | I60: Indie / Self-Published | J60: Metamorphosis Literary Agency | L60: Noel Regis | M60: 46288 | P60: 1_Autopsy of a Fairytale.docx | Q60: Autopsy of a Fairytale | R60: =IF(E60=H60,"Don't Proceed","Proceed")
A61: Academy of Unpredictable Magic | B61: Sadie Moss | C61: War College / Military Academy | D61: https://www.goodreads.com/series/264124-academy-of-unpredictable-magic | E61: 8519 | F61: 3.97 | G61: 6 | H61: 1738 | I61: ), Sarah Puckett (Narrator) Format: Audible Audiobook | J61: New Keywords - Amazon | L61: Noel Regis | M61: 46288 | P61: 1_Spark.docx | Q61: Academy of Unpredictable Magic | R61: =IF(E61=H61,"Don't Proceed","Proceed")
A62: Kingdom Series | B62: Lisa Daniels | C62: High Fantasy Court Adventure | D62: https://www.goodreads.com/series/88804-kingdom | E62: 8255 | F62: 3.78 | G62: 15 | H62: 5499 | I62: Indie / Self-Published | J62: New Keywords - Amazon | L62: Noel Regis | M62: 46288 | P62: 1_Her Mad Hatter.docx | Q62: Kingdom | R62: =IF(E62=H62,"Don't Proceed","Proceed")
A63: Loyal Wolf | B63: Krista Lark | C63: Werewolf / Shifter Romance ( Done ) | D63: https://www.goodreads.com/series/427926-loyal-wolf | E63: 8235 | F63: 4.1 | G63: 5 | H63: 1633 | I63: Amazon.com Services LLC Customers who viewed this item also viewed Claimed by My Fianc | J63: New Keywords - Amazon | L63: Noel Regis | M63: 46288 | P63: 1_Claimed by My Fiancé's Brother.docx | Q63: Loyal Wolf | R63: =IF(E63=H63,"Don't Proceed","Proceed")
A64: Fairy Tale Romance | B64: Kelly McClymer | C64: High Fantasy Court Adventure | D64: https://www.goodreads.com/series/411960-fairy-tale-romance | E64: 7974 | F64: 3.65 | G64: 9 | H64: 3232 | I64: Indie / Self-Published | J64: New Keywords - Amazon | L64: Noel Regis | M64: 46288 | P64: 1_Into the Woods.docx | Q64: Fairy Tale Romance | R64: =IF(E64=H64,"Don't Proceed","Proceed")
A65: Elite Guards | B65: Amelia Hutchkins | C65: Paranormal Romance | D65: https://www.goodreads.com/series/155363-the-elite-guards | E65: 7836 | G65: 3 | H65: 1247 | I65: Indie / Self-Published | J65: Self-Represented / N/A | K65: Indie / Self-Published | L65: Noel Regis | M65: 46288 | P65: 1_A Demon's Dark Embrace.docx | Q65: The Elite Guards | R65: =IF(E65=H65,"Don't Proceed","Proceed")
A66: Elemental Mysteries/World | B66: Elizabeth Hunter | C66: Urban / Contemporary Fantasy Romance | D66: https://www.goodreads.com/series/87198-elemental-world | E66: 7741 | F66: 4.31 | G66: 4 | H66: 1287 | I66: Recurve Press, LLC | J66: Self-Represented / N/A | K66: Indie / Self-Published | L66: Noel Regis | M66: 46288 | P66: 1_Building From Ashes.docx | Q66: Elemental World | R66: =IF(E66=H66,"Don't Proceed","Proceed")
A67: Age of Vampires Book 1 of 7: Age of Vampires | B67: Daniel Kensington | C67: High Fantasy Court Adventure | D67: https://www.goodreads.com/series/284005-dokiri-brides | E67: 7513 | F67: 3.84 | G67: 5 | H67: 1970 | I67: Indie / Self-Published | J67: New Keywords - Amazon | L67: Noel Regis | M67: 46288 | P67: 1_Hollen the Soulless.docx | Q67: Dokiri Brides | R67: =IF(E67=H67,"Don't Proceed","Proceed")
A68: Heir Academy | B68: Kieran Kramer | C68: High Fantasy Court Adventure | D68: https://www.goodreads.com/series/393529-heir-academy | E68: 7511 | F68: 4.2 | G68: 5 | H68: 2658 | I68: Amazon.com Services LLC Items included | J68: Jane Rotrosen Agency | L68: Noel Regis | M68: 46288 | P68: 1_The Kingdom of Ruin.docx | Q68: Heir Academy | R68: =IF(E68=H68,"Don't Proceed","Proceed")
A69: The Twisted Kingdoms | B69: Frost Kay | C69: High Fantasy Court Adventure | D69: https://www.goodreads.com/series/280588-the-twisted-kingdoms | E69: 7255 | F69: 3.98 | G69: 7 | H69: 2012 | I69: Indie / Self-Published | J69: New Keywords - Amazon | L69: Noel Regis | M69: 46288 | P69: 1_The Hunt.docx | Q69: The Twisted Kingdoms | R69: =IF(E69=H69,"Don't Proceed","Proceed")
A70: Hidden Magic: Dragon's Gift: The Huntress Novella | B70: Linsey Hall | C70: Urban / Contemporary Fantasy Romance | D70: https://www.goodreads.com/series/178018-dragon-s-gift-the-huntress | E70: 7231 | F70: 3.99 | G70: 5 | H70: 1276 | I70: Indie / Self-Published | J70: Self-Represented / N/A | K70: Audible Studios | L70: Noel Regis | M70: 46288 | P70: 1_Ancient Magic.docx | Q70: Dragon's Gift The Huntress | R70: =IF(E70=H70,"Don't Proceed","Proceed")
A71: Forsaken | B71: Penelope Barsetti | C71: High Fantasy Court Adventure | D71: https://www.goodreads.com/series/336422-forsaken | E71: 7217 | F71: 4.12 | G71: 3 | H71: 1501 | I71: Indie / Self-Published | J71: Self-Represented / N/A | K71: Indie / Self-Published | L71: Noel Regis | M71: 46288 | P71: 1_The Forsaken King.docx | Q71: Forsaken | R71: =IF(E71=H71,"Don't Proceed","Proceed")
A72: Tales Of A New World | B72: Elisabeth Popolow | C72: Paranormal Romance | D72: https://www.goodreads.com/series/177412-tales-of-a-new-world | E72: 7206 | F72: 4.01 | G72: 4 | H72: 2183 | I72: Indie / Self-Published | J72: Metamorphosis Literary Agency | L72: Noel Regis | M72: 46288 | P72: 1_Moon Chosen.docx | Q72: Tales of a New World | R72: =IF(E72=H72,"Don't Proceed","Proceed")
A73: Tempris | B73: Stephanie Eding | C73: High Fantasy Court Adventure | D73: https://www.goodreads.com/series/263383-tempris | E73: 7189 | F73: 4.25 | G73: 3 | H73: 1981 | I73: ) Format: Audible Audiobook | J73: Metamorphosis Literary Agency | L73: Noel Regis | M73: 46288 | P73: 1_Shardless.docx | Q73: Tempris | R73: =IF(E73=H73,"Don't Proceed","Proceed")
A74: Kings of Bolten | B74: K.G. Reuss | C74: War College / Military Academy | D74: https://www.goodreads.com/series/318948-kings-of-bolten | E74: 7053 | F74: 4.12 | G74: 5 | H74: 2174 | I74: Blue Nose Publishing | J74: New Keywords - Amazon | L74: Noel Regis | M74: 46288 | P74: 1_Dirty Little Secrets.docx | Q74: Kings of Bolten | R74: =IF(E74=H74,"Don't Proceed","Proceed")
A75: Rainshadow | B75: Mike Krentz | C75: Paranormal Romance | D75: https://www.goodreads.com/series/74500-rainshadow | E75: 7026 | F75: 4.1 | G75: 5 | H75: 1667 | I75: Indie / Self-Published | J75: Metamorphosis Literary Agency | L75: Noel Regis | M75: 46288 | P75: 1_The Lost Night.docx | Q75: Rainshadow | R75: =IF(E75=H75,"Don't Proceed","Proceed")
A76: The Legacy Trilogy | B76: Cayla Kluver | C76: High Fantasy Court Adventure | D76: https://www.goodreads.com/series/54760-legacy | E76: 7024 | F76: 3.66 | G76: 3 | H76: 1428 | I76: Indie / Self-Published | J76: Self-Represented / N/A | K76: Indie / Self-Published | L76: Noel Regis | M76: 46288 | P76: 1_Legacy.docx | Q76: Legacy | R76: =IF(E76=H76,"Don't Proceed","Proceed")
A77: Magic Side: Wolf Bound | B77: Veronica Douglas | C77: Werewolf / Shifter Romance | D77: https://www.goodreads.com/series/323939-magic-side-wolf-bound | E77: 6978 | G77: 4 | H77: 1465 | I77: Magic Side Press, LLC | J77: Self-Represented / N/A | K77: Indie / Self-Published | L77: Noel Regis | M77: 46288 | P77: 1_Wolf Marked.docx | Q77: Magic Side Wolf Bound | R77: =IF(E77=H77,"Don't Proceed","Proceed")
A78: The Kraken | B78: Tiffany W. Killoren | C78: Monster Romance (Non-Shifter) | D78: https://www.goodreads.com/series/222835-the-kraken | E78: 6944 | F78: 3.89 | G78: 8 | H78: 2600 | I78: Indie / Self-Published | J78: Metamorphosis Literary Agency | L78: Noel Regis | M78: 46288 | P78: 1_Treasure of the Abyss.docx | Q78: The Kraken | R78: =IF(E78=H78,"Don't Proceed","Proceed")
A79: Dark Fae FBI | B79: C.N. Crawford | C79: Urban / Contemporary Fantasy Romance | D79: https://www.goodreads.com/series/203354-dark-fae-fbi | E79: 6935 | F79: 4.01 | G79: 4 | H79: 1320 | I79: Corey Press | J79: Self-Represented / N/A | K79: Indie / Self-Published | L79: Noel Regis | M79: 46288 | P79: 1_Agent of Enchantment.docx | Q79: Dark Fae FBI | R79: =IF(E79=H79,"Don't Proceed","Proceed")
A80: Pretty Ruthless Monsters | B80: Eva Ashwood | C80: Monster Romance ( Non-Shifter ) | D80: https://www.goodreads.com/series/387808-pretty-ruthless-monsters | E80: 6904 | F80: 4.21 | G80: 4 | H80: 1832 | I80: ), Cassandra Medcalf (Narrator), & 1 more Format: Audible Audiobook | J80: New Keywords - Amazon | L80: Noel Regis | M80: 46288 | P80: 1_Princes of Carnage.docx | Q80: Pretty Ruthless Monsters | R80: =IF(E80=H80,"Don't Proceed","Proceed")
A81: Kait Silver | B81: Laken Cane | C81: Werewolf / Shifter Romance | D81: https://www.goodreads.com/series/325438-kait-silver | E81: 6883 | F81: 4.18 | G81: 5 | H81: 1421 | I81: Indie / Self-Published | J81: Self-Represented / N/A | K81: Audible Studios | L81: Noel Regis | M81: 46288 | P81: 1_Broken Moon.docx | Q81: Kait Silver | R81: =IF(E81=H81,"Don't Proceed","Proceed")
A82: Beyond the Four Kingdoms | B82: Melanie Cellier | C82: High Fantasy Court Adventure | D82: https://www.goodreads.com/series/216158-beyond-the-four-kingdoms | E82: 6871 | F82: 4.21 | G82: 6 | H82: 1978 | I82: Indie / Self-Published | J82: New Keywords - Amazon | L82: Noel Regis | M82: 46288 | P82: 1_A Dance of Silver and Shadow.docx | Q82: Beyond the Four Kingdoms | R82: =IF(E82=H82,"Don't Proceed","Proceed")
A83: Prodigium Academy | B83: Katie May | C83: Monster Romance ( Non-Shifter ) | D83: https://www.goodreads.com/series/274515-prodigium-academy | E83: 6828 | F83: 4.11 | G83: 5 | H83: 1820 | I83: Expresso Publishing | J83: New Keywords - Amazon | L83: Noel Regis | M83: 46288 | P83: 1_Monsters.docx | Q83: Prodigium Academy | R83: =IF(E83=H83,"Don't Proceed","Proceed")
A84: Daughters of Eville | B84: Chanda Hahn | C84: Subjective | D84: https://www.goodreads.com/series/261408-daughters-of-eville | E84: 6827 | F84: 3.9 | G84: 7 | H84: 2130 | I84: Indie / Self-Published | J84: New Keywords - Amazon | L84: Noel Regis | M84: 46288 | P84: 1_Of Beast and Beauty.docx | Q84: Daughters of Eville | R84: =IF(E84=H84,"Don't Proceed","Proceed")
A85: Master Class | B85: Annabelle Hawthorne | C85: High-Stakes Games & Deadly Trials (Done) | D85: https://www.goodreads.com/series/367471-master-class | E85: 6799 | F85: 4.49 | G85: 6 | H85: 2480 | I85: Indie / Self-Published | J85: New Keywords - Amazon | L85: Noel Regis | M85: 46288 | P85: 1_Master Class 1 A Slice of Life Harem LitRPG (Annabelle Hawthorne Virgil Knightley).docx | Q85: Master Class | R85: =IF(E85=H85,"Don't Proceed","Proceed")
A86: Elemental Fae Academy | B86: Lexi C. Foss | C86: War College / Military Academy | D86: https://www.goodreads.com/series/268709-elemental-fae-academy | E86: 6710 | F86: 4.05 | G86: 7 | H86: 1985 | I86: Ninja Newt Publishing, LLC | J86: New Keywords - Amazon | L86: Noel Regis | M86: 46288 | P86: 1_Elemental Fae Academy.docx | Q86: Elemental Fae Academy | R86: =IF(E86=H86,"Don't Proceed","Proceed")
A87: Legends of Abreia | B87: Kenley Davidson | C87: Hidden Magic Romance | D87: https://www.goodreads.com/series/304444-legends-of-abreia | E87: 6708 | F87: 4.11 | G87: 6 | H87: 1997 | I87: ) Format: Audible Audiobook | J87: New Keywords - Amazon | L87: Noel Regis | M87: 46288 | P87: 1_The Faceless Mage.docx | Q87: Legends of Abreia | R87: =IF(E87=H87,"Don't Proceed","Proceed")
A88: Kingdom of Wolves | B88: Amelia Hutchins | C88: Urban Fantasy Romance | D88: https://www.goodreads.com/series/300359-kingdom-of-wolves | E88: 6495 | F88: 3.77 | G88: 13 | H88: 3837 | I88: Amelia Hutchins | J88: New Keywords - Amazon | L88: Noel Regis | M88: 46288 | P88: 1_Wild Moon.docx | Q88: Kingdom of Wolves | R88: =IF(E88=H88,"Don't Proceed","Proceed")
A89: Belador | B89: Sherrilyn Kenyon | C89: Urban Coven Romance | D89: https://www.goodreads.com/series/77782-belador | E89: 6353 | F89: 3.99 | G89: 11 | H89: 4571 | I89: Blackstone Publishing | J89: New Keywords - Amazon | L89: Noel Regis | M89: 46288 | P89: 1_Blood Trinity.docx | Q89: Belador | R89: =IF(E89=H89,"Don't Proceed","Proceed")
A90: The Alliance | B90: S.J. Tilly | C90: High Fantasy Court Adventure | D90: https://www.goodreads.com/series/122042-the-alliance | E90: 6283 | F90: 3.86 | G90: 6 | H90: 1644 | I90: Indie / Self-Published | J90: New Keywords - Amazon | L90: Noel Regis | M90: 46288 | P90: 1_Hunter's Claim.docx | Q90: The Alliance | R90: =IF(E90=H90,"Don't Proceed","Proceed")
A91: The Beast Charmer | B91: Maxym M. Martineau | C91: High Fantasy Court Adventure | D91: https://www.goodreads.com/series/256085-the-beast-charmer | E91: 6212 | F91: 3.94 | G91: 3 | H91: 1334 | I91: Harper Voyager | J91: Self-Represented / N/A | K91: Indie / Self-Published | L91: Noel Regis | M91: 46288 | P91: 1_Kingdom of Exiles.docx | Q91: The Beast Charmer | R91: =IF(E91=H91,"Don't Proceed","Proceed")
A92: The Hidden Saga | B92: Amy Patrick | C92: Hidden Magic Romance | D92: https://www.goodreads.com/series/175466-hidden-saga | E92: 6211 | F92: 3.92 | G92: 10 | H92: 2816 | I92: Oxford South Press | J92: New Keywords - Amazon | L92: Noel Regis | M92: 46288 | P92: 1_Hidden Deep.docx | Q92: Hidden Saga by Amy Patrick | R92: =IF(E92=H92,"Don't Proceed","Proceed")
A93: Ruthless Villains | B93: Marion Blackwood | C93: Korean Romance Fantasy / Isekai | D93: https://www.goodreads.com/series/350968-ruthless-villains | E93: 6179 | F93: 3.53 | G93: 5 | H93: 1632 | I93: Black Dagger Publishing | J93: New Keywords - Amazon | L93: Noel Regis | M93: 46288 | P93: 1_Ruthless Villains.docx | Q93: Ruthless Villains | R93: =IF(E93=H93,"Don't Proceed","Proceed")
A94: Mate Hunt | B94: Margot Hunt | C94: Werewolf / Shifter Romance | D94: https://www.goodreads.com/series/341783-mate-hunt | E94: 6121 | F94: 3.87 | G94: 7 | H94: 1865 | I94: Indie / Self-Published | J94: Jane Rotrosen Agency | L94: Noel Regis | M94: 46288 | P94: 1_Thrown to the Wolves.docx | Q94: Mate Hunt | R94: =IF(E94=H94,"Don't Proceed","Proceed")
A95: Wolfsbane: The Complete Series | B95: by Lola Glass | C95: Werewolf / Shifter Romance | D95: https://www.goodreads.com/series/316345-wolfsbane | E95: 6102 | F95: 3.95 | G95: 5 | H95: 1344 | I95: Indie / Self-Published | J95: Self-Represented / N/A | K95: Indie / Self-Published | L95: Noel Regis | M95: 46288 | P95: 1_Running from the Wolves.docx | Q95: Wolfsbane | R95: =IF(E95=H95,"Don't Proceed","Proceed")
A96: Dark Sword | B96: Donna Grant | C96: Gothic Dark Romantasy | D96: https://www.goodreads.com/series/47066-dark-sword | E96: 5961 | F96: 3.93 | G96: 6 | H96: 1984 | I96: St. Martin's Paperbacks | J96: New Keywords - Amazon | L96: Noel Regis | M96: 46288 | P96: 1_Dangerous Highlander.docx | Q96: Dark Sword | R96: =IF(E96=H96,"Don't Proceed","Proceed")
A97: For the Love of Aliens | B97: J.R. Ward | C97: Subjective | D97: https://www.goodreads.com/series/380196-for-the-love-of-aliens | E97: 5959 | F97: 4.1 | G97: 3 | H97: 1641 | I97: Indie / Self-Published | J97: New Keywords - Amazon | L97: Noel Regis | M97: 46288 | P97: 1_Pheromone_-_CM_Stunich.docx | Q97: For the Love of Aliens | R97: =IF(E97=H97,"Don't Proceed","Proceed")
A98: The Fada Shapeshifter Series | B98: Kenley Davidson | C98: High Fantasy Court Adventure | D98: https://www.goodreads.com/series/162254-fada-shapeshifters | E98: 5889 | F98: 4.1 | G98: 6 | H98: 2141 | I98: Indie / Self-Published | J98: New Keywords - Amazon | L98: Noel Regis | M98: 46288 | P98: 1_Seducing the Sun Fae.docx | Q98: Fada Shapeshifters | R98: =IF(E98=H98,"Don't Proceed","Proceed")
A99: The Alice Worth Series | B99: Lisa Edmonds | C99: Urban Fantasy Romance | D99: https://www.goodreads.com/series/211872-alice-worth | E99: 5882 | F99: 4.15 | G99: 9 | H99: 4018 | I99: The Storybook House, LLC | J99: New Keywords - Amazon | L99: Noel Regis | M99: 46288 | P99: 1_Heart of Malice.docx | Q99: Alice Worth | R99: =IF(E99=H99,"Don't Proceed","Proceed")
A100: Fortune Academy | B100: by J.R. Thorn | C100: War College / Military Academy | D100: https://www.goodreads.com/series/269426-fortune-academy | E100: 5812 | F100: 3.89 | G100: 10 | H100: 2104 | I100: Indie / Self-Published | J100: New Keywords - Amazon | L100: Noel Regis | M100: 46288 | P100: 1_Fortune Academy Year One.docx | Q100: Fortune Academy | R100: =IF(E100=H100,"Don't Proceed","Proceed")
...

Sheet All Platform Matches
A1: Research Row ID | B1: Source Series Title | C1: Source Author | D1: Platform Name | E1: Candidate Fiction Title | F1: Candidate Author | G1: Platform URL | H1: Match Type | I1: Earliest Chapter Date | J1: Chapter Count / Status | K1: Platform Performance / Traction Metrics | L1: Web Pre-Dates Commercial? | M1: Evidence Notes
A2: RB-0007 | B2: Summer Court | C2: Gena Showalter | D2: Royal Road | E2: Summer | F2: Aurora808 | G2: https://www.royalroad.com/fiction/157220/summer | H2: Unrelated Same Title | I2: 2026-03-13T23:37:49.0000000+00:00 | J2: 9 | K2: 1 Followers | 1,057 Views | 9 Chapters | 43 Pages | L2: UNVERIFIED | M2: She is beautiful, sexy, alluring. But when she gets you in her deadly clutches she destroys you!When Lucas meets his best friend’s new wife he gets the shock of his life!Psychological thriller. Mature reading only.
A3: RB-0008 | B3: Fire And Fang | C3: Lindsay Flanagan | D3: Royal Road | E3: Fur and Fang | F3: Lotheringia | G3: https://www.royalroad.com/fiction/20272/fur-and-fang | H3: Unrelated Same Title | I3: 2018-08-29T08:53:38.0000000+00:00 | J3: 2 | K3: 3 Followers | 880 Views | 2 Chapters | 6 Pages | L3: UNVERIFIED | M3: "A fire burns across our land, it ravages villages and tears families apart. A fire burns across our land boy, just look!" A man grabs the face of his son and forces his crying visage to stare at the plumes of smoke which scar the night sky and illuminate it with the dim glow of violence.He tells hi
A4: RB-0009 | B4: The Coven: Elemental Magic | C4: Chandelle LaVaun | D4: Royal Road | E4: The Coven | F4: fcaulfield | G4: https://www.royalroad.com/fiction/54363/the-coven | H4: Unrelated Same Title | I4: 2022-05-14T10:50:35.0000000+00:00 | J4: 1 | K4: 1 Followers | 225 Views | 1 Chapters | 10 Pages | L4: UNVERIFIED | M4: Lillia has always wanted to become a mage and she is accepted into a magic school: Norvale's All-Girl Academy for Young Mages. However, there is one big problem - Lillia isn't very good at magic. As she begins to feel her dreams slip away, an older student gives her a powerful magical amulet and inv
A5: RB-0009 | B5: The Coven: Elemental Magic | C5: Chandelle LaVaun | D5: Royal Road | E5: THE COVEN | F5: june_calva81 | G5: https://www.royalroad.com/fiction/86564/the-coven | H5: Unrelated Same Title | I5: 2024-05-14T18:01:50.0000000+00:00 | J5: 73 | K5: 55 Followers | 17,393 Views | 73 Chapters | 363 Pages | L5: UNVERIFIED | M5: Get ready to be spellbound by the enchanting tale of Maya, a seemingly ordinary teenager whose life is about to take a dramatic turn. In the sleepy town of Harvest Grove, secrets lurk beneath the surface, waiting to be uncovered. And for Maya, the discovery of her own hidden heritage is only the beg
A6: RB-0010 | B6: Shatter Me | C6: Tahereh Mafi | D6: Royal Road | E6: Shatter Me and Love The Pieces [GL] | F6: LunarLexie | G6: https://www.royalroad.com/fiction/108922/shatter-me-and-love-the-pieces-gl | H6: Unrelated Same Title | I6: 2025-03-15T12:57:49.0000000+00:00 | J6: 12 | K6: 4 Followers | 1,699 Views | 12 Chapters | 89 Pages | L6: UNVERIFIED | M6: Shiori Sei is an easy going girl and a little Miss Perfect when it comes to school life. She's got the looks, the grades and the friends. But is the loveable fluffy girl all that she seems? In a moment of weakness she lets her facade slip and does something completely unbecoming of her, what's wors
A7: RB-0010 | B7: Shatter Me | C7: Tahereh Mafi | D7: Royal Road | E7: SHATTER | F7: Pineapple401 | G7: https://www.royalroad.com/fiction/156597/shatter | H7: Unrelated Same Title | I7: 2026-03-10T16:16:01.0000000+00:00 | J7: 7 | K7: 0 Followers | 480 Views | 7 Chapters | 32 Pages | L7: UNVERIFIED | M7: (This is not emo trust me, it sounds emo but again believe me its light hearted... mostly)In the nation of Caldenmere, trauma unlocks power. The Accord calls them Shatter abilities — crystalline fractures in the soul that manifest as something unique to the person who survived them. When objects are
A8: RB-0012 | B8: The Inheritance Games | C8: Angela Crocker | D8: Royal Road | E8: Inheritance | F8: AussieMark | G8: https://www.royalroad.com/fiction/15101/inheritance | H8: Unrelated Same Title | I8: 2017-11-17T21:21:41.0000000+00:00 | J8: 8 | K8: 74 Followers | 12,502 Views | 8 Chapters | 38 Pages | L8: UNVERIFIED | M8: William, an orphan, suddenly discovers he had a rich grandfather who left half his fortune to him. However, his seemingly kind step-grandmother turns out to be the one who caused the death of his parents and grandfather, and she doesn't want to share. After being poisoned, he awakes to find himself
A9: RB-0012 | B9: The Inheritance Games | C9: Angela Crocker | D9: Royal Road | E9: Inheritance of Fate | F9: Vera Markus | G9: https://www.royalroad.com/fiction/106117/inheritance-of-fate | H9: Unrelated Same Title | I9: 2025-02-15T14:28:48.0000000+00:00 | J9: 64 | K9: 40 Followers | 14,826 Views | 64 Chapters | 861 Pages | L9: UNVERIFIED | M9: Born into a world where rifts have appeared across the Earth, Sadie Whittaker discovers that humanity has a place in a much wider galaxy. Drawn into a forgotten war being fought across countless worlds, she inherits powers she barely understands while secrets others have spent millennia protecting s
A10: RB-0013 | B10: Tiffany Black Mysteries | C10: Tiffany W. Killoren | D10: Royal Road | E10: Tiffany | F10: TalesOfWonder | G10: https://www.royalroad.com/fiction/31794/tiffany | H10: Unrelated Same Title | I10: 2020-04-18T09:52:28.0000000+00:00 | J10: 64 | K10: 8 Followers | 25,513 Views | 64 Chapters | 302 Pages | L10: UNVERIFIED | M10: Some demons yawn at human affairs and others are outright mischievous.And then there’s Tiffany.Out of goodness or maybe just when her interest is piqued, she occasionally interferes in the fate of some poor soul. She usually shows up as a dark-haired woman in her middle 30s. Her eyes are black and
A11: RB-0015 | B11: Fae & Alchemy | C11: Callie Hart | D11: Royal Road | E11: Fae | F11: enby_me | G11: https://www.royalroad.com/fiction/43526/fae | H11: Unrelated Same Title | I11: 2021-05-27T23:19:08.0000000+00:00 | J11: 15 | K11: 52 Followers | 16,937 Views | 15 Chapters | 32 Pages | L11: UNVERIFIED | M11: A human is reincarnated as a caterpillar and the world tilts a little to the left.Posted simultaneously on Scribblehub under the same name and username.Cover picture kindly provided by gej302.
A12: RB-0015 | B12: Fae & Alchemy | C12: Callie Hart | D12: Royal Road | E12: Fae | F12: enby_me | G12: https://www.royalroad.com/fiction/43526/fae | H12: Unrelated Same Title | I12: 2021-05-27T23:19:08.0000000+00:00 | J12: 15 | K12: 52 Followers | 16,937 Views | 15 Chapters | 32 Pages | L12: UNVERIFIED | M12: A human is reincarnated as a caterpillar and the world tilts a little to the left.Posted simultaneously on Scribblehub under the same name and username.Cover picture kindly provided by gej302.
... A716: RB-1228 | B716: The Moonlit Fae Trilogy | C716: Verse and Bloom | D716: Royal Road | E716: Moonlit Anthology | F716: Wings of Icarus | G716: https://www.royalroad.com/fiction/78023/moonlit-anthology | H716: Unrelated Same Title | I716: 2023-12-06T09:30:24.0000000+00:00 | J716: 16 | K716: 0 Followers | 3,091 Views | 16 Chapters | 5 Pages | L716: UNVERIFIED | M716: A compilation of my Poems & LiteratureDark, Whimsical & Comical

Sheet Web-Fiction Shortlist
A1: Research Row ID | B1: Original Series Title | C1: GR Links | D1: Author | E1: Origin Platform | F1: Web Fiction Title | G1: Original Author / Pen Name | H1: Original Platform URL | I1: Earliest Web Date | J1: Commercial Pub Date | K1: Web Pre-Dates Commercial? | L1: Confidence Level | M1: Media & Audio Exclusion Screening | N1: Web Traction / Performance Metrics (Rating, Followers, Views) | O1: Commercial Performance Summary (Goodreads) | P1: Verification Evidence / Notes | Q1: Prime Video | R1: Netflix | S1: Audible Audio Availability | T1: Other Platforms (HBO, Peacock, Webtoon, Cinema) | U1: Adaptation Status / Details
